Workbook

Sheet Indicadores
A1: Desenvolvido por Wagner Teixeira - Whatsapp 27 31829481
A3: Curso/Campus: | B3: Engenharia de Controle e Automação - Campus Serra
A5: Inscritos: | B5: =VLOOKUP(VLOOKUP($B$3,Cursos!$A$2:$G$11,2,0),Enade!$I$2:$U$11,6,0) -> 49
A6: Participantes: | B6: =VLOOKUP(VLOOKUP($B$3,Cursos!$A$2:$G$11,2,0),Enade!$I$2:$U$11,7,0) -> 39
A7: Faltosos: | B7: =B5-B6 -> 10
A9: CPC: | B9: =VLOOKUP(VLOOKUP($B$3,Cursos!$A$2:$G$11,2,0),CPC!$I$2:$AL$11,30,0) -> 4 | C9: =VLOOKUP(VLOOKUP($B$3,Cursos!$A$2:$G$11,2,0),CPC!$I$2:$AL$11,29,0) -> 3.419
A10: IDD: | B10: =VLOOKUP(VLOOKUP($B$3,Cursos!$A$2:$G$11,2,0),IDD!$D$2:$O$11,12,0) -> 3 | C10: =VLOOKUP(VLOOKUP($B$3,Cursos!$A$2:$G$11,2,0),IDD!$D$2:$O$11,11,0) -> 2.779
A12: ENADE: | B12: =VLOOKUP(VLOOKUP($B$3,Cursos!$A$2:$G$11,2,0),Enade!$I$2:$U$11,13,0) -> 4 | C12: =VLOOKUP(VLOOKUP($B$3,Cursos!$A$2:$G$11,2,0),Enade!$I$2:$U$11,12,0) -> 3.0833
A13: Nota Bruta - FG | B13: =VLOOKUP(VLOOKUP($B$3,Cursos!$A$2:$G$11,2,0),Enade!$I$2:$U$11,8,0) -> 46.9641
A14: Nota Padronizada - FG | B14: =VLOOKUP(VLOOKUP($B$3,Cursos!$A$2:$G$11,2,0),Enade!$I$2:$U$11,9,0) -> 3.1065
A15: Nota Bruta - CE | B15: =VLOOKUP(VLOOKUP($B$3,Cursos!$A$2:$G$11,2,0),Enade!$I$2:$U$11,10,0) -> 44.1308
A16: Nota Padronizada - CE | B16: =VLOOKUP(VLOOKUP($B$3,Cursos!$A$2:$G$11,2,0),Enade!$I$2:$U$11,11,0) -> 3.0755

Sheet Microdados
A1: Desenvolvido por Wagner Teixeira - Whatsapp 27 31829481
A3: Curso/Campus: | B3: Engenharia Elétrica - Campus Vitória
A5: Dicionário de Variáveis do ENADE 2019
A6: NOME | B6: TIPO | C6: TAM | D6: DESCRIÇÃO | E6: CATEGORIAS
A7: NU_ANO | B7: N | C7: 4 | D7: Ano de realização do exame | E7: 2019
A8: INFORMAÇÕES DA INSTITUIÇÃO DE ENSINO SUPERIOR E DO CURSO
A9: CO_IES | B9: N | C9: 5 | D9: Código da IES (e-MEC) | E9: Entre 1 e 23410 | G9: 1808
A10: CO_CATEGAD | B10: N | C10: 1 | D10: Código da categoria administrativa da IES | E10: 1. Pública Federal | G10: 1
E11: 2. Pública Estadual
E12: 3. Pública Municipal
E13: 4. Privada com fins lucrativos
E14: 5. Privada sem fins lucrativos
E15: 7. Especial
A26: CO_ORGACAD | B26: N | C26: 5 | D26: Código da organização acadêmica da IES | E26: 10019 = Centro Federal de Educação Tecnológica | G26: 10026
E27: 10020 = Centro Universitário
E28: 10022 = Faculdade
E29: 10026 = Instituto Federal de Educação, Ciência e Tecnologia
E30: 10028 = Universidade
A31: CO_GRUPO | B31: N | C31: 4 | D31: Código da Área de enquadramento do curso no Enade | G31: =VLOOKUP($B$3,Cursos!$A$2:$C$11,1,0) -> Engenharia Elétrica - Campus Vitória
E32: 5 = MEDICINA VETERINÁRIA
E33: 6 = ODONTOLOGIA
E34: 12 = MEDICINA
E35: 17 = AGRONOMIA
E36: 19 = FARMÁCIA
E37: 21 = ARQUITETURA E URBANISMO
E38: 23 = ENFERMAGEM
E39: 27 = FONOAUDIOLOGIA
E40: 28 = NUTRIÇÃO
E41: 36 = FISIOTERAPIA
E42: 51 = ZOOTECNIA
E43: 55 = BIOMEDICINA
... E60: 6410 = TECNOLOGIA EM SEGURANÇA NO TRABALHO
A61: CO_CURSO | B61: N | C61: 7 | D61: Código do curso no Enade | E61: Entre 3 e 5001378 | G61: =VLOOKUP(B3,Cursos!$A$2:$B$11,2,0) -> 88399
A62: CO_MODALIDADE | B62: N | C62: 1 | D62: Código da Modalidade de Ensino | E62: 0 = EaD | G62: =VLOOKUP($B$3,Cursos!$A$2:$F$11,6,0) -> 1
E63: 1 = Presencial
A64: CO_MUNIC_CURSO | B64: N | C64: 7 | D64: Código do município de funcionamento do curso | E64: Ir para Planilha MUNICÍPIOS | G64: =VLOOKUP(VLOOKUP($B$3,Cursos!$A$2:$G$11,7,0),MUNICIPIOS!$B$5:$D$5574,2,0) -> VITORIA
A65: CO_UF_CURSO | B65: N | C65: 2 | D65: Código da UF de funcionamento do curso | E65: Conforme código do IBGE | G65: ES
E66: 11 = Rondônia (RO)
E67: 12 = Acre (AC)
E68: 13 = Amazonas (AM)
E69: 14 = Roraima (RR)
E70: 15 = Pará (PA)
E71: 16 = Amapa (AP)
E72: 17 = Tocantins (TO)
E73: 21 = Maranhão (MA)
E74: 22= Piauí (PI)
E75: 23 = Ceará (CE)
E76: 24 = Rio Grande do Norte (RN)
E77: 25 = Paraíba (PB)
... E92: 53 = Distrito federal (DF)
A93: CO_REGIÃO_CURSO | B93: N | C93: 1 | D93: Código da região de funcionamento do curso | E93: 1 = Região Norte (N) | G93: 3
E94: 2 = Região Nordeste (NE)
E95: 3 = Região Sudeste (SE)
E96: 4 = Região Sul (SUL)
E97: 5 = Região Centro-Oeste (CO)
A98: INFORMAÇÕES DO ESTUDANTE
A99: NU_IDADE | B99: N | C99: 2 | D99: Idade do inscrito em 24/11/2019 | E99: valores entre 10 e 86 (Dado procedente da base da Receita Federal) | G99: =SUMIFS(Arq_6!$C$2:$C$368,Arq_6!$B$2:$B$368,$G$61)/COUNTIF(Arq_6!$B$2:$B$368,$G$61) -> 27.06383 | H99: Média
E100: Menor ou igual a 20 | G100: =COUNTIFS(Arq_6!$B$2:$B$368,$G$61,Arq_6!$C$2:$C$368,"<=20") -> 0 | H100: =G100/SUM(G$100:G$105) -> 0
E101: 21 a 25 | G101: =COUNTIFS(Arq_6!$B$2:$B$368,$G$61,Arq_6!$C$2:$C$368,">=21")-COUNTIFS(Arq_6!$B$2:$B$368,$G$61,Arq_6!$C$2:$C$368,">=26") -> 18 | H101: =G101/SUM(G$100:G$105) -> 0.38297872
E102: 26 a 29 | G102: =COUNTIFS(Arq_6!$B$2:$B$368,$G$61,Arq_6!$C$2:$C$368,">=26")-COUNTIFS(Arq_6!$B$2:$B$368,$G$61,Arq_6!$C$2:$C$368,">=30") -> 23 | H102: =G102/SUM(G$100:G$105) -> 0.4893617
E103: 30 a 39 | G103: =COUNTIFS(Arq_6!$B$2:$B$368,$G$61,Arq_6!$C$2:$C$368,">=30")-COUNTIFS(Arq_6!$B$2:$B$368,$G$61,Arq_6!$C$2:$C$368,">=40") -> 4 | H103: =G103/SUM(G$100:G$105) -> 0.085106383
E104: 40 a 49 | G104: =COUNTIFS(Arq_6!$B$2:$B$368,$G$61,Arq_6!$C$2:$C$368,">=40")-COUNTIFS(Arq_6!$B$2:$B$368,$G$61,Arq_6!$C$2:$C$368,">=50") -> 2 | H104: =G104/SUM(G$100:G$105) -> 0.042553191
E105: Maior ou igual a 50 | G105: =COUNTIFS(Arq_6!$B$2:$B$368,$G$61,Arq_6!$C$2:$C$368,">=50") -> 0 | H105: =G105/SUM(G$100:G$105) -> 0
A106: TP_SEXO | B106: C | C106: 1 | D106: Sexo | E106: M = Masculino | G106: =COUNTIFS(Arq_5!$B$2:$B$368,$G$61,Arq_5!$C$2:$C$368,LEFT($E106,1)) -> 37 | H106: =G106/SUM(G$106:G$107) -> 0.78723404
E107: F = Feminino | G107: =COUNTIFS(Arq_5!$B$2:$B$368,$G$61,Arq_5!$C$2:$C$368,LEFT($E107,1)) -> 10 | H107: =G107/SUM(G$106:G$107) -> 0.21276596
A108: ANO_FIM_EM | B108: N | C108: 4 | D108: Ano de conclusão do Ensino Médio | E108: AAAA (valores entre 1014 e 2612), conforme lançado pelo estudante | G108: =SUMIFS(Arq_2!$C$2:$C$368,Arq_2!$B$2:$B$368,$G$61)/COUNTIF(Arq_2!$B$2:$B$368,$G$61) -> 2010 | H108: Média
E109: >= 2015 | G109: =COUNTIFS(Arq_2!$B$2:$B$368,$G$61,Arq_2!$C$2:$C$368,">=2015") -> 0 | H109: =G109/SUM(G$109:G$117) -> 0
E110: 2014 | G110: =COUNTIFS(Arq_2!$B$2:$B$368,$G$61,Arq_2!$C$2:$C$368,LEFT($E110,4)) -> 8 | H110: =G110/SUM(G$109:G$117) -> 0.17021277
E111: 2013 | G111: =COUNTIFS(Arq_2!$B$2:$B$368,$G$61,Arq_2!$C$2:$C$368,LEFT($E111,4)) -> 3 | H111: =G111/SUM(G$109:G$117) -> 0.063829787
E112: 2012 | G112: =COUNTIFS(Arq_2!$B$2:$B$368,$G$61,Arq_2!$C$2:$C$368,LEFT($E112,4)) -> 11 | H112: =G112/SUM(G$109:G$117) -> 0.23404255
E113: 2011 | G113: =COUNTIFS(Arq_2!$B$2:$B$368,$G$61,Arq_2!$C$2:$C$368,LEFT($E113,4)) -> 4 | H113: =G113/SUM(G$109:G$117) -> 0.085106383
E114: 2010 | G114: =COUNTIFS(Arq_2!$B$2:$B$368,$G$61,Arq_2!$C$2:$C$368,LEFT($E114,4)) -> 4 | H114: =G114/SUM(G$109:G$117) -> 0.085106383
E115: 2009 | G115: =COUNTIFS(Arq_2!$B$2:$B$368,$G$61,Arq_2!$C$2:$C$368,LEFT($E115,4)) -> 6 | H115: =G115/SUM(G$109:G$117) -> 0.12765957
E116: 2008 | G116: =COUNTIFS(Arq_2!$B$2:$B$368,$G$61,Arq_2!$C$2:$C$368,LEFT($E116,4)) -> 4 | H116: =G116/SUM(G$109:G$117) -> 0.085106383
E117: <= 2007 | G117: =COUNTIFS(Arq_2!$B$2:$B$368,$G$61,Arq_2!$C$2:$C$368,"<=2007") -> 7 | H117: =G117/SUM(G$109:G$117) -> 0.14893617
A118: ANO_IN_GRAD | B118: N | C118: 4 | D118: Ano de início da graduação | E118: AAAA (valores entre 3 e 2092), conforme lançado pelo estudante | G118: =SUMIFS(Arq_2!$D$2:$D$368,Arq_2!$B$2:$B$368,$G$61)/COUNTIF(Arq_2!$B$2:$B$368,$G$61) -> 2012.9787 | H118: Média
E119: >= 2016 (4 anos) | G119: =COUNTIFS(Arq_2!$B$2:$B$368,$G$61,Arq_2!$D$2:$D$368,">=2016") -> 0 | H119: =G119/SUM(G$119:G$126) -> 0
E120: 2015 (5 anos) | G120: =COUNTIFS(Arq_2!$B$2:$B$368,$G$61,Arq_2!$D$2:$D$368,LEFT($E120,4)) -> 13 | H120: =G120/SUM(G$119:G$126) -> 0.27659574
E121: 2014 (6 anos) | G121: =COUNTIFS(Arq_2!$B$2:$B$368,$G$61,Arq_2!$D$2:$D$368,LEFT($E121,4)) -> 7 | H121: =G121/SUM(G$119:G$126) -> 0.14893617
E122: 2013 (7 anos) | G122: =COUNTIFS(Arq_2!$B$2:$B$368,$G$61,Arq_2!$D$2:$D$368,LEFT($E122,4)) -> 11 | H122: =G122/SUM(G$119:G$126) -> 0.23404255
E123: 2012 (8 anos) | G123: =COUNTIFS(Arq_2!$B$2:$B$368,$G$61,Arq_2!$D$2:$D$368,LEFT($E123,4)) -> 6 | H123: =G123/SUM(G$119:G$126) -> 0.12765957
E124: 2011 (9 anos) | G124: =COUNTIFS(Arq_2!$B$2:$B$368,$G$61,Arq_2!$D$2:$D$368,LEFT($E124,4)) -> 3 | H124: =G124/SUM(G$119:G$126) -> 0.063829787
E125: 2010 (10 anos) | G125: =COUNTIFS(Arq_2!$B$2:$B$368,$G$61,Arq_2!$D$2:$D$368,LEFT($E125,4)) -> 6 | H125: =G125/SUM(G$119:G$126) -> 0.12765957
E126: <= 2009 (+ 11 anos) | G126: =COUNTIFS(Arq_2!$B$2:$B$368,$G$61,Arq_2!$D$2:$D$368,"<=2009") -> 1 | H126: =G126/SUM(G$119:G$126) -> 0.021276596
A127: CO_TURNO_GRADUACAO | B127: N | C127: 1 | D127: Código do turno de graduação cursado pelo estudante | E127: 1 = Matutino | G127: =VLOOKUP($B$3,Cursos!$A$2:$H$11,8,0) -> 3
E128: 2 = Vespertino
E129: 3 = Integral
E130: 4 = Noturno
A131: TP_INSCRICAO_ADM | B131: N | C131: 1 | D131: Forma pela qual foi realizada a inscrição | E131: 0 = Tradicional | G131: 0
A132: TP_INSCRICAO | B132: N | C132: 1 | D132: Tipo de inscrição | E132: 0 = Concluinte | G132: 0
A133: AVALIAÇÃO - FORMAÇÃO GERAL E COMPONENTE ESPECÍFICO
A134: NÚMERO DE ITENS DA PARTE OBJETIVA
A135: NU_ITEM_OFG | B135: N | C135: 1 | D135: Número de itens da parte objetiva da Formação Geral | E135: 8 itens
A136: NU_ITEM_OFG_Z | B136: N | C136: 1 | D136: Número de itens da parte objetiva da Formação Geral que foram excluídos devido a anulação | E136: Min=1 Max=1
A137: NU_ITEM_OFG_X | B137: N | C137: 1 | D137: Número de itens da parte objetiva da Formação Geral que foram excluídos devido ao coeficiente ponto-bisserial menor que 0,20 | E137: Min=0 Max=0
A138: NU_ITEM_OFG_N | B138: N | C138: 1 | D138: Número de itens da parte objetiva da Formação Geral que não se aplicam ao grupo de curso | E138: Min=0 Max=0
A139: NU_ITEM_OCE | B139: N | C139: 2 | D139: Número de itens da parte objetiva de Componente Específico | E139: 27 itens
A140: NU_ITEM_OCE_Z | B140: N | C140: 2 | D140: Número de itens da parte objetiva de Componente Específico que foram excluídos devido a anulação | E140: Min=0 Max=5
A141: NU_ITEM_OCE_X | B141: N | C141: 1 | D141: Número de itens da parte objetiva de Componente Específico que foram excluídos devido ao coeficiente ponto-bisserial menor que 0,20 | E141: Min=1 Max=8
A142: NU_ITEM_OCE_N | B142: N | C142: 1 | D142: Número de itens da parte objetiva de Componente Específico que não se aplicam ao grupo de curso | E142: Min=0 Max=0
...

Sheet Cursos
A1: CURSO_CAMPUS | B1: CO_CURSO | C1: CURSO | D1: CAMPUS | E1: CO_GRUPO | F1: CO_MODALIDADE | G1: CO_MUNIC_CURSO | H1: CO_TURNO_GRADUACAO
A2: =CONCATENATE(C2," - ",D2) -> Engenharia Elétrica - Campus Vitória | B2: 88399 | C2: Engenharia Elétrica | D2: Campus Vitória | E2: 5806 | F2: 1 | G2: 3205309 | H2: 3
A3: =CONCATENATE(C3," - ",D3) -> Engenharia de Controle e Automação - Campus Serra | B3: 102499 | C3: Engenharia de Controle e Automação | D3: Campus Serra | E3: 5814 | F3: 1 | G3: 3205002 | H3: 4
A4: =CONCATENATE(C4," - ",D4) -> Engenharia de Produção - Campus Cariacica | B4: 121880 | C4: Engenharia de Produção | D4: Campus Cariacica | E4: 6208 | F4: 1 | G4: 3201308 | H4: 3
A5: =CONCATENATE(C5," - ",D5) -> Engenharia Sanitária e Ambiental - Campus Vitória | B5: 121884 | C5: Engenharia Sanitária e Ambiental | D5: Campus Vitória | E5: 6307 | F5: 1 | G5: 3205309 | H5: 3
A6: =CONCATENATE(C6," - ",D6) -> Engenharia Mecânica - Campus São Mateus | B6: 123569 | C6: Engenharia Mecânica | D6: Campus São Mateus | E6: 5902 | F6: 1 | G6: 3204906 | H6: 3
A7: =CONCATENATE(C7," - ",D7) -> Agronomia - Campus Santa Teresa | B7: 1103831 | C7: Agronomia | D7: Campus Santa Teresa | E7: 17 | F7: 1 | G7: 3204609 | H7: 3
A8: =CONCATENATE(C8," - ",D8) -> Agronomia - Campus Itapina | B8: 1117583 | C8: Agronomia | D8: Campus Itapina | E8: 17 | F8: 1 | G8: 3201506 | H8: 3
A9: =CONCATENATE(C9," - ",D9) -> Engenharia Mecânica - Campus Cachoeiro de Itapemirim | B9: 1181815 | C9: Engenharia Mecânica | D9: Campus Cachoeiro de Itapemirim | E9: 5902 | F9: 1 | G9: 3201209 | H9: 3
A10: =CONCATENATE(C10," - ",D10) -> Arquitetura e Urbanismo - Campus Colatina | B10: 1181819 | C10: Arquitetura e Urbanismo | D10: Campus Colatina | E10: 21 | F10: 1 | G10: 3201506 | H10: 3
A11: =CONCATENATE(C11," - ",D11) -> Engenharia Mecânica - Campus Aracruz | B11: 1319229 | C11: Engenharia Mecânica | D11: Campus Aracruz | E11: 5902 | F11: 1 | G11: 3200607 | H11: 3

Sheet Enade
A1: Ano | B1: Código da Área | C1: Área de Avaliação | D1: Código da IES | E1: Nome da IES | F1: Sigla da IES | G1: Organização Acadêmica | H1: Categoria Administrativa | I1: Código do Curso | J1: Modalidade de Ensino | K1: Código do Município | L1: Município do Curso | M1: Sigla da UF | N1: Nº de Concluintes Inscritos | O1: Nº de Concluintes Participantes | P1: Nota Bruta - FG | Q1: Nota Padronizada - FG | R1: Nota Bruta - CE | S1: Nota Padronizada - CE | T1: Conceito Enade (Contínuo) | U1: Conceito Enade (Faixa) | V1: Observação
A2: 2019 | B2: 17 | C2: AGRONOMIA | D2: 1808 | E2: INSTITUTO FEDERAL DE EDUCAÇÃO, CIÊNCIA E TECNOLOGIA DO ESPÍRITO SANTO | F2: IFES | G2: Instituto Federal de Educação, Ciência e Tecnologia | H2: Pública Federal | I2: 1103831 | J2: Educação Presencial | K2: 3204609 | L2: Santa Teresa | M2: ES | N2: 30 | O2: 28 | P2: 39.6107 | Q2: 2.6791 | R2: 61.1643 | S2: 3.7511 | T2: 3.4831 | U2: 4
A3: 2019 | B3: 17 | C3: AGRONOMIA | D3: 1808 | E3: INSTITUTO FEDERAL DE EDUCAÇÃO, CIÊNCIA E TECNOLOGIA DO ESPÍRITO SANTO | F3: IFES | G3: Instituto Federal de Educação, Ciência e Tecnologia | H3: Pública Federal | I3: 1117583 | J3: Educação Presencial | K3: 3201506 | L3: Colatina | M3: ES | N3: 23 | O3: 23 | P3: 38.7 | Q3: 2.5389 | R3: 60.7261 | S3: 3.6818 | T3: 3.3961 | U3: 4
A4: 2019 | B4: 21 | C4: ARQUITETURA E URBANISMO | D4: 1808 | E4: INSTITUTO FEDERAL DE EDUCAÇÃO, CIÊNCIA E TECNOLOGIA DO ESPÍRITO SANTO | F4: IFES | G4: Instituto Federal de Educação, Ciência e Tecnologia | H4: Pública Federal | I4: 1181819 | J4: Educação Presencial | K4: 3201506 | L4: Colatina | M4: ES | N4: 40 | O4: 36 | P4: 44.0583 | Q4: 2.6228 | R4: 58.6944 | S4: 2.5711 | T4: 2.584 | U4: 3
A5: 2019 | B5: 5806 | C5: ENGENHARIA ELÉTRICA | D5: 1808 | E5: INSTITUTO FEDERAL DE EDUCAÇÃO, CIÊNCIA E TECNOLOGIA DO ESPÍRITO SANTO | F5: IFES | G5: Instituto Federal de Educação, Ciência e Tecnologia | H5: Pública Federal | I5: 88399 | J5: Educação Presencial | K5: 3205309 | L5: Vitória | M5: ES | N5: 47 | O5: 43 | P5: 56.0465 | Q5: 4.5377 | R5: 47.2558 | S5: 4.0332 | T5: 4.1593 | U5: 5
A6: 2019 | B6: 5814 | C6: ENGENHARIA DE CONTROLE E AUTOMAÇÃO | D6: 1808 | E6: INSTITUTO FEDERAL DE EDUCAÇÃO, CIÊNCIA E TECNOLOGIA DO ESPÍRITO SANTO | F6: IFES | G6: Instituto Federal de Educação, Ciência e Tecnologia | H6: Pública Federal | I6: 102499 | J6: Educação Presencial | K6: 3205002 | L6: Serra | M6: ES | N6: 49 | O6: 39 | P6: 46.9641 | Q6: 3.1065 | R6: 44.1308 | S6: 3.0755 | T6: 3.0833 | U6: 4
A7: 2019 | B7: 5902 | C7: ENGENHARIA MECÂNICA | D7: 1808 | E7: INSTITUTO FEDERAL DE EDUCAÇÃO, CIÊNCIA E TECNOLOGIA DO ESPÍRITO SANTO | F7: IFES | G7: Instituto Federal de Educação, Ciência e Tecnologia | H7: Pública Federal | I7: 123569 | J7: Educação Presencial | K7: 3204906 | L7: São Mateus | M7: ES | N7: 46 | O7: 38 | P7: 48.2421 | Q7: 3.1863 | R7: 39.5632 | S7: 2.9001 | T7: 2.9716 | U7: 4
A8: 2019 | B8: 5902 | C8: ENGENHARIA MECÂNICA | D8: 1808 | E8: INSTITUTO FEDERAL DE EDUCAÇÃO, CIÊNCIA E TECNOLOGIA DO ESPÍRITO SANTO | F8: IFES | G8: Instituto Federal de Educação, Ciência e Tecnologia | H8: Pública Federal | I8: 1181815 | J8: Educação Presencial | K8: 3201209 | L8: Cachoeiro de Itapemirim | M8: ES | N8: 17 | O8: 16 | P8: 41.7375 | Q8: 2.1787 | R8: 39.5562 | S8: 2.899 | T8: 2.7189 | U8: 3
A9: 2019 | B9: 5902 | C9: ENGENHARIA MECÂNICA | D9: 1808 | E9: INSTITUTO FEDERAL DE EDUCAÇÃO, CIÊNCIA E TECNOLOGIA DO ESPÍRITO SANTO | F9: IFES | G9: Instituto Federal de Educação, Ciência e Tecnologia | H9: Pública Federal | I9: 1319229 | J9: Educação Presencial | K9: 3200607 | L9: Aracruz | M9: ES | N9: 20 | O9: 20 | P9: 51.97 | Q9: 3.7638 | R9: 48.095 | S9: 4.2153 | T9: 4.1024 | U9: 5
A10: 2019 | B10: 6208 | C10: ENGENHARIA DE PRODUÇÃO | D10: 1808 | E10: INSTITUTO FEDERAL DE EDUCAÇÃO, CIÊNCIA E TECNOLOGIA DO ESPÍRITO SANTO | F10: IFES | G10: Instituto Federal de Educação, Ciência e Tecnologia | H10: Pública Federal | I10: 121880 | J10: Educação Presencial | K10: 3201308 | L10: Cariacica | M10: ES | N10: 63 | O10: 58 | P10: 50.869 | Q10: 3.9432 | R10: 51.8224 | S10: 3.4758 | T10: 3.5926 | U10: 4
A11: 2019 | B11: 6307 | C11: ENGENHARIA AMBIENTAL | D11: 1808 | E11: INSTITUTO FEDERAL DE EDUCAÇÃO, CIÊNCIA E TECNOLOGIA DO ESPÍRITO SANTO | F11: IFES | G11: Instituto Federal de Educação, Ciência e Tecnologia | H11: Pública Federal | I11: 121884 | J11: Educação Presencial | K11: 3205309 | L11: Vitória | M11: ES | N11: 32 | O11: 32 | P11: 55.5688 | Q11: 3.709 | R11: 54.9125 | S11: 3.8716 | T11: 3.831 | U11: 4

Sheet IDD
A1: Sigla da IES | B1: Organização Acadêmica | C1: Categoria Administrativa | D1: Código do Curso | E1: Modalidade de Ensino | F1: Código do Município | G1: Município do Curso | H1: Sigla da UF | I1: Nº de Concluintes Inscritos | J1: Nº de Concluintes Participantes | K1: Nº de Concluintes Participantes com nota no Enem | L1: Proporção de Concluintes participantes com nota no Enem | M1: Nota Bruta - IDD | N1: IDD (Contínuo) | O1: IDD (Faixa)
A2: IFES | B2: Instituto Federal de Educação, Ciência e Tecnologia | C2: Pública Federal | D2: 1181819 | E2: Educação Presencial | F2: 3201506 | G2: Colatina | H2: ES | I2: 40 | J2: 36 | K2: 34 | L2: 0.94444444 | M2: -1.8119 | N2: 1.0977 | O2: 2
A3: IFES | B3: Instituto Federal de Educação, Ciência e Tecnologia | C3: Pública Federal | D3: 1117583 | E3: Educação Presencial | F3: 3201506 | G3: Colatina | H3: ES | I3: 23 | J3: 23 | K3: 19 | L3: 0.82608696 | M3: -1.4334 | N3: 1.6179 | O3: 2
A4: IFES | B4: Instituto Federal de Educação, Ciência e Tecnologia | C4: Pública Federal | D4: 123569 | E4: Educação Presencial | F4: 3204906 | G4: São Mateus | H4: ES | I4: 46 | J4: 38 | K4: 36 | L4: 0.94736842 | M4: 0.0921 | N4: 2.2269 | O4: 3
A5: IFES | B5: Instituto Federal de Educação, Ciência e Tecnologia | C5: Pública Federal | D5: 1319229 | E5: Educação Presencial | F5: 3200607 | G5: Aracruz | H5: ES | I5: 20 | J5: 20 | K5: 19 | L5: 0.95 | M5: 4.0556 | N5: 4.1531 | O5: 5
A6: IFES | B6: Instituto Federal de Educação, Ciência e Tecnologia | C6: Pública Federal | D6: 1103831 | E6: Educação Presencial | F6: 3204609 | G6: Santa Teresa | H6: ES | I6: 30 | J6: 28 | K6: 27 | L6: 0.96428571 | M6: 0.4377 | N6: 3.1022 | O6: 4
A7: IFES | B7: Instituto Federal de Educação, Ciência e Tecnologia | C7: Pública Federal | D7: 121880 | E7: Educação Presencial | F7: 3201308 | G7: Cariacica | H7: ES | I7: 63 | J7: 58 | K7: 48 | L7: 0.82758621 | M7: -0.8358 | N7: 2.1435 | O7: 3
A8: IFES | B8: Instituto Federal de Educação, Ciência e Tecnologia | C8: Pública Federal | D8: 102499 | E8: Educação Presencial | F8: 3205002 | G8: Serra | H8: ES | I8: 49 | J8: 39 | K8: 17 | L8: 0.43589744 | M8: 0.1698 | N8: 2.779 | O8: 3
A9: IFES | B9: Instituto Federal de Educação, Ciência e Tecnologia | C9: Pública Federal | D9: 88399 | E9: Educação Presencial | F9: 3205309 | G9: Vitória | H9: ES | I9: 47 | J9: 43 | K9: 34 | L9: 0.79069767 | M9: 2.0828 | N9: 3.2867 | O9: 4
A10: IFES | B10: Instituto Federal de Educação, Ciência e Tecnologia | C10: Pública Federal | D10: 121884 | E10: Educação Presencial | F10: 3205309 | G10: Vitória | H10: ES | I10: 32 | J10: 32 | K10: 25 | L10: 0.78125 | M10: 0.4399 | N10: 2.58 | O10: 3
A11: IFES | B11: Instituto Federal de Educação, Ciência e Tecnologia | C11: Pública Federal | D11: 1181815 | E11: Educação Presencial | F11: 3201209 | G11: Cachoeiro de Itapemirim | H11: ES | I11: 17 | J11: 16 | K11: 15 | L11: 0.9375 | M11: -0.0142 | N11: 2.1752 | O11: 3

Sheet CPC
A1: Ano | B1: Código da Área | C1: Área de Avaliação | D1: Código da IES | E1: Nome da IES | F1: Sigla da IES | G1: Organização Acadêmica | H1: Categoria Administrativa | I1: Código do Curso | J1: Modalidade de Ensino | K1: Código do Município | L1: Município do Curso | M1: Sigla da UF | N1: Nº de Concluintes Inscritos | O1: Nº de Concluintes Participantes | P1: Nota Bruta - FG | Q1: Nota Padronizada - FG | R1: Nota Bruta - CE | S1: Nota Padronizada - CE | T1: Conceito Enade (Contínuo) | U1: Concluintes participantes com nota no Enem | V1: Proporção de concluintes participantes com nota no Enem | W1: Nota Bruta - IDD | X1: Nota Padronizada - IDD | Y1: Nota Bruta – Organização Didático-Pedagógica | Z1: Nota Padronizada - Organização Didático-Pedagógica | AA1: Nota Bruta – Infraestrutura e Instalações Físicas | AB1: Nota Padronizada - Infraestrutura e Instalações Físicas | AC1: Nota Bruta – Oportunidade de Ampliação da Formação | AD1: Nota Padronizada - Oportunidade de Ampliação da Formação | AE1: Nota Bruta - Mestres | AF1: Nota Padronizada - Mestres | AG1: Nota Bruta - Doutores | AH1: Nota Padronizada - Doutores | AI1: Nota Bruta – Regime de Trabalho | AJ1: Nota Padronizada - Regime de Trabalho | AK1: CPC (Contínuo) | AL1: CPC (Faixa) | AM1: Observação
A2: 2019 | B2: 17 | C2: AGRONOMIA | D2: 1808 | E2: INSTITUTO FEDERAL DE EDUCAÇÃO, CIÊNCIA E TECNOLOGIA DO ESPÍRITO SANTO | F2: IFES | G2: Instituto Federal de Educação, Ciência e Tecnologia | H2: Pública Federal | I2: 1103831 | J2: Educação Presencial | K2: 3204609 | L2: Santa Teresa | M2: ES | N2: 30 | O2: 28 | P2: 39.61 | Q2: 2.679 | R2: 61.164 | S2: 3.7511 | T2: 3.483 | U2: 27 | V2: 0.964 | W2: 0.437 | X2: 3.102 | Y2: 5.187 | Z2: 2.709 | AA2: 4.317 | AB2: 1.586 | AC2: 4.203 | AD2: 1.589 | AE2: 0.953 | AF2: 4.209 | AG2: 0.604 | AH2: 3.023 | AI2: 1 | AJ2: 5 | AK2: 3.248 | AL2: 4
A3: 2019 | B3: 17 | C3: AGRONOMIA | D3: 1808 | E3: INSTITUTO FEDERAL DE EDUCAÇÃO, CIÊNCIA E TECNOLOGIA DO ESPÍRITO SANTO | F3: IFES | G3: Instituto Federal de Educação, Ciência e Tecnologia | H3: Pública Federal | I3: 1117583 | J3: Educação Presencial | K3: 3201506 | L3: Colatina | M3: ES | N3: 23 | O3: 23 | P3: 38.7 | Q3: 2.538 | R3: 60.726 | S3: 3.6817 | T3: 3.396 | U3: 19 | V3: 0.826 | W3: -1.434 | X3: 1.617 | Y3: 5.136 | Z3: 2.565 | AA3: 5.117 | AB3: 3.209 | AC3: 4.88 | AD3: 2.874 | AE3: 1 | AF3: 5 | AG3: 0.75 | AH3: 3.75 | AI3: 1 | AJ3: 5 | AK3: 2.982 | AL3: 4
A4: 2019 | B4: 21 | C4: ARQUITETURA E URBANISMO | D4: 1808 | E4: INSTITUTO FEDERAL DE EDUCAÇÃO, CIÊNCIA E TECNOLOGIA DO ESPÍRITO SANTO | F4: IFES | G4: Instituto Federal de Educação, Ciência e Tecnologia | H4: Pública Federal | I4: 1181819 | J4: Educação Presencial | K4: 3201506 | L4: Colatina | M4: ES | N4: 40 | O4: 36 | P4: 44.058 | Q4: 2.622 | R4: 58.694 | S4: 2.571 | T4: 2.584 | U4: 34 | V4: 0.944 | W4: -1.812 | X4: 1.097 | Y4: 5.414 | Z4: 3.357 | AA4: 5.596 | AB4: 4.223 | AC4: 4.764 | AD4: 3.147 | AE4: 0.928 | AF4: 4.38 | AG4: 0.214 | AH4: 1.071 | AI4: 1 | AJ4: 5 | AK4: 2.306 | AL4: 3
A5: 2019 | B5: 5806 | C5: ENGENHARIA ELÉTRICA | D5: 1808 | E5: INSTITUTO FEDERAL DE EDUCAÇÃO, CIÊNCIA E TECNOLOGIA DO ESPÍRITO SANTO | F5: IFES | G5: Instituto Federal de Educação, Ciência e Tecnologia | H5: Pública Federal | I5: 88399 | J5: Educação Presencial | K5: 3205309 | L5: Vitória | M5: ES | N5: 47 | O5: 43 | P5: 56.046 | Q5: 4.537 | R5: 47.255 | S5: 4.0331 | T5: 4.159 | U5: 34 | V5: 0.79 | W5: 2.082 | X5: 3.286 | Y5: 5.217 | Z5: 3.441 | AA5: 5.37 | AB5: 3.78 | AC5: 5.399 | AD5: 4.221 | AE5: 0.981 | AF5: 4.791 | AG5: 0.611 | AH5: 3.055 | AI5: 1 | AJ5: 5 | AK5: 3.727 | AL5: 4
A6: 2019 | B6: 5814 | C6: ENGENHARIA DE CONTROLE E AUTOMAÇÃO | D6: 1808 | E6: INSTITUTO FEDERAL DE EDUCAÇÃO, CIÊNCIA E TECNOLOGIA DO ESPÍRITO SANTO | F6: IFES | G6: Instituto Federal de Educação, Ciência e Tecnologia | H6: Pública Federal | I6: 102499 | J6: Educação Presencial | K6: 3205002 | L6: Serra | M6: ES | N6: 49 | O6: 39 | P6: 46.964 | Q6: 3.106 | R6: 44.13 | S6: 3.0755 | T6: 3.083 | U6: 17 | V6: 0.435 | W6: 0.169 | X6: 2.778 | Y6: 5.076 | Z6: 3.014 | AA6: 5.124 | AB6: 3.163 | AC6: 4.933 | AD6: 3.608 | AE6: 1 | AF6: 5 | AG6: 0.807 | AH6: 4.038 | AI6: 1 | AJ6: 5 | AK6: 3.419 | AL6: 4
A7: 2019 | B7: 5902 | C7: ENGENHARIA MECÂNICA | D7: 1808 | E7: INSTITUTO FEDERAL DE EDUCAÇÃO, CIÊNCIA E TECNOLOGIA DO ESPÍRITO SANTO | F7: IFES | G7: Instituto Federal de Educação, Ciência e Tecnologia | H7: Pública Federal | I7: 123569 | J7: Educação Presencial | K7: 3204906 | L7: São Mateus | M7: ES | N7: 46 | O7: 38 | P7: 48.242 | Q7: 3.186 | R7: 39.563 | S7: 2.9 | T7: 2.971 | U7: 36 | V7: 0.947 | W7: 0.092 | X7: 2.226 | Y7: 4.736 | Z7: 2.542 | AA7: 4.682 | AB7: 2.334 | AC7: 4.649 | AD7: 3.223 | AE7: 0.88 | AF7: 3.487 | AG7: 0.166 | AH7: 0.833 | AI7: 1 | AJ7: 5 | AK7: 2.523 | AL7: 3
A8: 2019 | B8: 5902 | C8: ENGENHARIA MECÂNICA | D8: 1808 | E8: INSTITUTO FEDERAL DE EDUCAÇÃO, CIÊNCIA E TECNOLOGIA DO ESPÍRITO SANTO | F8: IFES | G8: Instituto Federal de Educação, Ciência e Tecnologia | H8: Pública Federal | I8: 1181815 | J8: Educação Presencial | K8: 3201209 | L8: Cachoeiro de Itapemirim | M8: ES | N8: 17 | O8: 16 | P8: 41.737 | Q8: 2.178 | R8: 39.556 | S8: 2.899 | T8: 2.718 | U8: 15 | V8: 0.937 | W8: -0.015 | X8: 2.175 | Y8: 4.63 | Z8: 2.336 | AA8: 4.222 | AB8: 1.404 | AC8: 2.722 | AD8: 0.688 | AE8: 0.928 | AF8: 4.092 | AG8: 0.357 | AH8: 1.785 | AI8: 1 | AJ8: 5 | AK8: 2.517 | AL8: 3
A9: 2019 | B9: 5902 | C9: ENGENHARIA MECÂNICA | D9: 1808 | E9: INSTITUTO FEDERAL DE EDUCAÇÃO, CIÊNCIA E TECNOLOGIA DO ESPÍRITO SANTO | F9: IFES | G9: Instituto Federal de Educação, Ciência e Tecnologia | H9: Pública Federal | I9: 1319229 | J9: Educação Presencial | K9: 3200607 | L9: Aracruz | M9: ES | N9: 20 | O9: 20 | P9: 51.97 | Q9: 3.763 | R9: 48.095 | S9: 4.2152 | T9: 4.102 | U9: 19 | V9: 0.949 | W9: 4.055 | X9: 4.153 | Y9: 5.302 | Z9: 3.644 | AA9: 5.275 | AB9: 3.535 | AC9: 5.008 | AD9: 3.695 | AE9: 1 | AF9: 5 | AG9: 0.285 | AH9: 1.428 | AI9: 1 | AJ9: 5 | AK9: 3.78 | AL9: 4
A10: 2019 | B10: 6208 | C10: ENGENHARIA DE PRODUÇÃO | D10: 1808 | E10: INSTITUTO FEDERAL DE EDUCAÇÃO, CIÊNCIA E TECNOLOGIA DO ESPÍRITO SANTO | F10: IFES | G10: Instituto Federal de Educação, Ciência e Tecnologia | H10: Pública Federal | I10: 121880 | J10: Educação Presencial | K10: 3201308 | L10: Cariacica | M10: ES | N10: 63 | O10: 58 | P10: 50.868 | Q10: 3.943 | R10: 51.822 | S10: 3.4757 | T10: 3.592 | U10: 48 | V10: 0.827 | W10: -0.836 | X10: 2.143 | Y10: 4.841 | Z10: 2.438 | AA10: 5.247 | AB10: 3.527 | AC10: 4.258 | AD10: 2.581 | AE10: 0.937 | AF10: 4.403 | AG10: 0.5 | AH10: 2.5 | AI10: 1 | AJ10: 5 | AK10: 2.972 | AL10: 4
A11: 2019 | B11: 6307 | C11: ENGENHARIA AMBIENTAL | D11: 1808 | E11: INSTITUTO FEDERAL DE EDUCAÇÃO, CIÊNCIA E TECNOLOGIA DO ESPÍRITO SANTO | F11: IFES | G11: Instituto Federal de Educação, Ciência e Tecnologia | H11: Pública Federal | I11: 121884 | J11: Educação Presencial | K11: 3205309 | L11: Vitória | M11: ES | N11: 32 | O11: 32 | P11: 55.568 | Q11: 3.709 | R11: 54.912 | S11: 3.8716 | T11: 3.83 | U11: 25 | V11: 0.781 | W11: 0.439 | X11: 2.579 | Y11: 5.256 | Z11: 2.998 | AA11: 5.099 | AB11: 3.247 | AC11: 4.991 | AD11: 3.559 | AE11: 0.968 | AF11: 4.648 | AG11: 0.593 | AH11: 2.968 | AI11: 1 | AJ11: 5 | AK11: 3.314 | AL11: 4

Sheet Arq_1
A1: NU_ANO | B1: CO_CURSO | C1: CO_IES | D1: CO_CATEGAD | E1: CO_ORGACAD | F1: CO_GRUPO | G1: CO_MODALIDADE | H1: CO_MUNIC_CURSO | I1: CO_UF_CURSO | J1: CO_REGIAO_CURSO
A2: 2019 | B2: 88399 | C2: 1808 | D2: 1 | E2: 10026 | F2: 5806 | G2: 1 | H2: 3205309 | I2: 32 | J2: 3
A3: 2019 | B3: 88399 | C3: 1808 | D3: 1 | E3: 10026 | F3: 5806 | G3: 1 | H3: 3205309 | I3: 32 | J3: 3
A4: 2019 | B4: 88399 | C4: 1808 | D4: 1 | E4: 10026 | F4: 5806 | G4: 1 | H4: 3205309 | I4: 32 | J4: 3
A5: 2019 | B5: 88399 | C5: 1808 | D5: 1 | E5: 10026 | F5: 5806 | G5: 1 | H5: 3205309 | I5: 32 | J5: 3
A6: 2019 | B6: 88399 | C6: 1808 | D6: 1 | E6: 10026 | F6: 5806 | G6: 1 | H6: 3205309 | I6: 32 | J6: 3
A7: 2019 | B7: 88399 | C7: 1808 | D7: 1 | E7: 10026 | F7: 5806 | G7: 1 | H7: 3205309 | I7: 32 | J7: 3
A8: 2019 | B8: 88399 | C8: 1808 | D8: 1 | E8: 10026 | F8: 5806 | G8: 1 | H8: 3205309 | I8: 32 | J8: 3
A9: 2019 | B9: 88399 | C9: 1808 | D9: 1 | E9: 10026 | F9: 5806 | G9: 1 | H9: 3205309 | I9: 32 | J9: 3
A10: 2019 | B10: 88399 | C10: 1808 | D10: 1 | E10: 10026 | F10: 5806 | G10: 1 | H10: 3205309 | I10: 32 | J10: 3
A11: 2019 | B11: 88399 | C11: 1808 | D11: 1 | E11: 10026 | F11: 5806 | G11: 1 | H11: 3205309 | I11: 32 | J11: 3
A12: 2019 | B12: 88399 | C12: 1808 | D12: 1 | E12: 10026 | F12: 5806 | G12: 1 | H12: 3205309 | I12: 32 | J12: 3
A13: 2019 | B13: 88399 | C13: 1808 | D13: 1 | E13: 10026 | F13: 5806 | G13: 1 | H13: 3205309 | I13: 32 | J13: 3
... A368: 2019 | B368: 1319229 | C368: 1808 | D368: 1 | E368: 10026 | F368: 5902 | G368: 1 | H368: 3200607 | I368: 32 | J368: 3

Sheet Arq_2
A1: NU_ANO | B1: CO_CURSO | C1: ANO_FIM_EM | D1: ANO_IN_GRAD | E1: CO_TURNO_GRADUACAO
A2: 2019 | B2: 88399 | C2: 1993 | D2: 2012 | E2: 3
A3: 2019 | B3: 121880 | C3: 1993 | D3: 2015 | E3: 3
A4: 2019 | B4: 102499 | C4: 1993 | D4: 2012 | E4: 4
A5: 2019 | B5: 123569 | C5: 1995 | D5: 2010 | E5: 3
A6: 2019 | B6: 88399 | C6: 1998 | D6: 2011 | E6: 3
A7: 2019 | B7: 123569 | C7: 1998 | D7: 2010 | E7: 3
A8: 2019 | B8: 121880 | C8: 1999 | D8: 2010 | E8: 3
A9: 2019 | B9: 1319229 | C9: 1999 | D9: 2015 | E9: 3
A10: 2019 | B10: 121884 | C10: 2000 | D10: 2015 | E10: 3
A11: 2019 | B11: 123569 | C11: 2001 | D11: 2012 | E11: 3
A12: 2019 | B12: 88399 | C12: 2001 | D12: 2015 | E12: 3
A13: 2019 | B13: 102499 | C13: 2001 | D13: 2015 | E13: 4
... A368: 2019 | B368: 1319229 | C368: 2015 | D368: 2016 | E368: 3

Sheet Arq_3
A1: NU_ANO | B1: CO_CURSO | C1: NU_ITEM_OFG | D1: NU_ITEM_OFG_Z | E1: NU_ITEM_OFG_X | F1: NU_ITEM_OFG_N | G1: NU_ITEM_OCE | H1: NU_ITEM_OCE_Z | I1: NU_ITEM_OCE_X | J1: NU_ITEM_OCE_N | K1: DS_VT_GAB_OFG_FIN | L1: DS_VT_GAB_OCE_FIN | M1: DS_VT_ESC_OFG | N1: DS_VT_ACE_OFG | O1: DS_VT_ESC_OCE | P1: DS_VT_ACE_OCE | Q1: TP_PRES | R1: TP_PR_GER | S1: TP_PR_OB_FG | T1: TP_PR_DI_FG | U1: TP_PR_OB_CE | V1: TP_PR_DI_CE | W1: TP_SFG_D1 | X1: TP_SFG_D2 | Y1: TP_SCE_D1 | Z1: TP_SCE_D2 | AA1: TP_SCE_D3 | AB1: NT_GER | AC1: NT_FG | AD1: NT_OBJ_FG | AE1: NT_DIS_FG | AF1: NT_FG_D1 | AG1: NT_FG_D1_PT | AH1: NT_FG_D1_CT | AI1: NT_FG_D2 | AJ1: NT_FG_D2_PT | AK1: NT_FG_D2_CT | AL1: NT_CE | AM1: NT_OBJ_CE | AN1: NT_DIS_CE | AO1: NT_CE_D1 | AP1: NT_CE_D2 | AQ1: NT_CE_D3 | AR1: CO_RS_I1 | AS1: CO_RS_I2 | AT1: CO_RS_I3 | AU1: CO_RS_I4 | AV1: CO_RS_I5 | AW1: CO_RS_I6 | AX1: CO_RS_I7 | AY1: CO_RS_I8 | AZ1: CO_RS_I9
A2: 2019 | B2: 1117583 | C2: 8 | D2: 1 | E2: 0 | F2: 0 | G2: 27 | H2: 3 | I2: 2 | J2: 0 | K2: ZDCBCCDB | L2: ZBBZBEBEDDEDDAZXCDEECACAXAB | M2: ........ | N2: 80000000 | O2: ........................... | P2: 8.008e+26 | Q2: 555 | R2: 333 | S2: 333 | T2: 333 | U2: 333 | V2: 333 | W2: 333 | X2: 333 | Y2: 333 | Z2: 333 | AA2: 333 | AB2: 0 | AC2: 0 | AD2: 0 | AE2: 0 | AF2: 0 | AG2: 0 | AH2: 0 | AI2: 0 | AJ2: 0 | AK2: 0 | AL2: 0 | AM2: 0 | AN2: 0 | AO2: 0 | AP2: 0 | AQ2: 0
A3: 2019 | B3: 121880 | C3: 8 | D3: 1 | E3: 0 | F3: 0 | G3: 27 | H3: 0 | I3: 4 | J3: 0 | K3: ZDCBCCDB | L3: BXCAXDEXCBECDACEDACADEBXBBE | M3: DCAABDBC | N3: 80000000 | O3: ADDEECABBECBAEADCEAADDBCCBE | P3: 9.009009e+25 | Q3: 555 | R3: 555 | S3: 555 | T3: 555 | U3: 555 | V3: 333 | W3: 555 | X3: 555 | Y3: 333 | Z3: 333 | AA3: 333 | AB3: 16 | AC3: 8.6 | AD3: 0 | AE3: 21.5 | AF3: 29 | AG3: 65 | AH3: 20 | AI3: 14 | AJ3: 70 | AK3: 0 | AL3: 18.4 | AM3: 21.7 | AN3: 0 | AO3: 0 | AP3: 0 | AQ3: 0 | AR3: D | AS3: E | AT3: B | AU3: D | AV3: C | AW3: C | AX3: C | AY3: C | AZ3: D
A4: 2019 | B4: 88399 | C4: 8 | D4: 1 | E4: 0 | F4: 0 | G4: 27 | H4: 5 | I4: 3 | J4: 0 | K4: ZDCBCCDB | L4: ZAXDBBAXDABEEZECZAEZBCXBZBC | M4: ADACABCC | N4: 81000000 | O4: CCCCCCCCCCCCCCCCCCCCCCCCCCC | P4: 8.0900009e+26 | Q4: 555 | R4: 555 | S4: 555 | T4: 555 | U4: 555 | V4: 555 | W4: 555 | X4: 555 | Y4: 333 | Z4: 555 | AA4: 333 | AB4: 17 | AC4: 27.8 | AD4: 14.3 | AE4: 48 | AF4: 24 | AG4: 40 | AH4: 20 | AI4: 72 | AJ4: 60 | AK4: 75 | AL4: 13.4 | AM4: 15.8 | AN4: 0 | AO4: 0 | AP4: 0 | AQ4: 0 | AR4: C | AS4: C | AT4: C | AU4: A | AV4: A | AW4: C | AX4: A | AY4: C | AZ4: B
A5: 2019 | B5: 1181815 | C5: 8 | D5: 1 | E5: 0 | F5: 0 | G5: 27 | H5: 3 | I5: 4 | J5: 0 | K5: ZDCBCCDB | L5: ZDEBDAEBXDACZXCBXDCZABBEDXC | M5: ABCDEABC | N5: 80100000 | O5: CDEDEDDBDCADCBAECEDDDCCBABC | P5: 8.1100002e+26 | Q5: 555 | R5: 555 | S5: 555 | T5: 555 | U5: 555 | V5: 555 | W5: 555 | X5: 336 | Y5: 555 | Z5: 666 | AA5: 555 | AB5: 19.5 | AC5: 8.6 | AD5: 14.3 | AE5: 0 | AF5: 0 | AG5: 0 | AH5: 0 | AI5: 0 | AJ5: 0 | AK5: 0 | AL5: 23.1 | AM5: 25 | AN5: 12.5 | AO5: 25 | AP5: 0 | AQ5: 0 | AR5: C | AS5: C | AT5: B | AU5: B | AV5: B | AW5: C | AX5: B | AY5: E | AZ5: E
A6: 2019 | B6: 123569 | C6: 8 | D6: 1 | E6: 0 | F6: 0 | G6: 27 | H6: 3 | I6: 4 | J6: 0 | K6: ZDCBCCDB | L6: ZDEBDAEBXDACZXCBXDCZABBEDXC | M6: ADDCECBA | N6: 81000100 | O6: EDBBCBCACCADCDAECBBDDEBCBBA | P6: 8.1010001e+26 | Q6: 555 | R6: 555 | S6: 555 | T6: 555 | U6: 555 | V6: 555 | W6: 555 | X6: 555 | Y6: 555 | Z6: 666 | AA6: 555 | AB6: 22.2 | AC6: 23 | AD6: 28.6 | AE6: 14.5 | AF6: 15 | AG6: 75 | AH6: 0 | AI6: 14 | AJ6: 70 | AK6: 0 | AL6: 21.9 | AM6: 20 | AN6: 32.5 | AO6: 25 | AP6: 0 | AQ6: 40 | AR6: D | AS6: D | AT6: C | AU6: D | AV6: D | AW6: D | AX6: C | AY6: D | AZ6: D
A7: 2019 | B7: 1181819 | C7: 8 | D7: 1 | E7: 0 | F7: 0 | G7: 27 | H7: 0 | I7: 2 | J7: 0 | K7: ZDCBCCDB | L7: DBCDECEDACECCDDBCADACEAXEXD | M7: ADCAACDD | N7: 81100110 | O7: CBCCBBCADDCEECCAABCBDDECBCD | P7: 1.1e+25 | Q7: 555 | R7: 555 | S7: 555 | T7: 555 | U7: 555 | V7: 555 | W7: 555 | X7: 555 | Y7: 555 | Z7: 555 | AA7: 555 | AB7: 22.5 | AC7: 44.3 | AD7: 57.1 | AE7: 25 | AF7: 41 | AG7: 45 | AH7: 40 | AI7: 9 | AJ7: 45 | AK7: 0 | AL7: 15.2 | AM7: 12 | AN7: 33.3 | AO7: 50 | AP7: 10 | AQ7: 40 | AR7: C | AS7: C | AT7: C | AU7: A | AV7: A | AW7: B | AX7: E | AY7: D | AZ7: B
A8: 2019 | B8: 123569 | C8: 8 | D8: 1 | E8: 0 | F8: 0 | G8: 27 | H8: 3 | I8: 4 | J8: 0 | K8: ZDCBCCDB | L8: ZDEBDAEBXDACZXCBXDCZABBEDXC | M8: BBCAABCD | N8: 80100000 | O8: AE*DBDDEECAADBCBCCDDAABCBAC | P8: 8.0000001e+26 | Q8: 555 | R8: 555 | S8: 555 | T8: 555 | U8: 555 | V8: 555 | W8: 555 | X8: 555 | Y8: 555 | Z8: 666 | AA8: 555 | AB8: 24.4 | AC8: 21 | AD8: 14.3 | AE8: 31 | AF8: 8 | AG8: 40 | AH8: 0 | AI8: 54 | AJ8: 70 | AK8: 50 | AL8: 25.5 | AM8: 30 | AN8: 0 | AO8: 0 | AP8: 0 | AQ8: 0 | AR8: D | AS8: D | AT8: C | AU8: A | AV8: A | AW8: B | AX8: E | AY8: E | AZ8: B
A9: 2019 | B9: 123569 | C9: 8 | D9: 1 | E9: 0 | F9: 0 | G9: 27 | H9: 3 | I9: 4 | J9: 0 | K9: ZDCBCCDB | L9: ZDEBDAEBXDACZXCBXDCZABBEDXC | M9: CDCDCCCC | N9: 81101100 | O9: EDDDEBDBCDBBDCCCADBCCCCCCCD | P9: 8.1000002e+26 | Q9: 555 | R9: 555 | S9: 555 | T9: 555 | U9: 555 | V9: 555 | W9: 333 | X9: 555 | Y9: 555 | Z9: 666 | AA9: 555 | AB9: 25.3 | AC9: 37.1 | AD9: 57.1 | AE9: 7 | AF9: 0 | AG9: 0 | AH9: 0 | AI9: 14 | AJ9: 70 | AK9: 0 | AL9: 21.3 | AM9: 25 | AN9: 0 | AO9: 0 | AP9: 0 | AQ9: 0 | AR9: C | AS9: C | AT9: A | AU9: E | AV9: B | AW9: E | AX9: D | AY9: E | AZ9: B
A10: 2019 | B10: 1103831 | C10: 8 | D10: 1 | E10: 0 | F10: 0 | G10: 27 | H10: 3 | I10: 2 | J10: 0 | K10: ZDCBCCDB | L10: ZBBZBEBEDDEDDAZXCDEECACAXAB | M10: ADDBCDDC | N10: 81011010 | O10: EBABDEDBCADBECDADBCEADBECAE | P10: 8.10801e+26 | Q10: 555 | R10: 555 | S10: 555 | T10: 555 | U10: 555 | V10: 555 | W10: 555 | X10: 555 | Y10: 555 | Z10: 555 | AA10: 555 | AB10: 26.2 | AC10: 39.7 | AD10: 57.1 | AE10: 13.5 | AF10: 13 | AG10: 65 | AH10: 0 | AI10: 14 | AJ10: 70 | AK10: 0 | AL10: 21.7 | AM10: 18.2 | AN10: 41.7 | AO10: 30 | AP10: 40 | AQ10: 55 | AR10: D | AS10: D | AT10: C | AU10: B | AV10: B | AW10: C | AX10: D | AY10: C | AZ10: C
A11: 2019 | B11: 121880 | C11: 8 | D11: 1 | E11: 0 | F11: 0 | G11: 27 | H11: 0 | I11: 4 | J11: 0 | K11: ZDCBCCDB | L11: BXCAXDEXCBECDACEDACADEBXBBE | M11: ADDAEBDA | N11: 81000010 | O11: ABBAABCDCECCDADECACBBBDCDCD | P11: 9.0190091e+25 | Q11: 555 | R11: 555 | S11: 555 | T11: 333 | U11: 555 | V11: 333 | W11: 333 | X11: 333 | Y11: 333 | Z11: 333 | AA11: 333 | AB11: 26.5 | AC11: 17.2 | AD11: 28.6 | AE11: 0 | AF11: 0 | AG11: 0 | AH11: 0 | AI11: 0 | AJ11: 0 | AK11: 0 | AL11: 29.6 | AM11: 34.8 | AN11: 0 | AO11: 0 | AP11: 0 | AQ11: 0 | AR11: C | AS11: C | AT11: C | AU11: A | AV11: A | AW11: C | AX11: E | AY11: D | AZ11: D
A12: 2019 | B12: 1181815 | C12: 8 | D12: 1 | E12: 0 | F12: 0 | G12: 27 | H12: 3 | I12: 4 | J12: 0 | K12: ZDCBCCDB | L12: ZDEBDAEBXDACZXCBXDCZABBEDXC | M12: BDCADEEE | N12: 81100000 | O12: CCADDACBBAEBEDDADECCBACEADC | P12: 8.0001102e+26 | Q12: 555 | R12: 555 | S12: 555 | T12: 555 | U12: 555 | V12: 555 | W12: 555 | X12: 555 | Y12: 555 | Z12: 666 | AA12: 555 | AB12: 26.6 | AC12: 21 | AD12: 28.6 | AE12: 9.5 | AF12: 8 | AG12: 40 | AH12: 0 | AI12: 11 | AJ12: 55 | AK12: 0 | AL12: 28.5 | AM12: 30 | AN12: 20 | AO12: 25 | AP12: 0 | AQ12: 15 | AR12: C | AS12: C | AT12: D | AU12: E | AV12: B | AW12: C | AX12: C | AY12: E | AZ12: D
A13: 2019 | B13: 123569 | C13: 8 | D13: 1 | E13: 0 | F13: 0 | G13: 27 | H13: 3 | I13: 4 | J13: 0 | K13: ZDCBCCDB | L13: ZDEBDAEBXDACZXCBXDCZABBEDXC | M13: ADBCEABB | N13: 81000001 | O13: EBEDEDAACDABCDCBDBECACCBABA | P13: 8.0100001e+26 | Q13: 555 | R13: 555 | S13: 555 | T13: 555 | U13: 555 | V13: 555 | W13: 555 | X13: 555 | Y13: 555 | Z13: 666 | AA13: 555 | AB13: 27.2 | AC13: 26.4 | AD13: 28.6 | AE13: 23 | AF13: 14 | AG13: 70 | AH13: 0 | AI13: 32 | AJ13: 60 | AK13: 25 | AL13: 27.4 | AM13: 30 | AN13: 12.5 | AO13: 25 | AP13: 0 | AQ13: 0 | AR13: C | AS13: C | AT13: C | AU13: B | AV13: A | AW13: B | AX13: D | AY13: C | AZ13: B
A14: 2019 | B14: 88399 | C14: 8 | D14: 1 | E14: 0 | F14: 0 | G14: 27 | H14: 5 | I14: 3 | J14: 0 | K14: ZDCBCCDB | L14: ZAXDBBAXDABEEZECZAEZBCXBZBC | M14: DDCADBDE | N14: 81100010 | O14: CABCBBCCEBACBCCDCDECDCCAAAB | P14: 8.1901109e+26 | Q14: 555 | R14: 555 | S14: 555 | T14: 555 | U14: 555 | V14: 555 | W14: 555 | X14: 555 | Y14: 555 | Z14: 555 | AA14: 333 | AB14: 27.4 | AC14: 42.3 | AD14: 42.9 | AE14: 41.5 | AF14: 32 | AG14: 80 | AH14: 20 | AI14: 51 | AJ14: 55 | AK14: 50 | AL14: 22.4 | AM14: 26.3 | AN14: 0 | AO14: 0 | AP14: 0 | AQ14: 0 | AR14: C | AS14: D | AT14: C | AU14: B | AV14: C | AW14: D | AX14: D | AY14: C | AZ14: C
... A77: 2019 | B77: 123569 | C77: 8 | D77: 1 | E77: 0 | F77: 0 | G77: 27 | H77: 3 | I77: 4 | J77: 0 | K77: ZDCBCCDB | L77: ZDEBDAEBXDACZXCBXDCZABBEDXC | M77: ADDBAAEB | N77: 81010001 | O77: EDAAEBBBEAACDDCBAECEDCBEADB | P77: 8.1000002e+26 | Q77: 555 | R77: 555 | S77: 555 | T77: 555 | U77: 555 | V77: 555 | W77: 555 | X77: 555 | Y77: 555 | Z77: 666 | AA77: 555 | AB77: 39.2 | AC77: 41.7 | AD77: 42.9 | AE77: 40 | AF77: 8 | AG77: 40 | AH77: 0 | AI77: 72 | AJ77: 60 | AK77: 75 | AL77: 38.3 | AM77: 45 | AN77: 0 | AO77: 0 | AP77: 0 | AQ77: 0 | AR77: C | AS77: D | AT77: C | AU77: A | AV77: A | AW77: C | AX77: D | AY77: C | AZ77: B
A78: 2019 | B78: 88399 | C78: 8 | D78: 1 | E78: 0 | F78: 0 | G78: 27 | H78: 5 | I78: 3 | J78: 0 | K78: ZDCBCCDB | L78: ZAXDBBAXDABEEZECZAEZBCXBZBC | M78: ADCBACDB | N78: 81110111 | O78: EBBDBBEABCADEDBEBDEDCADABBB | P78: 8.0911109e+26 | Q78: 555 | R78: 555 | S78: 555 | T78: 555 | U78: 555 | V78: 555 | W78: 555 | X78: 555 | Y78: 333 | Z78: 333 | AA78: 555 | AB78: 39.3 | AC78: 65.8 | AD78: 85.7 | AE78: 36 | AF78: 16 | AG78: 80 | AH78: 0 | AI78: 56 | AJ78: 80 | AK78: 50 | AL78: 30.4 | AM78: 31.6 | AN78: 23.3 | AO78: 0 | AP78: 0 | AQ78: 70
A79: 2019 | B79: 123569 | C79: 8 | D79: 1 | E79: 0 | F79: 0 | G79: 27 | H79: 3 | I79: 4 | J79: 0 | K79: ZDCBCCDB | L79: ZDEBDAEBXDACZXCBXDCZABBEDXC | M79: EDEBDCDC | N79: 81010110 | O79: EAEDCABADDACCEAABECBEEBEAAB | P79: 8.0100101e+26 | Q79: 555 | R79: 555 | S79: 555 | T79: 555 | U79: 555 | V79: 555 | W79: 555 | X79: 555 | Y79: 555 | Z79: 666 | AA79: 555 | AB79: 39.5 | AC79: 50.3 | AD79: 57.1 | AE79: 40 | AF79: 44 | AG79: 40 | AH79: 45 | AI79: 36 | AJ79: 80 | AK79: 25 | AL79: 35.9 | AM79: 40 | AN79: 12.5 | AO79: 25 | AP79: 0 | AQ79: 0 | AR79: C | AS79: D | AT79: A | AU79: B | AV79: B | AW79: C | AX79: D | AY79: D | AZ79: D
A80: 2019 | B80: 1181815 | C80: 8 | D80: 1 | E80: 0 | F80: 0 | G80: 27 | H80: 3 | I80: 4 | J80: 0 | K80: ZDCBCCDB | L80: ZDEBDAEBXDACZXCBXDCZABBEDXC | M80: ADCBCCDC | N80: 81111110 | O80: CBEBEDACDAABCDDBEDBDAABCAAB | P80: 8.0110001e+26 | Q80: 555 | R80: 555 | S80: 555 | T80: 555 | U80: 555 | V80: 555 | W80: 555 | X80: 555 | Y80: 555 | Z80: 666 | AA80: 555 | AB80: 39.6 | AC80: 63.6 | AD80: 85.7 | AE80: 30.5 | AF80: 47 | AG80: 55 | AH80: 45 | AI80: 14 | AJ80: 70 | AK80: 0 | AL80: 31.6 | AM80: 35 | AN80: 12.5 | AO80: 25 | AP80: 0 | AQ80: 0 | AR80: C | AS80: C | AT80: C | AU80: B | AV80: B | AW80: C | AX80: D | AY80: E | AZ80: D
A81: 2019 | B81: 1117583 | C81: 8 | D81: 1 | E81: 0 | F81: 0 | G81: 27 | H81: 3 | I81: 2 | J81: 0 | K81: ZDCBCCDB | L81: ZBBZBEBEDDEDDAZXCDEECACAXAB | M81: EDACADDE | N81: 81000010 | O81: ADBBACBEEDCBDAEBCBBAADAAAAB | P81: 8.0180011e+26 | Q81: 555 | R81: 555 | S81: 555 | T81: 555 | U81: 555 | V81: 555 | W81: 555 | X81: 555 | Y81: 555 | Z81: 555 | AA81: 555 | AB81: 39.7 | AC81: 20 | AD81: 28.6 | AE81: 7 | AF81: 5 | AG81: 25 | AH81: 0 | AI81: 9 | AJ81: 45 | AK81: 0 | AL81: 46.2 | AM81: 45.5 | AN81: 50 | AO81: 40 | AP81: 55 | AQ81: 55 | AR81: C | AS81: C | AT81: B | AU81: D | AV81: B | AW81: C | AX81: B | AY81: D | AZ81: D
A82: 2019 | B82: 123569 | C82: 8 | D82: 1 | E82: 0 | F82: 0 | G82: 27 | H82: 3 | I82: 4 | J82: 0 | K82: ZDCBCCDB | L82: ZDEBDAEBXDACZXCBXDCZABBEDXC | M82: ADCBECDB | N82: 81110111 | O82: ECEBECDACBDDCABDEEAAACCEDBC | P82: 8.0110001e+26 | Q82: 555 | R82: 555 | S82: 555 | T82: 555 | U82: 555 | V82: 555 | W82: 555 | X82: 555 | Y82: 555 | Z82: 666 | AA82: 555 | AB82: 39.8 | AC82: 63.4 | AD82: 85.7 | AE82: 30 | AF82: 8 | AG82: 40 | AH82: 0 | AI82: 52 | AJ82: 60 | AK82: 50 | AL82: 31.9 | AM82: 30 | AN82: 42.5 | AO82: 75 | AP82: 0 | AQ82: 10 | AR82: C | AS82: D | AT82: D | AU82: A | AV82: A | AW82: A | AX82: E | AY82: D | AZ82: E
A83: 2019 | B83: 123569 | C83: 8 | D83: 1 | E83: 0 | F83: 0 | G83: 27 | H83: 3 | I83: 4 | J83: 0 | K83: ZDCBCCDB | L83: ZDEBDAEBXDACZXCBXDCZABBEDXC | M83: CDCCACDC | N83: 81100110 | O83: ADBBEBCABDACCBBDAECDACCCDAB | P83: 8.1010001e+26 | Q83: 555 | R83: 555 | S83: 555 | T83: 555 | U83: 555 | V83: 555 | W83: 555 | X83: 555 | Y83: 555 | Z83: 666 | AA83: 555 | AB83: 40 | AC83: 37.5 | AD83: 57.1 | AE83: 8 | AF83: 5 | AG83: 25 | AH83: 0 | AI83: 11 | AJ83: 55 | AK83: 0 | AL83: 40.8 | AM83: 40 | AN83: 45 | AO83: 50 | AP83: 0 | AQ83: 40 | AR83: C | AS83: C | AT83: C | AU83: A | AV83: A | AW83: B | AX83: E | AY83: D | AZ83: D
A84: 2019 | B84: 121884 | C84: 8 | D84: 1 | E84: 0 | F84: 0 | G84: 27 | H84: 1 | I84: 3 | J84: 0 | K84: ZDCBCCDB | L84: AEDBBEDCBCDEBCAZADCXBXCAADX | M84: BECBECEB | N84: 80110101 | O84: EEDBBCCCDBDDDCCBAEEADECCBDC | P84: 1.111001e+25 | Q84: 555 | R84: 555 | S84: 555 | T84: 555 | U84: 555 | V84: 555 | W84: 555 | X84: 555 | Y84: 555 | Z84: 555 | AA84: 555 | AB84: 40.1 | AC84: 42.7 | AD84: 57.1 | AE84: 21 | AF84: 24 | AG84: 40 | AH84: 20 | AI84: 18 | AJ84: 90 | AK84: 0 | AL84: 39.2 | AM84: 43.5 | AN84: 15 | AO84: 15 | AP84: 30 | AQ84: 0 | AR84: C | AS84: C | AT84: C | AU84: B | AV84: B | AW84: B | AX84: E | AY84: D | AZ84: C
A85: 2019 | B85: 88399 | C85: 8 | D85: 1 | E85: 0 | F85: 0 | G85: 27 | H85: 5 | I85: 3 | J85: 0 | K85: ZDCBCCDB | L85: ZAXDBBAXDABEEZECZAEZBCXBZBC | M85: BDCCAEDB | N85: 81100011 | O85: ECCCBDACDCCCEECECBEDCECCBBC | P85: 8.0901019e+26 | Q85: 555 | R85: 555 | S85: 555 | T85: 555 | U85: 555 | V85: 555 | W85: 555 | X85: 555 | Y85: 555 | Z85: 333 | AA85: 555 | AB85: 40.3 | AC85: 52.1 | AD85: 57.1 | AE85: 44.5 | AF85: 13 | AG85: 65 | AH85: 0 | AI85: 76 | AJ85: 80 | AK85: 75 | AL85: 36.3 | AM85: 36.8 | AN85: 33.3 | AO85: 0 | AP85: 0 | AQ85: 100 | AR85: C | AS85: D | AT85: E | AU85: B | AV85: B | AW85: C | AX85: B | AY85: D | AZ85: D
A86: 2019 | B86: 88399 | C86: 8 | D86: 1 | E86: 0 | F86: 0 | G86: 27 | H86: 5 | I86: 3 | J86: 0 | K86: ZDCBCCDB | L86: ZAXDBBAXDABEEZECZAEZBCXBZBC | M86: BDCBCADB | N86: 81111011 | O86: ECBBEBAABABAAEBAADEDBCACBED | P86: 8.0900119e+26 | Q86: 555 | R86: 555 | S86: 555 | T86: 555 | U86: 555 | V86: 333 | W86: 555 | X86: 555 | Y86: 333 | Z86: 333 | AA86: 333 | AB86: 40.4 | AC86: 67.8 | AD86: 85.7 | AE86: 41 | AF86: 15 | AG86: 75 | AH86: 0 | AI86: 67 | AJ86: 35 | AK86: 75 | AL86: 31.3 | AM86: 36.8 | AN86: 0 | AO86: 0 | AP86: 0 | AQ86: 0 | AR86: C | AS86: D | AT86: A | AU86: B | AV86: B | AW86: C | AX86: B | AY86: D | AZ86: E
A87: 2019 | B87: 121880 | C87: 8 | D87: 1 | E87: 0 | F87: 0 | G87: 27 | H87: 0 | I87: 4 | J87: 0 | K87: ZDCBCCDB | L87: BXCAXDEXCBECDACEDACADEBXBBE | M87: DDCBAADB | N87: 81110011 | O87: AEDABACECACEDEAECCABDEAEBBC | P87: 9.0190091e+25 | Q87: 555 | R87: 555 | S87: 555 | T87: 555 | U87: 555 | V87: 555 | W87: 555 | X87: 555 | Y87: 555 | Z87: 555 | AA87: 555 | AB87: 40.5 | AC87: 58 | AD87: 71.4 | AE87: 38 | AF87: 22 | AG87: 30 | AH87: 20 | AI87: 54 | AJ87: 70 | AK87: 50 | AL87: 34.6 | AM87: 34.8 | AN87: 33.3 | AO87: 0 | AP87: 100 | AQ87: 0 | AR87: C | AS87: C | AT87: C | AU87: B | AV87: C | AW87: C | AX87: B | AY87: D | AZ87: C
A88: 2019 | B88: 88399 | C88: 8 | D88: 1 | E88: 0 | F88: 0 | G88: 27 | H88: 5 | I88: 3 | J88: 0 | K88: ZDCBCCDB | L88: ZAXDBBAXDABEEZECZAEZBCXBZBC | M88: DDCCEBEE | N88: 81100000 | O88: CCCBBBECBADAEDCDDEDDBCEABBC | P88: 8.0901109e+26 | Q88: 555 | R88: 555 | S88: 555 | T88: 555 | U88: 555 | V88: 555 | W88: 555 | X88: 555 | Y88: 333 | Z88: 333 | AA88: 555 | AB88: 41.3 | AC88: 44.2 | AD88: 28.6 | AE88: 67.5 | AF88: 83 | AG88: 55 | AH88: 90 | AI88: 52 | AJ88: 60 | AK88: 50 | AL88: 40.3 | AM88: 42.1 | AN88: 30 | AO88: 0 | AP88: 0 | AQ88: 90 | AR88: C | AS88: D | AT88: B | AU88: B | AV88: B | AW88: C | AX88: D | AY88: D | AZ88: E
A89: 2019 | B89: 123569 | C89: 8 | D89: 1 | E89: 0 | F89: 0 | G89: 27 | H89: 3 | I89: 4 | J89: 0 | K89: ZDCBCCDB | L89: ZDEBDAEBXDACZXCBXDCZABBEDXC | M89: ADCBAAEB | N89: 81110001 | O89: EBEAEBBAEDADCCCCCEBCABBDDAA | P89: 8.0100001e+26 | Q89: 555 | R89: 555 | S89: 555 | T89: 555 | U89: 555 | V89: 555 | W89: 555 | X89: 555 | Y89: 555 | Z89: 666 | AA89: 333 | AB89: 41.7 | AC89: 55.7 | AD89: 57.1 | AE89: 53.5 | AF89: 49 | AG89: 65 | AH89: 45 | AI89: 58 | AJ89: 90 | AK89: 50 | AL89: 37 | AM89: 40 | AN89: 20 | AO89: 40 | AP89: 0 | AQ89: 0 | AR89: C | AS89: E | AT89: C | AU89: B | AV89: B | AW89: D | AX89: B | AY89: D | AZ89: C
A90: 2019 | B90: 1181815 | C90: 8 | D90: 1 | E90: 0 | F90: 0 | G90: 27 | H90: 3 | I90: 4 | J90: 0 | K90: ZDCBCCDB | L90: ZDEBDAEBXDACZXCBXDCZABBEDXC | M90: CDDBECDE | N90: 81010110 | O90: ECABEABBDDABEBCAACCCAACEECB | P90: 8.0010102e+26 | Q90: 555 | R90: 555 | S90: 555 | T90: 555 | U90: 555 | V90: 555 | W90: 333 | X90: 555 | Y90: 555 | Z90: 666 | AA90: 333 | AB90: 41.7 | AC90: 40.7 | AD90: 57.1 | AE90: 16 | AF90: 0 | AG90: 0 | AH90: 0 | AI90: 32 | AJ90: 60 | AK90: 25 | AL90: 42 | AM90: 45 | AN90: 25 | AO90: 50 | AP90: 0 | AQ90: 0 | AR90: D | AS90: D | AT90: C | AU90: B | AV90: A | AW90: C | AX90: B | AY90: C | AZ90: D
... A96: 2019 | B96: 1181815 | C96: 8 | D96: 1 | E96: 0 | F96: 0 | G96: 27 | H96: 3 | I96: 4 | J96: 0 | K96: ZDCBCCDB | L96: ZDEBDAEBXDACZXCBXDCZABBEDXC | M96: EDDACCDC | N96: 81001110 | O96: ADAECDBBBDACECCAEECDAABAAAA | P96: 8.1000002e+26 | Q96: 555 | R96: 555 | S96: 555 | T96: 555 | U96: 555 | V96: 555 | W96: 555 | X96: 555 | Y96: 555 | Z96: 666 | AA96: 555 | AB96: 42.3 | AC96: 46.5 | AD96: 57.1 | AE96: 30.5 | AF96: 50 | AG96: 70 | AH96: 45 | AI96: 11 | AJ96: 55 | AK96: 0 | AL96: 40.9 | AM96: 45 | AN96: 17.5 | AO96: 25 | AP96: 0 | AQ96: 10 | AR96: C | AS96: C | AT96: B | AU96: A | AV96: A | AW96: C | AX96: D | AY96: D | AZ96: D
A97: 2019 | B97: 102499 | C97: 8 | D97: 1 | E97: 0 | F97: 0 | G97: 27 | H97: 1 | I97: 5 | J97: 0 | K97: ZDCBCCDB | L97: BXBCDXEBAAEDAABXECCCDXXCAAZ | M97: EECAACEB | N97: 80100101 | O97: BADDBAEBAAEDBBBADCBCBDEDDDD | P97: 1.9000911e+26 | Q97: 555 | R97: 555 | S97: 555 | T97: 555 | U97: 555 | V97: 555 | W97: 555 | X97: 555 | Y97: 555 | Z97: 333 | AA97: 555 | AB97: 42.4 | AC97: 42.1 | AD97: 42.9 | AE97: 41 | AF97: 33 | AG97: 85 | AH97: 20 | AI97: 49 | AJ97: 45 | AK97: 50 | AL97: 42.5 | AM97: 47.6 | AN97: 13.3 | AO97: 40 | AP97: 0 | AQ97: 0
A98: 2019 | B98: 1181819 | C98: 8 | D98: 1 | E98: 0 | F98: 0 | G98: 27 | H98: 0 | I98: 2 | J98: 0 | K98: ZDCBCCDB | L98: DBCDECEDACECCDDBCADACEAXEXD | M98: ADCDDAEC | N98: 81100000 | O98: DCCEECDACEECADDBEADCCDEACAD | P98: 1.01011e+26 | Q98: 555 | R98: 555 | S98: 555 | T98: 555 | U98: 555 | V98: 555 | W98: 555 | X98: 555 | Y98: 555 | Z98: 555 | AA98: 555 | AB98: 42.5 | AC98: 27.4 | AD98: 28.6 | AE98: 25.5 | AF98: 24 | AG98: 40 | AH98: 20 | AI98: 27 | AJ98: 35 | AK98: 25 | AL98: 47.5 | AM98: 52 | AN98: 21.7 | AO98: 25 | AP98: 20 | AQ98: 20 | AR98: C | AS98: C | AT98: C | AU98: A | AV98: B | AW98: B | AX98: A | AY98: D | AZ98: C
A99: 2019 | B99: 88399 | C99: 8 | D99: 1 | E99: 0 | F99: 0 | G99: 27 | H99: 5 | I99: 3 | J99: 0 | K99: ZDCBCCDB | L99: ZAXDBBAXDABEEZECZAEZBCXBZBC | M99: ADCCEBDB | N99: 81100011 | O99: EBAEDBEDBEBAEEEEDEBCCEECABC | P99: 8.0900109e+26 | Q99: 555 | R99: 555 | S99: 555 | T99: 555 | U99: 555 | V99: 555 | W99: 555 | X99: 555 | Y99: 333 | Z99: 555 | AA99: 555 | AB99: 42.6 | AC99: 67.1 | AD99: 57.1 | AE99: 82 | AF99: 70 | AG99: 90 | AH99: 65 | AI99: 94 | AJ99: 70 | AK99: 100 | AL99: 34.4 | AM99: 31.6 | AN99: 50 | AO99: 0 | AP99: 50 | AQ99: 100 | AR99: C | AS99: C | AT99: C | AU99: B | AV99: B | AW99: C | AX99: D | AY99: D | AZ99: D
A100: 2019 | B100: 102499 | C100: 8 | D100: 1 | E100: 0 | F100: 0 | G100: 27 | H100: 1 | I100: 5 | J100: 0 | K100: ZDCBCCDB | L100: BXBCDXEBAAEDAABXECCCDXXCAAZ | M100: BDCCEADB | N100: 81100011 | O100: CABCCEEEADEDBBBAACAABCEEAAE | P100: 9.1109101e+25 | Q100: 555 | R100: 555 | S100: 555 | T100: 555 | U100: 555 | V100: 555 | W100: 555 | X100: 555 | Y100: 333 | Z100: 333 | AA100: 555 | AB100: 42.6 | AC100: 48.7 | AD100: 57.1 | AE100: 36 | AF100: 16 | AG100: 80 | AH100: 0 | AI100: 56 | AJ100: 80 | AK100: 50 | AL100: 40.5 | AM100: 47.6 | AN100: 0 | AO100: 0 | AP100: 0 | AQ100: 0 | AR100: C | AS100: C | AT100: A | AU100: A | AV100: A | AW100: D | AX100: E | AY100: D | AZ100: E
A101: 2019 | B101: 88399 | C101: 8 | D101: 1 | E101: 0 | F101: 0 | G101: 27 | H101: 5 | I101: 3 | J101: 0 | K101: ZDCBCCDB | L101: ZAXDBBAXDABEEZECZAEZBCXBZBC | M101: EDCBACEC | N101: 81110100 | O101: EABABAACECAAEDACAAACACEBABC | P101: 8.1901019e+26 | Q101: 555 | R101: 555 | S101: 555 | T101: 555 | U101: 555 | V101: 333 | W101: 555 | X101: 555 | Y101: 333 | Z101: 333 | AA101: 333 | AB101: 42.9 | AC101: 37.3 | AD101: 57.1 | AE101: 7.5 | AF101: 6 | AG101: 30 | AH101: 0 | AI101: 9 | AJ101: 45 | AK101: 0 | AL101: 44.7 | AM101: 52.6 | AN101: 0 | AO101: 0 | AP101: 0 | AQ101: 0 | AR101: C | AS101: C | AT101: C | AU101: B | AV101: B | AW101: B | AX101: A | AY101: C | AZ101: B
A102: 2019 | B102: 121880 | C102: 8 | D102: 1 | E102: 0 | F102: 0 | G102: 27 | H102: 0 | I102: 4 | J102: 0 | K102: ZDCBCCDB | L102: BXCAXDEXCBECDACEDACADEBXBBE | M102: EDCBBCDA | N102: 81110110 | O102: BCDAECCECBEEDACEBCBDDBCADAC | P102: 1.9019009e+26 | Q102: 555 | R102: 555 | S102: 555 | T102: 333 | U102: 555 | V102: 555 | W102: 333 | X102: 333 | Y102: 555 | Z102: 333 | AA102: 555 | AB102: 43 | AC102: 42.8 | AD102: 71.4 | AE102: 0 | AF102: 0 | AG102: 0 | AH102: 0 | AI102: 0 | AJ102: 0 | AK102: 0 | AL102: 43 | AM102: 43.5 | AN102: 40 | AO102: 70 | AP102: 0 | AQ102: 50 | AR102: B | AS102: B | AT102: C | AU102: C | AV102: B | AW102: B | AX102: E | AY102: E | AZ102: B
A103: 2019 | B103: 102499 | C103: 8 | D103: 1 | E103: 0 | F103: 0 | G103: 27 | H103: 1 | I103: 5 | J103: 0 | K103: ZDCBCCDB | L103: BXBCDXEBAAEDAABXECCCDXXCAAZ | M103: CACBAAED | N103: 80110000 | O103: BABBCDEDCAEDDBBDBECBDECCABD | P103: 1.910091e+26 | Q103: 555 | R103: 555 | S103: 555 | T103: 555 | U103: 555 | V103: 555 | W103: 555 | X103: 555 | Y103: 555 | Z103: 333 | AA103: 333 | AB103: 43.3 | AC103: 35 | AD103: 28.6 | AE103: 44.5 | AF103: 15 | AG103: 75 | AH103: 0 | AI103: 74 | AJ103: 70 | AK103: 75 | AL103: 46 | AM103: 52.4 | AN103: 10 | AO103: 30 | AP103: 0 | AQ103: 0 | AR103: D | AS103: D | AT103: C | AU103: B | AV103: A | AW103: B | AX103: D | AY103: D | AZ103: C
A104: 2019 | B104: 123569 | C104: 8 | D104: 1 | E104: 0 | F104: 0 | G104: 27 | H104: 3 | I104: 4 | J104: 0 | K104: ZDCBCCDB | L104: ZDEBDAEBXDACZXCBXDCZABBEDXC | M104: CDDBACDB | N104: 81010111 | O104: CBEACDADDCABCCBAEBCBADBCDAE | P104: 8.0100001e+26 | Q104: 555 | R104: 555 | S104: 555 | T104: 555 | U104: 555 | V104: 555 | W104: 555 | X104: 555 | Y104: 555 | Z104: 666 | AA104: 555 | AB104: 43.4 | AC104: 73.2 | AD104: 71.4 | AE104: 76 | AF104: 58 | AG104: 30 | AH104: 65 | AI104: 94 | AJ104: 70 | AK104: 100 | AL104: 33.4 | AM104: 30 | AN104: 52.5 | AO104: 50 | AP104: 0 | AQ104: 55 | AR104: C | AS104: D | AT104: C | AU104: A | AV104: A | AW104: D | AX104: A | AY104: D | AZ104: D
A105: 2019 | B105: 121880 | C105: 8 | D105: 1 | E105: 0 | F105: 0 | G105: 27 | H105: 0 | I105: 4 | J105: 0 | K105: ZDCBCCDB | L105: BXCAXDEXCBECDACEDACADEBXBBE | M105: DDCBABDB | N105: 81110011 | O105: BACAEAEEECEBBDCEBBDCCCBCDDC | P105: 1.9119019e+26 | Q105: 555 | R105: 555 | S105: 555 | T105: 555 | U105: 555 | V105: 555 | W105: 555 | X105: 555 | Y105: 555 | Z105: 555 | AA105: 555 | AB105: 43.7 | AC105: 57.6 | AD105: 71.4 | AE105: 37 | AF105: 43 | AG105: 55 | AH105: 40 | AI105: 31 | AJ105: 55 | AK105: 25 | AL105: 39.1 | AM105: 34.8 | AN105: 63.3 | AO105: 50 | AP105: 90 | AQ105: 50 | AR105: C | AS105: B | AT105: C | AU105: A | AV105: A | AW105: B | AX105: B | AY105: D | AZ105: C
A106: 2019 | B106: 121880 | C106: 8 | D106: 1 | E106: 0 | F106: 0 | G106: 27 | H106: 0 | I106: 4 | J106: 0 | K106: ZDCBCCDB | L106: BXCAXDEXCBECDACEDACADEBXBBE | M106: EDCCABDB | N106: 81100011 | O106: BCCABBCECBECEBCBBDCEACDBCBE | P106: 1.9119009e+26 | Q106: 555 | R106: 555 | S106: 555 | T106: 555 | U106: 555 | V106: 333 | W106: 555 | X106: 555 | Y106: 333 | Z106: 333 | AA106: 333 | AB106: 43.7 | AC106: 52.9 | AD106: 57.1 | AE106: 46.5 | AF106: 62 | AG106: 50 | AH106: 65 | AI106: 31 | AJ106: 55 | AK106: 25 | AL106: 40.6 | AM106: 47.8 | AN106: 0 | AO106: 0 | AP106: 0 | AQ106: 0 | AR106: B | AS106: C | AT106: C | AU106: B | AV106: B | AW106: B | AX106: B | AY106: D | AZ106: B
A107: 2019 | B107: 121884 | C107: 8 | D107: 1 | E107: 0 | F107: 0 | G107: 27 | H107: 1 | I107: 3 | J107: 0 | K107: ZDCBCCDB | L107: AEDBBEDCBCDEBCAZADCXBXCAADX | M107: ADCAECEE | N107: 81100100 | O107: AEDBBEBEDCDBDADDCEDBDBCAEDC | P107: 1.11111e+26 | Q107: 555 | R107: 555 | S107: 555 | T107: 555 | U107: 555 | V107: 555 | W107: 555 | X107: 555 | Y107: 555 | Z107: 555 | AA107: 555 | AB107: 43.7 | AC107: 36.9 | AD107: 42.9 | AE107: 28 | AF107: 7 | AG107: 35 | AH107: 0 | AI107: 49 | AJ107: 45 | AK107: 50 | AL107: 45.9 | AM107: 47.8 | AN107: 35 | AO107: 25 | AP107: 30 | AQ107: 50 | AR107: C | AS107: C | AT107: A | AU107: D | AV107: C | AW107: C | AX107: D | AY107: C | AZ107: B
A108: 2019 | B108: 123569 | C108: 8 | D108: 1 | E108: 0 | F108: 0 | G108: 27 | H108: 3 | I108: 4 | J108: 0 | K108: ZDCBCCDB | L108: ZDEBDAEBXDACZXCBXDCZABBEDXC | M108: CDABABDB | N108: 81010011 | O108: ADEAEAEAEDACCDCDEECCACBCCBE | P108: 8.1100111e+26 | Q108: 555 | R108: 555 | S108: 555 | T108: 333 | U108: 555 | V108: 555 | W108: 333 | X108: 333 | Y108: 333 | Z108: 666 | AA108: 555 | AB108: 43.7 | AC108: 34.3 | AD108: 57.1 | AE108: 0 | AF108: 0 | AG108: 0 | AH108: 0 | AI108: 0 | AJ108: 0 | AK108: 0 | AL108: 46.8 | AM108: 55 | AN108: 0 | AO108: 0 | AP108: 0 | AQ108: 0 | AR108: C | AS108: C | AT108: C | AU108: B | AV108: B | AW108: C | AX108: A | AY108: D | AZ108: D
A109: 2019 | B109: 121884 | C109: 8 | D109: 1 | E109: 0 | F109: 0 | G109: 27 | H109: 1 | I109: 3 | J109: 0 | K109: ZDCBCCDB | L109: AEDBBEDCBCDEBCAZADCXBXCAADX | M109: ADDBAEDB | N109: 81010011 | O109: CCBEBECBBECBBCADDECABCECADA | P109: 1.1001e+22 | Q109: 555 | R109: 555 | S109: 555 | T109: 555 | U109: 555 | V109: 555 | W109: 555 | X109: 555 | Y109: 555 | Z109: 555 | AA109: 555 | AB109: 43.9 | AC109: 54.9 | AD109: 57.1 | AE109: 51.5 | AF109: 29 | AG109: 65 | AH109: 20 | AI109: 74 | AJ109: 70 | AK109: 75 | AL109: 40.2 | AM109: 43.5 | AN109: 21.7 | AO109: 0 | AP109: 65 | AQ109: 0 | AR109: C | AS109: D | AT109: C | AU109: A | AV109: A | AW109: B | AX109: D | AY109: E | AZ109: C
... A334: 2019 | B334: 88399 | C334: 8 | D334: 1 | E334: 0 | F334: 0 | G334: 27 | H334: 5 | I334: 3 | J334: 0 | K334: ZDCBCCDB | L334: ZAXDBBAXDABEEZECZAEZBCXBZBC | M334: BDCBCCDB | N334: 81111111 | O334: AACDBBADDABEEDBCBAEDBCABBBA | P334: 8.1911119e+26 | Q334: 555 | R334: 555 | S334: 555 | T334: 555 | U334: 555 | V334: 555 | W334: 555 | X334: 555 | Y334: 555 | Z334: 555 | AA334: 555 | AB334: 87.7 | AC334: 84.8 | AD334: 100 | AE334: 62 | AF334: 68 | AG334: 80 | AH334: 65 | AI334: 56 | AJ334: 80 | AK334: 50 | AL334: 88.6 | AM334: 89.5 | AN334: 83.3 | AO334: 80 | AP334: 70 | AQ334: 100 | AR334: D | AS334: B | AT334: C | AU334: B | AV334: B | AW334: B | AX334: E | AY334: D | AZ334: D
A335: 2019 | B335: 88399 | C335: 8 | D335: 1 | E335: 0 | F335: 0 | G335: 27 | H335: 5 | I335: 3 | J335: 0 | K335: ZDCBCCDB | L335: ZAXDBBAXDABEEZECZAEZBCXBZBC | Q335: 222 | R335: 222 | S335: 222 | T335: 222 | U335: 222 | V335: 222 | W335: 222 | X335: 222 | Y335: 222 | Z335: 222 | AA335: 222
A336: 2019 | B336: 88399 | C336: 8 | D336: 1 | E336: 0 | F336: 0 | G336: 27 | H336: 5 | I336: 3 | J336: 0 | K336: ZDCBCCDB | L336: ZAXDBBAXDABEEZECZAEZBCXBZBC | Q336: 222 | R336: 222 | S336: 222 | T336: 222 | U336: 222 | V336: 222 | W336: 222 | X336: 222 | Y336: 222 | Z336: 222 | AA336: 222
A337: 2019 | B337: 88399 | C337: 8 | D337: 1 | E337: 0 | F337: 0 | G337: 27 | H337: 5 | I337: 3 | J337: 0 | K337: ZDCBCCDB | L337: ZAXDBBAXDABEEZECZAEZBCXBZBC | Q337: 222 | R337: 222 | S337: 222 | T337: 222 | U337: 222 | V337: 222 | W337: 222 | X337: 222 | Y337: 222 | Z337: 222 | AA337: 222
A338: 2019 | B338: 88399 | C338: 8 | D338: 1 | E338: 0 | F338: 0 | G338: 27 | H338: 5 | I338: 3 | J338: 0 | K338: ZDCBCCDB | L338: ZAXDBBAXDABEEZECZAEZBCXBZBC | Q338: 222 | R338: 222 | S338: 222 | T338: 222 | U338: 222 | V338: 222 | W338: 222 | X338: 222 | Y338: 222 | Z338: 222 | AA338: 222
A339: 2019 | B339: 102499 | C339: 8 | D339: 1 | E339: 0 | F339: 0 | G339: 27 | H339: 1 | I339: 5 | J339: 0 | K339: ZDCBCCDB | L339: BXBCDXEBAAEDAABXECCCDXXCAAZ | Q339: 222 | R339: 222 | S339: 222 | T339: 222 | U339: 222 | V339: 222 | W339: 222 | X339: 222 | Y339: 222 | Z339: 222 | AA339: 222
A340: 2019 | B340: 102499 | C340: 8 | D340: 1 | E340: 0 | F340: 0 | G340: 27 | H340: 1 | I340: 5 | J340: 0 | K340: ZDCBCCDB | L340: BXBCDXEBAAEDAABXECCCDXXCAAZ | Q340: 222 | R340: 222 | S340: 222 | T340: 222 | U340: 222 | V340: 222 | W340: 222 | X340: 222 | Y340: 222 | Z340: 222 | AA340: 222
A341: 2019 | B341: 102499 | C341: 8 | D341: 1 | E341: 0 | F341: 0 | G341: 27 | H341: 1 | I341: 5 | J341: 0 | K341: ZDCBCCDB | L341: BXBCDXEBAAEDAABXECCCDXXCAAZ | Q341: 222 | R341: 222 | S341: 222 | T341: 222 | U341: 222 | V341: 222 | W341: 222 | X341: 222 | Y341: 222 | Z341: 222 | AA341: 222
A342: 2019 | B342: 102499 | C342: 8 | D342: 1 | E342: 0 | F342: 0 | G342: 27 | H342: 1 | I342: 5 | J342: 0 | K342: ZDCBCCDB | L342: BXBCDXEBAAEDAABXECCCDXXCAAZ | Q342: 222 | R342: 222 | S342: 222 | T342: 222 | U342: 222 | V342: 222 | W342: 222 | X342: 222 | Y342: 222 | Z342: 222 | AA342: 222
A343: 2019 | B343: 102499 | C343: 8 | D343: 1 | E343: 0 | F343: 0 | G343: 27 | H343: 1 | I343: 5 | J343: 0 | K343: ZDCBCCDB | L343: BXBCDXEBAAEDAABXECCCDXXCAAZ | Q343: 222 | R343: 222 | S343: 222 | T343: 222 | U343: 222 | V343: 222 | W343: 222 | X343: 222 | Y343: 222 | Z343: 222 | AA343: 222
A344: 2019 | B344: 102499 | C344: 8 | D344: 1 | E344: 0 | F344: 0 | G344: 27 | H344: 1 | I344: 5 | J344: 0 | K344: ZDCBCCDB | L344: BXBCDXEBAAEDAABXECCCDXXCAAZ | Q344: 222 | R344: 222 | S344: 222 | T344: 222 | U344: 222 | V344: 222 | W344: 222 | X344: 222 | Y344: 222 | Z344: 222 | AA344: 222
A345: 2019 | B345: 102499 | C345: 8 | D345: 1 | E345: 0 | F345: 0 | G345: 27 | H345: 1 | I345: 5 | J345: 0 | K345: ZDCBCCDB | L345: BXBCDXEBAAEDAABXECCCDXXCAAZ | Q345: 222 | R345: 222 | S345: 222 | T345: 222 | U345: 222 | V345: 222 | W345: 222 | X345: 222 | Y345: 222 | Z345: 222 | AA345: 222
A346: 2019 | B346: 102499 | C346: 8 | D346: 1 | E346: 0 | F346: 0 | G346: 27 | H346: 1 | I346: 5 | J346: 0 | K346: ZDCBCCDB | L346: BXBCDXEBAAEDAABXECCCDXXCAAZ | Q346: 222 | R346: 222 | S346: 222 | T346: 222 | U346: 222 | V346: 222 | W346: 222 | X346: 222 | Y346: 222 | Z346: 222 | AA346: 222
... A368: 2019 | B368: 1181819 | C368: 8 | D368: 1 | E368: 0 | F368: 0 | G368: 27 | H368: 0 | I368: 2 | J368: 0 | K368: ZDCBCCDB | L368: DBCDECEDACECCDDBCADACEAXEXD | Q368: 222 | R368: 222 | S368: 222 | T368: 222 | U368: 222 | V368: 222 | W368: 222 | X368: 222 | Y368: 222 | Z368: 222 | AA368: 222

Sheet Arq_3B
A1: NU_ANO | B1: CO_CURSO | C1: DS_VT_GAB_OFG_FIN | D1: DS_VT_GAB_OCE_FIN | E1: DS_VT_ESC_OFG | F1: DS_VT_ESC_OCE | G1: Ob1 | H1: Ob2 | I1: Ob3 | J1: Ob4 | K1: Ob5 | L1: Ob6 | M1: Ob7 | N1: Ob8 | O1: CE1 | P1: CE2 | Q1: CE3 | R1: CE4 | S1: CE5 | T1: CE6 | U1: CE7 | V1: CE8 | W1: CE9 | X1: CE10 | Y1: CE11 | Z1: CE12 | AA1: CE13 | AB1: CE14 | AC1: CE15 | AD1: CE16 | AE1: CE17 | AF1: CE18 | AG1: CE19 | AH1: CE20 | AI1: CE21 | AJ1: CE22 | AK1: CE23 | AL1: CE24 | AM1: CE25 | AN1: CE26 | AO1: CE27
A2: 2019 | B2: 1117583 | C2: ZDCBCCDB | D2: ZBBZBEBEDDEDDAZXCDEECACAXAB | E2: ........ | F2: ........................... | G2: =IF(E2="","",IF(RIGHT(LEFT(E2,1))=".","B",IF(RIGHT(LEFT(E2,1))="*","M",IF(RIGHT(LEFT(C2,1))="Z",8,IF(RIGHT(LEFT(C2,1))="X",9,IF(RIGHT(LEFT(E2,1))=RIGHT(LEFT(C2,1)),1,0)))))) -> B | H2: =IF(E2="","",IF(RIGHT(LEFT(E2,2))=".","B",IF(RIGHT(LEFT(E2,2))="*","M",IF(RIGHT(LEFT(C2,2))="Z",8,IF(RIGHT(LEFT(C2,2))="X",9,IF(RIGHT(LEFT(E2,2))=RIGHT(LEFT(C2,2)),1,0)))))) -> B | I2: =IF(E2="","",IF(RIGHT(LEFT(E2,3))=".","B",IF(RIGHT(LEFT(E2,3))="*","M",IF(RIGHT(LEFT(C2,3))="Z",8,IF(RIGHT(LEFT(C2,3))="X",9,IF(RIGHT(LEFT(E2,3))=RIGHT(LEFT(C2,3)),1,0)))))) -> B | J2: =IF(E2="","",IF(RIGHT(LEFT(E2,4))=".","B",IF(RIGHT(LEFT(E2,4))="*","M",IF(RIGHT(LEFT(C2,4))="Z",8,IF(RIGHT(LEFT(C2,4))="X",9,IF(RIGHT(LEFT(E2,4))=RIGHT(LEFT(C2,4)),1,0)))))) -> B | K2: =IF(E2="","",IF(RIGHT(LEFT(E2,5))=".","B",IF(RIGHT(LEFT(E2,5))="*","M",IF(RIGHT(LEFT(C2,5))="Z",8,IF(RIGHT(LEFT(C2,5))="X",9,IF(RIGHT(LEFT(E2,5))=RIGHT(LEFT(C2,5)),1,0)))))) -> B | L2: =IF(E2="","",IF(RIGHT(LEFT(E2,6))=".","B",IF(RIGHT(LEFT(E2,6))="*","M",IF(RIGHT(LEFT(C2,6))="Z",8,IF(RIGHT(LEFT(C2,6))="X",9,IF(RIGHT(LEFT(E2,6))=RIGHT(LEFT(C2,6)),1,0)))))) -> B | M2: =IF(E2="","",IF(RIGHT(LEFT(E2,7))=".","B",IF(RIGHT(LEFT(E2,7))="*","M",IF(RIGHT(LEFT(C2,7))="Z",8,IF(RIGHT(LEFT(C2,7))="X",9,IF(RIGHT(LEFT(E2,7))=RIGHT(LEFT(C2,7)),1,0)))))) -> B | N2: =IF(E2="","",IF(RIGHT(LEFT(E2,8))=".","B",IF(RIGHT(LEFT(E2,8))="*","M",IF(RIGHT(LEFT(C2,8))="Z",8,IF(RIGHT(LEFT(C2,8))="X",9,IF(RIGHT(LEFT(E2,8))=RIGHT(LEFT(C2,8)),1,0)))))) -> B | O2: =IF(F2="","",IF(RIGHT(LEFT(F2,1))=".","B",IF(RIGHT(LEFT(F2,1))="*","M",IF(RIGHT(LEFT(D2,1))="Z",8,IF(RIGHT(LEFT(D2,1))="X",9,IF(RIGHT(LEFT(F2,1))=RIGHT(LEFT(D2,1)),1,0)))))) -> B | P2: =IF(F2="","",IF(RIGHT(LEFT(F2,2))=".","B",IF(RIGHT(LEFT(F2,2))="*","M",IF(RIGHT(LEFT(D2,2))="Z",8,IF(RIGHT(LEFT(D2,2))="X",9,IF(RIGHT(LEFT(F2,2))=RIGHT(LEFT(D2,2)),1,0)))))) -> B | Q2: =IF(F2="","",IF(RIGHT(LEFT(F2,3))=".","B",IF(RIGHT(LEFT(F2,3))="*","M",IF(RIGHT(LEFT(D2,3))="Z",8,IF(RIGHT(LEFT(D2,3))="X",9,IF(RIGHT(LEFT(F2,3))=RIGHT(LEFT(D2,3)),1,0)))))) -> B | R2: =IF(F2="","",IF(RIGHT(LEFT(F2,4))=".","B",IF(RIGHT(LEFT(F2,4))="*","M",IF(RIGHT(LEFT(D2,4))="Z",8,IF(RIGHT(LEFT(D2,4))="X",9,IF(RIGHT(LEFT(F2,4))=RIGHT(LEFT(D2,4)),1,0)))))) -> B | S2: =IF(F2="","",IF(RIGHT(LEFT(F2,5))=".","B",IF(RIGHT(LEFT(F2,5))="*","M",IF(RIGHT(LEFT(D2,5))="Z",8,IF(RIGHT(LEFT(D2,5))="X",9,IF(RIGHT(LEFT(F2,5))=RIGHT(LEFT(D2,5)),1,0)))))) -> B | T2: =IF(F2="","",IF(RIGHT(LEFT(F2,6))=".","B",IF(RIGHT(LEFT(F2,6))="*","M",IF(RIGHT(LEFT(D2,6))="Z",8,IF(RIGHT(LEFT(D2,6))="X",9,IF(RIGHT(LEFT(F2,6))=RIGHT(LEFT(D2,6)),1,0)))))) -> B | U2: =IF(F2="","",IF(RIGHT(LEFT(F2,7))=".","B",IF(RIGHT(LEFT(F2,7))="*","M",IF(RIGHT(LEFT(D2,7))="Z",8,IF(RIGHT(LEFT(D2,7))="X",9,IF(RIGHT(LEFT(F2,7))=RIGHT(LEFT(D2,7)),1,0)))))) -> B | V2: =IF(F2="","",IF(RIGHT(LEFT(F2,8))=".","B",IF(RIGHT(LEFT(F2,8))="*","M",IF(RIGHT(LEFT(D2,8))="Z",8,IF(RIGHT(LEFT(D2,8))="X",9,IF(RIGHT(LEFT(F2,8))=RIGHT(LEFT(D2,8)),1,0)))))) -> B | W2: =IF(F2="","",IF(RIGHT(LEFT(F2,9))=".","B",IF(RIGHT(LEFT(F2,9))="*","M",IF(RIGHT(LEFT(D2,9))="Z",8,IF(RIGHT(LEFT(D2,9))="X",9,IF(RIGHT(LEFT(F2,9))=RIGHT(LEFT(D2,9)),1,0)))))) -> B | X2: =IF(F2="","",IF(RIGHT(LEFT(F2,10))=".","B",IF(RIGHT(LEFT(F2,10))="*","M",IF(RIGHT(LEFT(D2,10))="Z",8,IF(RIGHT(LEFT(D2,10))="X",9,IF(RIGHT(LEFT(F2,10))=RIGHT(LEFT(D2,10)),1,0)))))) -> B | Y2: =IF(F2="","",IF(RIGHT(LEFT(F2,11))=".","B",IF(RIGHT(LEFT(F2,11))="*","M",IF(RIGHT(LEFT(D2,11))="Z",8,IF(RIGHT(LEFT(D2,11))="X",9,IF(RIGHT(LEFT(F2,11))=RIGHT(LEFT(D2,11)),1,0)))))) -> B | Z2: =IF(F2="","",IF(RIGHT(LEFT(F2,12))=".","B",IF(RIGHT(LEFT(F2,12))="*","M",IF(RIGHT(LEFT(D2,12))="Z",8,IF(RIGHT(LEFT(D2,12))="X",9,IF(RIGHT(LEFT(F2,12))=RIGHT(LEFT(D2,12)),1,0)))))) -> B | AA2: =IF(F2="","",IF(RIGHT(LEFT(F2,13))=".","B",IF(RIGHT(LEFT(F2,13))="*","M",IF(RIGHT(LEFT(D2,13))="Z",8,IF(RIGHT(LEFT(D2,13))="X",9,IF(RIGHT(LEFT(F2,13))=RIGHT(LEFT(D2,13)),1,0)))))) -> B | AB2: =IF(F2="","",IF(RIGHT(LEFT(F2,14))=".","B",IF(RIGHT(LEFT(F2,14))="*","M",IF(RIGHT(LEFT(D2,14))="Z",8,IF(RIGHT(LEFT(D2,14))="X",9,IF(RIGHT(LEFT(F2,14))=RIGHT(LEFT(D2,14)),1,0)))))) -> B | AC2: =IF(F2="","",IF(RIGHT(LEFT(F2,15))=".","B",IF(RIGHT(LEFT(F2,15))="*","M",IF(RIGHT(LEFT(D2,15))="Z",8,IF(RIGHT(LEFT(D2,15))="X",9,IF(RIGHT(LEFT(F2,15))=RIGHT(LEFT(D2,15)),1,0)))))) -> B | AD2: =IF(F2="","",IF(RIGHT(LEFT(F2,16))=".","B",IF(RIGHT(LEFT(F2,16))="*","M",IF(RIGHT(LEFT(D2,16))="Z",8,IF(RIGHT(LEFT(D2,16))="X",9,IF(RIGHT(LEFT(F2,16))=RIGHT(LEFT(D2,16)),1,0)))))) -> B | AE2: =IF(F2="","",IF(RIGHT(LEFT(F2,17))=".","B",IF(RIGHT(LEFT(F2,17))="*","M",IF(RIGHT(LEFT(D2,17))="Z",8,IF(RIGHT(LEFT(D2,17))="X",9,IF(RIGHT(LEFT(F2,17))=RIGHT(LEFT(D2,17)),1,0)))))) -> B | AF2: =IF(F2="","",IF(RIGHT(LEFT(F2,18))=".","B",IF(RIGHT(LEFT(F2,18))="*","M",IF(RIGHT(LEFT(D2,18))="Z",8,IF(RIGHT(LEFT(D2,18))="X",9,IF(RIGHT(LEFT(F2,18))=RIGHT(LEFT(D2,18)),1,0)))))) -> B | AG2: =IF(F2="","",IF(RIGHT(LEFT(F2,19))=".","B",IF(RIGHT(LEFT(F2,19))="*","M",IF(RIGHT(LEFT(D2,19))="Z",8,IF(RIGHT(LEFT(D2,19))="X",9,IF(RIGHT(LEFT(F2,19))=RIGHT(LEFT(D2,19)),1,0)))))) -> B | AH2: =IF(F2="","",IF(RIGHT(LEFT(F2,20))=".","B",IF(RIGHT(LEFT(F2,20))="*","M",IF(RIGHT(LEFT(D2,20))="Z",8,IF(RIGHT(LEFT(D2,20))="X",9,IF(RIGHT(LEFT(F2,20))=RIGHT(LEFT(D2,20)),1,0)))))) -> B | AI2: =IF(F2="","",IF(RIGHT(LEFT(F2,21))=".","B",IF(RIGHT(LEFT(F2,21))="*","M",IF(RIGHT(LEFT(D2,21))="Z",8,IF(RIGHT(LEFT(D2,21))="X",9,IF(RIGHT(LEFT(F2,21))=RIGHT(LEFT(D2,21)),1,0)))))) -> B | AJ2: =IF(F2="","",IF(RIGHT(LEFT(F2,22))=".","B",IF(RIGHT(LEFT(F2,22))="*","M",IF(RIGHT(LEFT(D2,22))="Z",8,IF(RIGHT(LEFT(D2,22))="X",9,IF(RIGHT(LEFT(F2,22))=RIGHT(LEFT(D2,22)),1,0)))))) -> B | AK2: =IF(F2="","",IF(RIGHT(LEFT(F2,23))=".","B",IF(RIGHT(LEFT(F2,23))="*","M",IF(RIGHT(LEFT(D2,23))="Z",8,IF(RIGHT(LEFT(D2,23))="X",9,IF(RIGHT(LEFT(F2,23))=RIGHT(LEFT(D2,23)),1,0)))))) -> B | AL2: =IF(F2="","",IF(RIGHT(LEFT(F2,24))=".","B",IF(RIGHT(LEFT(F2,24))="*","M",IF(RIGHT(LEFT(D2,24))="Z",8,IF(RIGHT(LEFT(D2,24))="X",9,IF(RIGHT(LEFT(F2,24))=RIGHT(LEFT(D2,24)),1,0)))))) -> B | AM2: =IF(F2="","",IF(RIGHT(LEFT(F2,25))=".","B",IF(RIGHT(LEFT(F2,25))="*","M",IF(RIGHT(LEFT(D2,25))="Z",8,IF(RIGHT(LEFT(D2,25))="X",9,IF(RIGHT(LEFT(F2,25))=RIGHT(LEFT(D2,25)),1,0)))))) -> B | AN2: =IF(F2="","",IF(RIGHT(LEFT(F2,26))=".","B",IF(RIGHT(LEFT(F2,26))="*","M",IF(RIGHT(LEFT(D2,26))="Z",8,IF(RIGHT(LEFT(D2,26))="X",9,IF(RIGHT(LEFT(F2,26))=RIGHT(LEFT(D2,26)),1,0)))))) -> B | AO2: =IF(F2="","",IF(RIGHT(LEFT(F2,27))=".","B",IF(RIGHT(LEFT(F2,27))="*","M",IF(RIGHT(LEFT(D2,27))="Z",8,IF(RIGHT(LEFT(D2,27))="X",9,IF(RIGHT(LEFT(F2,27))=RIGHT(LEFT(D2,27)),1,0)))))) -> B
A3: 2019 | B3: 121880 | C3: ZDCBCCDB | D3: BXCAXDEXCBECDACEDACADEBXBBE | E3: DCAABDBC | F3: ADDEECABBECBAEADCEAADDBCCBE | G3: =IF(E3="","",IF(RIGHT(LEFT(E3,1))=".","B",IF(RIGHT(LEFT(E3,1))="*","M",IF(RIGHT(LEFT(C3,1))="Z",8,IF(RIGHT(LEFT(C3,1))="X",9,IF(RIGHT(LEFT(E3,1))=RIGHT(LEFT(C3,1)),1,0)))))) -> 8 | H3: =IF(E3="","",IF(RIGHT(LEFT(E3,2))=".","B",IF(RIGHT(LEFT(E3,2))="*","M",IF(RIGHT(LEFT(C3,2))="Z",8,IF(RIGHT(LEFT(C3,2))="X",9,IF(RIGHT(LEFT(E3,2))=RIGHT(LEFT(C3,2)),1,0)))))) -> 0 | I3: =IF(E3="","",IF(RIGHT(LEFT(E3,3))=".","B",IF(RIGHT(LEFT(E3,3))="*","M",IF(RIGHT(LEFT(C3,3))="Z",8,IF(RIGHT(LEFT(C3,3))="X",9,IF(RIGHT(LEFT(E3,3))=RIGHT(LEFT(C3,3)),1,0)))))) -> 0 | J3: =IF(E3="","",IF(RIGHT(LEFT(E3,4))=".","B",IF(RIGHT(LEFT(E3,4))="*","M",IF(RIGHT(LEFT(C3,4))="Z",8,IF(RIGHT(LEFT(C3,4))="X",9,IF(RIGHT(LEFT(E3,4))=RIGHT(LEFT(C3,4)),1,0)))))) -> 0 | K3: =IF(E3="","",IF(RIGHT(LEFT(E3,5))=".","B",IF(RIGHT(LEFT(E3,5))="*","M",IF(RIGHT(LEFT(C3,5))="Z",8,IF(RIGHT(LEFT(C3,5))="X",9,IF(RIGHT(LEFT(E3,5))=RIGHT(LEFT(C3,5)),1,0)))))) -> 0 | L3: =IF(E3="","",IF(RIGHT(LEFT(E3,6))=".","B",IF(RIGHT(LEFT(E3,6))="*","M",IF(RIGHT(LEFT(C3,6))="Z",8,IF(RIGHT(LEFT(C3,6))="X",9,IF(RIGHT(LEFT(E3,6))=RIGHT(LEFT(C3,6)),1,0)))))) -> 0 | M3: =IF(E3="","",IF(RIGHT(LEFT(E3,7))=".","B",IF(RIGHT(LEFT(E3,7))="*","M",IF(RIGHT(LEFT(C3,7))="Z",8,IF(RIGHT(LEFT(C3,7))="X",9,IF(RIGHT(LEFT(E3,7))=RIGHT(LEFT(C3,7)),1,0)))))) -> 0 | N3: =IF(E3="","",IF(RIGHT(LEFT(E3,8))=".","B",IF(RIGHT(LEFT(E3,8))="*","M",IF(RIGHT(LEFT(C3,8))="Z",8,IF(RIGHT(LEFT(C3,8))="X",9,IF(RIGHT(LEFT(E3,8))=RIGHT(LEFT(C3,8)),1,0)))))) -> 0 | O3: =IF(F3="","",IF(RIGHT(LEFT(F3,1))=".","B",IF(RIGHT(LEFT(F3,1))="*","M",IF(RIGHT(LEFT(D3,1))="Z",8,IF(RIGHT(LEFT(D3,1))="X",9,IF(RIGHT(LEFT(F3,1))=RIGHT(LEFT(D3,1)),1,0)))))) -> 0 | P3: =IF(F3="","",IF(RIGHT(LEFT(F3,2))=".","B",IF(RIGHT(LEFT(F3,2))="*","M",IF(RIGHT(LEFT(D3,2))="Z",8,IF(RIGHT(LEFT(D3,2))="X",9,IF(RIGHT(LEFT(F3,2))=RIGHT(LEFT(D3,2)),1,0)))))) -> 9 | Q3: =IF(F3="","",IF(RIGHT(LEFT(F3,3))=".","B",IF(RIGHT(LEFT(F3,3))="*","M",IF(RIGHT(LEFT(D3,3))="Z",8,IF(RIGHT(LEFT(D3,3))="X",9,IF(RIGHT(LEFT(F3,3))=RIGHT(LEFT(D3,3)),1,0)))))) -> 0 | R3: =IF(F3="","",IF(RIGHT(LEFT(F3,4))=".","B",IF(RIGHT(LEFT(F3,4))="*","M",IF(RIGHT(LEFT(D3,4))="Z",8,IF(RIGHT(LEFT(D3,4))="X",9,IF(RIGHT(LEFT(F3,4))=RIGHT(LEFT(D3,4)),1,0)))))) -> 0 | S3: =IF(F3="","",IF(RIGHT(LEFT(F3,5))=".","B",IF(RIGHT(LEFT(F3,5))="*","M",IF(RIGHT(LEFT(D3,5))="Z",8,IF(RIGHT(LEFT(D3,5))="X",9,IF(RIGHT(LEFT(F3,5))=RIGHT(LEFT(D3,5)),1,0)))))) -> 9 | T3: =IF(F3="","",IF(RIGHT(LEFT(F3,6))=".","B",IF(RIGHT(LEFT(F3,6))="*","M",IF(RIGHT(LEFT(D3,6))="Z",8,IF(RIGHT(LEFT(D3,6))="X",9,IF(RIGHT(LEFT(F3,6))=RIGHT(LEFT(D3,6)),1,0)))))) -> 0 | U3: =IF(F3="","",IF(RIGHT(LEFT(F3,7))=".","B",IF(RIGHT(LEFT(F3,7))="*","M",IF(RIGHT(LEFT(D3,7))="Z",8,IF(RIGHT(LEFT(D3,7))="X",9,IF(RIGHT(LEFT(F3,7))=RIGHT(LEFT(D3,7)),1,0)))))) -> 0 | V3: =IF(F3="","",IF(RIGHT(LEFT(F3,8))=".","B",IF(RIGHT(LEFT(F3,8))="*","M",IF(RIGHT(LEFT(D3,8))="Z",8,IF(RIGHT(LEFT(D3,8))="X",9,IF(RIGHT(LEFT(F3,8))=RIGHT(LEFT(D3,8)),1,0)))))) -> 9 | W3: =IF(F3="","",IF(RIGHT(LEFT(F3,9))=".","B",IF(RIGHT(LEFT(F3,9))="*","M",IF(RIGHT(LEFT(D3,9))="Z",8,IF(RIGHT(LEFT(D3,9))="X",9,IF(RIGHT(LEFT(F3,9))=RIGHT(LEFT(D3,9)),1,0)))))) -> 0 | X3: =IF(F3="","",IF(RIGHT(LEFT(F3,10))=".","B",IF(RIGHT(LEFT(F3,10))="*","M",IF(RIGHT(LEFT(D3,10))="Z",8,IF(RIGHT(LEFT(D3,10))="X",9,IF(RIGHT(LEFT(F3,10))=RIGHT(LEFT(D3,10)),1,0)))))) -> 0 | Y3: =IF(F3="","",IF(RIGHT(LEFT(F3,11))=".","B",IF(RIGHT(LEFT(F3,11))="*","M",IF(RIGHT(LEFT(D3,11))="Z",8,IF(RIGHT(LEFT(D3,11))="X",9,IF(RIGHT(LEFT(F3,11))=RIGHT(LEFT(D3,11)),1,0)))))) -> 0 | Z3: =IF(F3="","",IF(RIGHT(LEFT(F3,12))=".","B",IF(RIGHT(LEFT(F3,12))="*","M",IF(RIGHT(LEFT(D3,12))="Z",8,IF(RIGHT(LEFT(D3,12))="X",9,IF(RIGHT(LEFT(F3,12))=RIGHT(LEFT(D3,12)),1,0)))))) -> 0 | AA3: =IF(F3="","",IF(RIGHT(LEFT(F3,13))=".","B",IF(RIGHT(LEFT(F3,13))="*","M",IF(RIGHT(LEFT(D3,13))="Z",8,IF(RIGHT(LEFT(D3,13))="X",9,IF(RIGHT(LEFT(F3,13))=RIGHT(LEFT(D3,13)),1,0)))))) -> 0 | AB3: =IF(F3="","",IF(RIGHT(LEFT(F3,14))=".","B",IF(RIGHT(LEFT(F3,14))="*","M",IF(RIGHT(LEFT(D3,14))="Z",8,IF(RIGHT(LEFT(D3,14))="X",9,IF(RIGHT(LEFT(F3,14))=RIGHT(LEFT(D3,14)),1,0)))))) -> 0 | AC3: =IF(F3="","",IF(RIGHT(LEFT(F3,15))=".","B",IF(RIGHT(LEFT(F3,15))="*","M",IF(RIGHT(LEFT(D3,15))="Z",8,IF(RIGHT(LEFT(D3,15))="X",9,IF(RIGHT(LEFT(F3,15))=RIGHT(LEFT(D3,15)),1,0)))))) -> 0 | AD3: =IF(F3="","",IF(RIGHT(LEFT(F3,16))=".","B",IF(RIGHT(LEFT(F3,16))="*","M",IF(RIGHT(LEFT(D3,16))="Z",8,IF(RIGHT(LEFT(D3,16))="X",9,IF(RIGHT(LEFT(F3,16))=RIGHT(LEFT(D3,16)),1,0)))))) -> 0 | AE3: =IF(F3="","",IF(RIGHT(LEFT(F3,17))=".","B",IF(RIGHT(LEFT(F3,17))="*","M",IF(RIGHT(LEFT(D3,17))="Z",8,IF(RIGHT(LEFT(D3,17))="X",9,IF(RIGHT(LEFT(F3,17))=RIGHT(LEFT(D3,17)),1,0)))))) -> 0 | AF3: =IF(F3="","",IF(RIGHT(LEFT(F3,18))=".","B",IF(RIGHT(LEFT(F3,18))="*","M",IF(RIGHT(LEFT(D3,18))="Z",8,IF(RIGHT(LEFT(D3,18))="X",9,IF(RIGHT(LEFT(F3,18))=RIGHT(LEFT(D3,18)),1,0)))))) -> 0 | AG3: =IF(F3="","",IF(RIGHT(LEFT(F3,19))=".","B",IF(RIGHT(LEFT(F3,19))="*","M",IF(RIGHT(LEFT(D3,19))="Z",8,IF(RIGHT(LEFT(D3,19))="X",9,IF(RIGHT(LEFT(F3,19))=RIGHT(LEFT(D3,19)),1,0)))))) -> 0 | AH3: =IF(F3="","",IF(RIGHT(LEFT(F3,20))=".","B",IF(RIGHT(LEFT(F3,20))="*","M",IF(RIGHT(LEFT(D3,20))="Z",8,IF(RIGHT(LEFT(D3,20))="X",9,IF(RIGHT(LEFT(F3,20))=RIGHT(LEFT(D3,20)),1,0)))))) -> 1 | AI3: =IF(F3="","",IF(RIGHT(LEFT(F3,21))=".","B",IF(RIGHT(LEFT(F3,21))="*","M",IF(RIGHT(LEFT(D3,21))="Z",8,IF(RIGHT(LEFT(D3,21))="X",9,IF(RIGHT(LEFT(F3,21))=RIGHT(LEFT(D3,21)),1,0)))))) -> 1 | AJ3: =IF(F3="","",IF(RIGHT(LEFT(F3,22))=".","B",IF(RIGHT(LEFT(F3,22))="*","M",IF(RIGHT(LEFT(D3,22))="Z",8,IF(RIGHT(LEFT(D3,22))="X",9,IF(RIGHT(LEFT(F3,22))=RIGHT(LEFT(D3,22)),1,0)))))) -> 0 | AK3: =IF(F3="","",IF(RIGHT(LEFT(F3,23))=".","B",IF(RIGHT(LEFT(F3,23))="*","M",IF(RIGHT(LEFT(D3,23))="Z",8,IF(RIGHT(LEFT(D3,23))="X",9,IF(RIGHT(LEFT(F3,23))=RIGHT(LEFT(D3,23)),1,0)))))) -> 1 | AL3: =IF(F3="","",IF(RIGHT(LEFT(F3,24))=".","B",IF(RIGHT(LEFT(F3,24))="*","M",IF(RIGHT(LEFT(D3,24))="Z",8,IF(RIGHT(LEFT(D3,24))="X",9,IF(RIGHT(LEFT(F3,24))=RIGHT(LEFT(D3,24)),1,0)))))) -> 9 | AM3: =IF(F3="","",IF(RIGHT(LEFT(F3,25))=".","B",IF(RIGHT(LEFT(F3,25))="*","M",IF(RIGHT(LEFT(D3,25))="Z",8,IF(RIGHT(LEFT(D3,25))="X",9,IF(RIGHT(LEFT(F3,25))=RIGHT(LEFT(D3,25)),1,0)))))) -> 0 | AN3: =IF(F3="","",IF(RIGHT(LEFT(F3,26))=".","B",IF(RIGHT(LEFT(F3,26))="*","M",IF(RIGHT(LEFT(D3,26))="Z",8,IF(RIGHT(LEFT(D3,26))="X",9,IF(RIGHT(LEFT(F3,26))=RIGHT(LEFT(D3,26)),1,0)))))) -> 1 | AO3: =IF(F3="","",IF(RIGHT(LEFT(F3,27))=".","B",IF(RIGHT(LEFT(F3,27))="*","M",IF(RIGHT(LEFT(D3,27))="Z",8,IF(RIGHT(LEFT(D3,27))="X",9,IF(RIGHT(LEFT(F3,27))=RIGHT(LEFT(D3,27)),1,0)))))) -> 1
A4: 2019 | B4: 88399 | C4: ZDCBCCDB | D4: ZAXDBBAXDABEEZECZAEZBCXBZBC | E4: ADACABCC | F4: CCCCCCCCCCCCCCCCCCCCCCCCCCC | G4: =IF(E4="","",IF(RIGHT(LEFT(E4,1))=".","B",IF(RIGHT(LEFT(E4,1))="*","M",IF(RIGHT(LEFT(C4,1))="Z",8,IF(RIGHT(LEFT(C4,1))="X",9,IF(RIGHT(LEFT(E4,1))=RIGHT(LEFT(C4,1)),1,0)))))) -> 8 | H4: =IF(E4="","",IF(RIGHT(LEFT(E4,2))=".","B",IF(RIGHT(LEFT(E4,2))="*","M",IF(RIGHT(LEFT(C4,2))="Z",8,IF(RIGHT(LEFT(C4,2))="X",9,IF(RIGHT(LEFT(E4,2))=RIGHT(LEFT(C4,2)),1,0)))))) -> 1 | I4: =IF(E4="","",IF(RIGHT(LEFT(E4,3))=".","B",IF(RIGHT(LEFT(E4,3))="*","M",IF(RIGHT(LEFT(C4,3))="Z",8,IF(RIGHT(LEFT(C4,3))="X",9,IF(RIGHT(LEFT(E4,3))=RIGHT(LEFT(C4,3)),1,0)))))) -> 0 | J4: =IF(E4="","",IF(RIGHT(LEFT(E4,4))=".","B",IF(RIGHT(LEFT(E4,4))="*","M",IF(RIGHT(LEFT(C4,4))="Z",8,IF(RIGHT(LEFT(C4,4))="X",9,IF(RIGHT(LEFT(E4,4))=RIGHT(LEFT(C4,4)),1,0)))))) -> 0 | K4: =IF(E4="","",IF(RIGHT(LEFT(E4,5))=".","B",IF(RIGHT(LEFT(E4,5))="*","M",IF(RIGHT(LEFT(C4,5))="Z",8,IF(RIGHT(LEFT(C4,5))="X",9,IF(RIGHT(LEFT(E4,5))=RIGHT(LEFT(C4,5)),1,0)))))) -> 0 | L4: =IF(E4="","",IF(RIGHT(LEFT(E4,6))=".","B",IF(RIGHT(LEFT(E4,6))="*","M",IF(RIGHT(LEFT(C4,6))="Z",8,IF(RIGHT(LEFT(C4,6))="X",9,IF(RIGHT(LEFT(E4,6))=RIGHT(LEFT(C4,6)),1,0)))))) -> 0 | M4: =IF(E4="","",IF(RIGHT(LEFT(E4,7))=".","B",IF(RIGHT(LEFT(E4,7))="*","M",IF(RIGHT(LEFT(C4,7))="Z",8,IF(RIGHT(LEFT(C4,7))="X",9,IF(RIGHT(LEFT(E4,7))=RIGHT(LEFT(C4,7)),1,0)))))) -> 0 | N4: =IF(E4="","",IF(RIGHT(LEFT(E4,8))=".","B",IF(RIGHT(LEFT(E4,8))="*","M",IF(RIGHT(LEFT(C4,8))="Z",8,IF(RIGHT(LEFT(C4,8))="X",9,IF(RIGHT(LEFT(E4,8))=RIGHT(LEFT(C4,8)),1,0)))))) -> 0 | O4: =IF(F4="","",IF(RIGHT(LEFT(F4,1))=".","B",IF(RIGHT(LEFT(F4,1))="*","M",IF(RIGHT(LEFT(D4,1))="Z",8,IF(RIGHT(LEFT(D4,1))="X",9,IF(RIGHT(LEFT(F4,1))=RIGHT(LEFT(D4,1)),1,0)))))) -> 8 | P4: =IF(F4="","",IF(RIGHT(LEFT(F4,2))=".","B",IF(RIGHT(LEFT(F4,2))="*","M",IF(RIGHT(LEFT(D4,2))="Z",8,IF(RIGHT(LEFT(D4,2))="X",9,IF(RIGHT(LEFT(F4,2))=RIGHT(LEFT(D4,2)),1,0)))))) -> 0 | Q4: =IF(F4="","",IF(RIGHT(LEFT(F4,3))=".","B",IF(RIGHT(LEFT(F4,3))="*","M",IF(RIGHT(LEFT(D4,3))="Z",8,IF(RIGHT(LEFT(D4,3))="X",9,IF(RIGHT(LEFT(F4,3))=RIGHT(LEFT(D4,3)),1,0)))))) -> 9 | R4: =IF(F4="","",IF(RIGHT(LEFT(F4,4))=".","B",IF(RIGHT(LEFT(F4,4))="*","M",IF(RIGHT(LEFT(D4,4))="Z",8,IF(RIGHT(LEFT(D4,4))="X",9,IF(RIGHT(LEFT(F4,4))=RIGHT(LEFT(D4,4)),1,0)))))) -> 0 | S4: =IF(F4="","",IF(RIGHT(LEFT(F4,5))=".","B",IF(RIGHT(LEFT(F4,5))="*","M",IF(RIGHT(LEFT(D4,5))="Z",8,IF(RIGHT(LEFT(D4,5))="X",9,IF(RIGHT(LEFT(F4,5))=RIGHT(LEFT(D4,5)),1,0)))))) -> 0 | T4: =IF(F4="","",IF(RIGHT(LEFT(F4,6))=".","B",IF(RIGHT(LEFT(F4,6))="*","M",IF(RIGHT(LEFT(D4,6))="Z",8,IF(RIGHT(LEFT(D4,6))="X",9,IF(RIGHT(LEFT(F4,6))=RIGHT(LEFT(D4,6)),1,0)))))) -> 0 | U4: =IF(F4="","",IF(RIGHT(LEFT(F4,7))=".","B",IF(RIGHT(LEFT(F4,7))="*","M",IF(RIGHT(LEFT(D4,7))="Z",8,IF(RIGHT(LEFT(D4,7))="X",9,IF(RIGHT(LEFT(F4,7))=RIGHT(LEFT(D4,7)),1,0)))))) -> 0 | V4: =IF(F4="","",IF(RIGHT(LEFT(F4,8))=".","B",IF(RIGHT(LEFT(F4,8))="*","M",IF(RIGHT(LEFT(D4,8))="Z",8,IF(RIGHT(LEFT(D4,8))="X",9,IF(RIGHT(LEFT(F4,8))=RIGHT(LEFT(D4,8)),1,0)))))) -> 9 | W4: =IF(F4="","",IF(RIGHT(LEFT(F4,9))=".","B",IF(RIGHT(LEFT(F4,9))="*","M",IF(RIGHT(LEFT(D4,9))="Z",8,IF(RIGHT(LEFT(D4,9))="X",9,IF(RIGHT(LEFT(F4,9))=RIGHT(LEFT(D4,9)),1,0)))))) -> 0 | X4: =IF(F4="","",IF(RIGHT(LEFT(F4,10))=".","B",IF(RIGHT(LEFT(F4,10))="*","M",IF(RIGHT(LEFT(D4,10))="Z",8,IF(RIGHT(LEFT(D4,10))="X",9,IF(RIGHT(LEFT(F4,10))=RIGHT(LEFT(D4,10)),1,0)))))) -> 0 | Y4: =IF(F4="","",IF(RIGHT(LEFT(F4,11))=".","B",IF(RIGHT(LEFT(F4,11))="*","M",IF(RIGHT(LEFT(D4,11))="Z",8,IF(RIGHT(LEFT(D4,11))="X",9,IF(RIGHT(LEFT(F4,11))=RIGHT(LEFT(D4,11)),1,0)))))) -> 0 | Z4: =IF(F4="","",IF(RIGHT(LEFT(F4,12))=".","B",IF(RIGHT(LEFT(F4,12))="*","M",IF(RIGHT(LEFT(D4,12))="Z",8,IF(RIGHT(LEFT(D4,12))="X",9,IF(RIGHT(LEFT(F4,12))=RIGHT(LEFT(D4,12)),1,0)))))) -> 0 | AA4: =IF(F4="","",IF(RIGHT(LEFT(F4,13))=".","B",IF(RIGHT(LEFT(F4,13))="*","M",IF(RIGHT(LEFT(D4,13))="Z",8,IF(RIGHT(LEFT(D4,13))="X",9,IF(RIGHT(LEFT(F4,13))=RIGHT(LEFT(D4,13)),1,0)))))) -> 0 | AB4: =IF(F4="","",IF(RIGHT(LEFT(F4,14))=".","B",IF(RIGHT(LEFT(F4,14))="*","M",IF(RIGHT(LEFT(D4,14))="Z",8,IF(RIGHT(LEFT(D4,14))="X",9,IF(RIGHT(LEFT(F4,14))=RIGHT(LEFT(D4,14)),1,0)))))) -> 8 | AC4: =IF(F4="","",IF(RIGHT(LEFT(F4,15))=".","B",IF(RIGHT(LEFT(F4,15))="*","M",IF(RIGHT(LEFT(D4,15))="Z",8,IF(RIGHT(LEFT(D4,15))="X",9,IF(RIGHT(LEFT(F4,15))=RIGHT(LEFT(D4,15)),1,0)))))) -> 0 | AD4: =IF(F4="","",IF(RIGHT(LEFT(F4,16))=".","B",IF(RIGHT(LEFT(F4,16))="*","M",IF(RIGHT(LEFT(D4,16))="Z",8,IF(RIGHT(LEFT(D4,16))="X",9,IF(RIGHT(LEFT(F4,16))=RIGHT(LEFT(D4,16)),1,0)))))) -> 1 | AE4: =IF(F4="","",IF(RIGHT(LEFT(F4,17))=".","B",IF(RIGHT(LEFT(F4,17))="*","M",IF(RIGHT(LEFT(D4,17))="Z",8,IF(RIGHT(LEFT(D4,17))="X",9,IF(RIGHT(LEFT(F4,17))=RIGHT(LEFT(D4,17)),1,0)))))) -> 8 | AF4: =IF(F4="","",IF(RIGHT(LEFT(F4,18))=".","B",IF(RIGHT(LEFT(F4,18))="*","M",IF(RIGHT(LEFT(D4,18))="Z",8,IF(RIGHT(LEFT(D4,18))="X",9,IF(RIGHT(LEFT(F4,18))=RIGHT(LEFT(D4,18)),1,0)))))) -> 0 | AG4: =IF(F4="","",IF(RIGHT(LEFT(F4,19))=".","B",IF(RIGHT(LEFT(F4,19))="*","M",IF(RIGHT(LEFT(D4,19))="Z",8,IF(RIGHT(LEFT(D4,19))="X",9,IF(RIGHT(LEFT(F4,19))=RIGHT(LEFT(D4,19)),1,0)))))) -> 0 | AH4: =IF(F4="","",IF(RIGHT(LEFT(F4,20))=".","B",IF(RIGHT(LEFT(F4,20))="*","M",IF(RIGHT(LEFT(D4,20))="Z",8,IF(RIGHT(LEFT(D4,20))="X",9,IF(RIGHT(LEFT(F4,20))=RIGHT(LEFT(D4,20)),1,0)))))) -> 8 | AI4: =IF(F4="","",IF(RIGHT(LEFT(F4,21))=".","B",IF(RIGHT(LEFT(F4,21))="*","M",IF(RIGHT(LEFT(D4,21))="Z",8,IF(RIGHT(LEFT(D4,21))="X",9,IF(RIGHT(LEFT(F4,21))=RIGHT(LEFT(D4,21)),1,0)))))) -> 0 | AJ4: =IF(F4="","",IF(RIGHT(LEFT(F4,22))=".","B",IF(RIGHT(LEFT(F4,22))="*","M",IF(RIGHT(LEFT(D4,22))="Z",8,IF(RIGHT(LEFT(D4,22))="X",9,IF(RIGHT(LEFT(F4,22))=RIGHT(LEFT(D4,22)),1,0)))))) -> 1 | AK4: =IF(F4="","",IF(RIGHT(LEFT(F4,23))=".","B",IF(RIGHT(LEFT(F4,23))="*","M",IF(RIGHT(LEFT(D4,23))="Z",8,IF(RIGHT(LEFT(D4,23))="X",9,IF(RIGHT(LEFT(F4,23))=RIGHT(LEFT(D4,23)),1,0)))))) -> 9 | AL4: =IF(F4="","",IF(RIGHT(LEFT(F4,24))=".","B",IF(RIGHT(LEFT(F4,24))="*","M",IF(RIGHT(LEFT(D4,24))="Z",8,IF(RIGHT(LEFT(D4,24))="X",9,IF(RIGHT(LEFT(F4,24))=RIGHT(LEFT(D4,24)),1,0)))))) -> 0 | AM4: =IF(F4="","",IF(RIGHT(LEFT(F4,25))=".","B",IF(RIGHT(LEFT(F4,25))="*","M",IF(RIGHT(LEFT(D4,25))="Z",8,IF(RIGHT(LEFT(D4,25))="X",9,IF(RIGHT(LEFT(F4,25))=RIGHT(LEFT(D4,25)),1,0)))))) -> 8 | AN4: =IF(F4="","",IF(RIGHT(LEFT(F4,26))=".","B",IF(RIGHT(LEFT(F4,26))="*","M",IF(RIGHT(LEFT(D4,26))="Z",8,IF(RIGHT(LEFT(D4,26))="X",9,IF(RIGHT(LEFT(F4,26))=RIGHT(LEFT(D4,26)),1,0)))))) -> 0 | AO4: =IF(F4="","",IF(RIGHT(LEFT(F4,27))=".","B",IF(RIGHT(LEFT(F4,27))="*","M",IF(RIGHT(LEFT(D4,27))="Z",8,IF(RIGHT(LEFT(D4,27))="X",9,IF(RIGHT(LEFT(F4,27))=RIGHT(LEFT(D4,27)),1,0)))))) -> 1
A5: 2019 | B5: 1181815 | C5: ZDCBCCDB | D5: ZDEBDAEBXDACZXCBXDCZABBEDXC | E5: ABCDEABC | F5: CDEDEDDBDCADCBAECEDDDCCBABC | G5: =IF(E5="","",IF(RIGHT(LEFT(E5,1))=".","B",IF(RIGHT(LEFT(E5,1))="*","M",IF(RIGHT(LEFT(C5,1))="Z",8,IF(RIGHT(LEFT(C5,1))="X",9,IF(RIGHT(LEFT(E5,1))=RIGHT(LEFT(C5,1)),1,0)))))) -> 8 | H5: =IF(E5="","",IF(RIGHT(LEFT(E5,2))=".","B",IF(RIGHT(LEFT(E5,2))="*","M",IF(RIGHT(LEFT(C5,2))="Z",8,IF(RIGHT(LEFT(C5,2))="X",9,IF(RIGHT(LEFT(E5,2))=RIGHT(LEFT(C5,2)),1,0)))))) -> 0 | I5: =IF(E5="","",IF(RIGHT(LEFT(E5,3))=".","B",IF(RIGHT(LEFT(E5,3))="*","M",IF(RIGHT(LEFT(C5,3))="Z",8,IF(RIGHT(LEFT(C5,3))="X",9,IF(RIGHT(LEFT(E5,3))=RIGHT(LEFT(C5,3)),1,0)))))) -> 1 | J5: =IF(E5="","",IF(RIGHT(LEFT(E5,4))=".","B",IF(RIGHT(LEFT(E5,4))="*","M",IF(RIGHT(LEFT(C5,4))="Z",8,IF(RIGHT(LEFT(C5,4))="X",9,IF(RIGHT(LEFT(E5,4))=RIGHT(LEFT(C5,4)),1,0)))))) -> 0 | K5: =IF(E5="","",IF(RIGHT(LEFT(E5,5))=".","B",IF(RIGHT(LEFT(E5,5))="*","M",IF(RIGHT(LEFT(C5,5))="Z",8,IF(RIGHT(LEFT(C5,5))="X",9,IF(RIGHT(LEFT(E5,5))=RIGHT(LEFT(C5,5)),1,0)))))) -> 0 | L5: =IF(E5="","",IF(RIGHT(LEFT(E5,6))=".","B",IF(RIGHT(LEFT(E5,6))="*","M",IF(RIGHT(LEFT(C5,6))="Z",8,IF(RIGHT(LEFT(C5,6))="X",9,IF(RIGHT(LEFT(E5,6))=RIGHT(LEFT(C5,6)),1,0)))))) -> 0 | M5: =IF(E5="","",IF(RIGHT(LEFT(E5,7))=".","B",IF(RIGHT(LEFT(E5,7))="*","M",IF(RIGHT(LEFT(C5,7))="Z",8,IF(RIGHT(LEFT(C5,7))="X",9,IF(RIGHT(LEFT(E5,7))=RIGHT(LEFT(C5,7)),1,0)))))) -> 0 | N5: =IF(E5="","",IF(RIGHT(LEFT(E5,8))=".","B",IF(RIGHT(LEFT(E5,8))="*","M",IF(RIGHT(LEFT(C5,8))="Z",8,IF(RIGHT(LEFT(C5,8))="X",9,IF(RIGHT(LEFT(E5,8))=RIGHT(LEFT(C5,8)),1,0)))))) -> 0 | O5: =IF(F5="","",IF(RIGHT(LEFT(F5,1))=".","B",IF(RIGHT(LEFT(F5,1))="*","M",IF(RIGHT(LEFT(D5,1))="Z",8,IF(RIGHT(LEFT(D5,1))="X",9,IF(RIGHT(LEFT(F5,1))=RIGHT(LEFT(D5,1)),1,0)))))) -> 8 | P5: =IF(F5="","",IF(RIGHT(LEFT(F5,2))=".","B",IF(RIGHT(LEFT(F5,2))="*","M",IF(RIGHT(LEFT(D5,2))="Z",8,IF(RIGHT(LEFT(D5,2))="X",9,IF(RIGHT(LEFT(F5,2))=RIGHT(LEFT(D5,2)),1,0)))))) -> 1 | Q5: =IF(F5="","",IF(RIGHT(LEFT(F5,3))=".","B",IF(RIGHT(LEFT(F5,3))="*","M",IF(RIGHT(LEFT(D5,3))="Z",8,IF(RIGHT(LEFT(D5,3))="X",9,IF(RIGHT(LEFT(F5,3))=RIGHT(LEFT(D5,3)),1,0)))))) -> 1 | R5: =IF(F5="","",IF(RIGHT(LEFT(F5,4))=".","B",IF(RIGHT(LEFT(F5,4))="*","M",IF(RIGHT(LEFT(D5,4))="Z",8,IF(RIGHT(LEFT(D5,4))="X",9,IF(RIGHT(LEFT(F5,4))=RIGHT(LEFT(D5,4)),1,0)))))) -> 0 | S5: =IF(F5="","",IF(RIGHT(LEFT(F5,5))=".","B",IF(RIGHT(LEFT(F5,5))="*","M",IF(RIGHT(LEFT(D5,5))="Z",8,IF(RIGHT(LEFT(D5,5))="X",9,IF(RIGHT(LEFT(F5,5))=RIGHT(LEFT(D5,5)),1,0)))))) -> 0 | T5: =IF(F5="","",IF(RIGHT(LEFT(F5,6))=".","B",IF(RIGHT(LEFT(F5,6))="*","M",IF(RIGHT(LEFT(D5,6))="Z",8,IF(RIGHT(LEFT(D5,6))="X",9,IF(RIGHT(LEFT(F5,6))=RIGHT(LEFT(D5,6)),1,0)))))) -> 0 | U5: =IF(F5="","",IF(RIGHT(LEFT(F5,7))=".","B",IF(RIGHT(LEFT(F5,7))="*","M",IF(RIGHT(LEFT(D5,7))="Z",8,IF(RIGHT(LEFT(D5,7))="X",9,IF(RIGHT(LEFT(F5,7))=RIGHT(LEFT(D5,7)),1,0)))))) -> 0 | V5: =IF(F5="","",IF(RIGHT(LEFT(F5,8))=".","B",IF(RIGHT(LEFT(F5,8))="*","M",IF(RIGHT(LEFT(D5,8))="Z",8,IF(RIGHT(LEFT(D5,8))="X",9,IF(RIGHT(LEFT(F5,8))=RIGHT(LEFT(D5,8)),1,0)))))) -> 1 | W5: =IF(F5="","",IF(RIGHT(LEFT(F5,9))=".","B",IF(RIGHT(LEFT(F5,9))="*","M",IF(RIGHT(LEFT(D5,9))="Z",8,IF(RIGHT(LEFT(D5,9))="X",9,IF(RIGHT(LEFT(F5,9))=RIGHT(LEFT(D5,9)),1,0)))))) -> 9 | X5: =IF(F5="","",IF(RIGHT(LEFT(F5,10))=".","B",IF(RIGHT(LEFT(F5,10))="*","M",IF(RIGHT(LEFT(D5,10))="Z",8,IF(RIGHT(LEFT(D5,10))="X",9,IF(RIGHT(LEFT(F5,10))=RIGHT(LEFT(D5,10)),1,0)))))) -> 0 | Y5: =IF(F5="","",IF(RIGHT(LEFT(F5,11))=".","B",IF(RIGHT(LEFT(F5,11))="*","M",IF(RIGHT(LEFT(D5,11))="Z",8,IF(RIGHT(LEFT(D5,11))="X",9,IF(RIGHT(LEFT(F5,11))=RIGHT(LEFT(D5,11)),1,0)))))) -> 1 | Z5: =IF(F5="","",IF(RIGHT(LEFT(F5,12))=".","B",IF(RIGHT(LEFT(F5,12))="*","M",IF(RIGHT(LEFT(D5,12))="Z",8,IF(RIGHT(LEFT(D5,12))="X",9,IF(RIGHT(LEFT(F5,12))=RIGHT(LEFT(D5,12)),1,0)))))) -> 0 | AA5: =IF(F5="","",IF(RIGHT(LEFT(F5,13))=".","B",IF(RIGHT(LEFT(F5,13))="*","M",IF(RIGHT(LEFT(D5,13))="Z",8,IF(RIGHT(LEFT(D5,13))="X",9,IF(RIGHT(LEFT(F5,13))=RIGHT(LEFT(D5,13)),1,0)))))) -> 8 | AB5: =IF(F5="","",IF(RIGHT(LEFT(F5,14))=".","B",IF(RIGHT(LEFT(F5,14))="*","M",IF(RIGHT(LEFT(D5,14))="Z",8,IF(RIGHT(LEFT(D5,14))="X",9,IF(RIGHT(LEFT(F5,14))=RIGHT(LEFT(D5,14)),1,0)))))) -> 9 | AC5: =IF(F5="","",IF(RIGHT(LEFT(F5,15))=".","B",IF(RIGHT(LEFT(F5,15))="*","M",IF(RIGHT(LEFT(D5,15))="Z",8,IF(RIGHT(LEFT(D5,15))="X",9,IF(RIGHT(LEFT(F5,15))=RIGHT(LEFT(D5,15)),1,0)))))) -> 0 | AD5: =IF(F5="","",IF(RIGHT(LEFT(F5,16))=".","B",IF(RIGHT(LEFT(F5,16))="*","M",IF(RIGHT(LEFT(D5,16))="Z",8,IF(RIGHT(LEFT(D5,16))="X",9,IF(RIGHT(LEFT(F5,16))=RIGHT(LEFT(D5,16)),1,0)))))) -> 0 | AE5: =IF(F5="","",IF(RIGHT(LEFT(F5,17))=".","B",IF(RIGHT(LEFT(F5,17))="*","M",IF(RIGHT(LEFT(D5,17))="Z",8,IF(RIGHT(LEFT(D5,17))="X",9,IF(RIGHT(LEFT(F5,17))=RIGHT(LEFT(D5,17)),1,0)))))) -> 9 | AF5: =IF(F5="","",IF(RIGHT(LEFT(F5,18))=".","B",IF(RIGHT(LEFT(F5,18))="*","M",IF(RIGHT(LEFT(D5,18))="Z",8,IF(RIGHT(LEFT(D5,18))="X",9,IF(RIGHT(LEFT(F5,18))=RIGHT(LEFT(D5,18)),1,0)))))) -> 0 | AG5: =IF(F5="","",IF(RIGHT(LEFT(F5,19))=".","B",IF(RIGHT(LEFT(F5,19))="*","M",IF(RIGHT(LEFT(D5,19))="Z",8,IF(RIGHT(LEFT(D5,19))="X",9,IF(RIGHT(LEFT(F5,19))=RIGHT(LEFT(D5,19)),1,0)))))) -> 0 | AH5: =IF(F5="","",IF(RIGHT(LEFT(F5,20))=".","B",IF(RIGHT(LEFT(F5,20))="*","M",IF(RIGHT(LEFT(D5,20))="Z",8,IF(RIGHT(LEFT(D5,20))="X",9,IF(RIGHT(LEFT(F5,20))=RIGHT(LEFT(D5,20)),1,0)))))) -> 8 | AI5: =IF(F5="","",IF(RIGHT(LEFT(F5,21))=".","B",IF(RIGHT(LEFT(F5,21))="*","M",IF(RIGHT(LEFT(D5,21))="Z",8,IF(RIGHT(LEFT(D5,21))="X",9,IF(RIGHT(LEFT(F5,21))=RIGHT(LEFT(D5,21)),1,0)))))) -> 0 | AJ5: =IF(F5="","",IF(RIGHT(LEFT(F5,22))=".","B",IF(RIGHT(LEFT(F5,22))="*","M",IF(RIGHT(LEFT(D5,22))="Z",8,IF(RIGHT(LEFT(D5,22))="X",9,IF(RIGHT(LEFT(F5,22))=RIGHT(LEFT(D5,22)),1,0)))))) -> 0 | AK5: =IF(F5="","",IF(RIGHT(LEFT(F5,23))=".","B",IF(RIGHT(LEFT(F5,23))="*","M",IF(RIGHT(LEFT(D5,23))="Z",8,IF(RIGHT(LEFT(D5,23))="X",9,IF(RIGHT(LEFT(F5,23))=RIGHT(LEFT(D5,23)),1,0)))))) -> 0 | AL5: =IF(F5="","",IF(RIGHT(LEFT(F5,24))=".","B",IF(RIGHT(LEFT(F5,24))="*","M",IF(RIGHT(LEFT(D5,24))="Z",8,IF(RIGHT(LEFT(D5,24))="X",9,IF(RIGHT(LEFT(F5,24))=RIGHT(LEFT(D5,24)),1,0)))))) -> 0 | AM5: =IF(F5="","",IF(RIGHT(LEFT(F5,25))=".","B",IF(RIGHT(LEFT(F5,25))="*","M",IF(RIGHT(LEFT(D5,25))="Z",8,IF(RIGHT(LEFT(D5,25))="X",9,IF(RIGHT(LEFT(F5,25))=RIGHT(LEFT(D5,25)),1,0)))))) -> 0 | AN5: =IF(F5="","",IF(RIGHT(LEFT(F5,26))=".","B",IF(RIGHT(LEFT(F5,26))="*","M",IF(RIGHT(LEFT(D5,26))="Z",8,IF(RIGHT(LEFT(D5,26))="X",9,IF(RIGHT(LEFT(F5,26))=RIGHT(LEFT(D5,26)),1,0)))))) -> 9 | AO5: =IF(F5="","",IF(RIGHT(LEFT(F5,27))=".","B",IF(RIGHT(LEFT(F5,27))="*","M",IF(RIGHT(LEFT(D5,27))="Z",8,IF(RIGHT(LEFT(D5,27))="X",9,IF(RIGHT(LEFT(F5,27))=RIGHT(LEFT(D5,27)),1,0)))))) -> 1
A6: 2019 | B6: 123569 | C6: ZDCBCCDB | D6: ZDEBDAEBXDACZXCBXDCZABBEDXC | E6: ADDCECBA | F6: EDBBCBCACCADCDAECBBDDEBCBBA | G6: =IF(E6="","",IF(RIGHT(LEFT(E6,1))=".","B",IF(RIGHT(LEFT(E6,1))="*","M",IF(RIGHT(LEFT(C6,1))="Z",8,IF(RIGHT(LEFT(C6,1))="X",9,IF(RIGHT(LEFT(E6,1))=RIGHT(LEFT(C6,1)),1,0)))))) -> 8 | H6: =IF(E6="","",IF(RIGHT(LEFT(E6,2))=".","B",IF(RIGHT(LEFT(E6,2))="*","M",IF(RIGHT(LEFT(C6,2))="Z",8,IF(RIGHT(LEFT(C6,2))="X",9,IF(RIGHT(LEFT(E6,2))=RIGHT(LEFT(C6,2)),1,0)))))) -> 1 | I6: =IF(E6="","",IF(RIGHT(LEFT(E6,3))=".","B",IF(RIGHT(LEFT(E6,3))="*","M",IF(RIGHT(LEFT(C6,3))="Z",8,IF(RIGHT(LEFT(C6,3))="X",9,IF(RIGHT(LEFT(E6,3))=RIGHT(LEFT(C6,3)),1,0)))))) -> 0 | J6: =IF(E6="","",IF(RIGHT(LEFT(E6,4))=".","B",IF(RIGHT(LEFT(E6,4))="*","M",IF(RIGHT(LEFT(C6,4))="Z",8,IF(RIGHT(LEFT(C6,4))="X",9,IF(RIGHT(LEFT(E6,4))=RIGHT(LEFT(C6,4)),1,0)))))) -> 0 | K6: =IF(E6="","",IF(RIGHT(LEFT(E6,5))=".","B",IF(RIGHT(LEFT(E6,5))="*","M",IF(RIGHT(LEFT(C6,5))="Z",8,IF(RIGHT(LEFT(C6,5))="X",9,IF(RIGHT(LEFT(E6,5))=RIGHT(LEFT(C6,5)),1,0)))))) -> 0 | L6: =IF(E6="","",IF(RIGHT(LEFT(E6,6))=".","B",IF(RIGHT(LEFT(E6,6))="*","M",IF(RIGHT(LEFT(C6,6))="Z",8,IF(RIGHT(LEFT(C6,6))="X",9,IF(RIGHT(LEFT(E6,6))=RIGHT(LEFT(C6,6)),1,0)))))) -> 1 | M6: =IF(E6="","",IF(RIGHT(LEFT(E6,7))=".","B",IF(RIGHT(LEFT(E6,7))="*","M",IF(RIGHT(LEFT(C6,7))="Z",8,IF(RIGHT(LEFT(C6,7))="X",9,IF(RIGHT(LEFT(E6,7))=RIGHT(LEFT(C6,7)),1,0)))))) -> 0 | N6: =IF(E6="","",IF(RIGHT(LEFT(E6,8))=".","B",IF(RIGHT(LEFT(E6,8))="*","M",IF(RIGHT(LEFT(C6,8))="Z",8,IF(RIGHT(LEFT(C6,8))="X",9,IF(RIGHT(LEFT(E6,8))=RIGHT(LEFT(C6,8)),1,0)))))) -> 0 | O6: =IF(F6="","",IF(RIGHT(LEFT(F6,1))=".","B",IF(RIGHT(LEFT(F6,1))="*","M",IF(RIGHT(LEFT(D6,1))="Z",8,IF(RIGHT(LEFT(D6,1))="X",9,IF(RIGHT(LEFT(F6,1))=RIGHT(LEFT(D6,1)),1,0)))))) -> 8 | P6: =IF(F6="","",IF(RIGHT(LEFT(F6,2))=".","B",IF(RIGHT(LEFT(F6,2))="*","M",IF(RIGHT(LEFT(D6,2))="Z",8,IF(RIGHT(LEFT(D6,2))="X",9,IF(RIGHT(LEFT(F6,2))=RIGHT(LEFT(D6,2)),1,0)))))) -> 1 | Q6: =IF(F6="","",IF(RIGHT(LEFT(F6,3))=".","B",IF(RIGHT(LEFT(F6,3))="*","M",IF(RIGHT(LEFT(D6,3))="Z",8,IF(RIGHT(LEFT(D6,3))="X",9,IF(RIGHT(LEFT(F6,3))=RIGHT(LEFT(D6,3)),1,0)))))) -> 0 | R6: =IF(F6="","",IF(RIGHT(LEFT(F6,4))=".","B",IF(RIGHT(LEFT(F6,4))="*","M",IF(RIGHT(LEFT(D6,4))="Z",8,IF(RIGHT(LEFT(D6,4))="X",9,IF(RIGHT(LEFT(F6,4))=RIGHT(LEFT(D6,4)),1,0)))))) -> 1 | S6: =IF(F6="","",IF(RIGHT(LEFT(F6,5))=".","B",IF(RIGHT(LEFT(F6,5))="*","M",IF(RIGHT(LEFT(D6,5))="Z",8,IF(RIGHT(LEFT(D6,5))="X",9,IF(RIGHT(LEFT(F6,5))=RIGHT(LEFT(D6,5)),1,0)))))) -> 0 | T6: =IF(F6="","",IF(RIGHT(LEFT(F6,6))=".","B",IF(RIGHT(LEFT(F6,6))="*","M",IF(RIGHT(LEFT(D6,6))="Z",8,IF(RIGHT(LEFT(D6,6))="X",9,IF(RIGHT(LEFT(F6,6))=RIGHT(LEFT(D6,6)),1,0)))))) -> 0 | U6: =IF(F6="","",IF(RIGHT(LEFT(F6,7))=".","B",IF(RIGHT(LEFT(F6,7))="*","M",IF(RIGHT(LEFT(D6,7))="Z",8,IF(RIGHT(LEFT(D6,7))="X",9,IF(RIGHT(LEFT(F6,7))=RIGHT(LEFT(D6,7)),1,0)))))) -> 0 | V6: =IF(F6="","",IF(RIGHT(LEFT(F6,8))=".","B",IF(RIGHT(LEFT(F6,8))="*","M",IF(RIGHT(LEFT(D6,8))="Z",8,IF(RIGHT(LEFT(D6,8))="X",9,IF(RIGHT(LEFT(F6,8))=RIGHT(LEFT(D6,8)),1,0)))))) -> 0 | W6: =IF(F6="","",IF(RIGHT(LEFT(F6,9))=".","B",IF(RIGHT(LEFT(F6,9))="*","M",IF(RIGHT(LEFT(D6,9))="Z",8,IF(RIGHT(LEFT(D6,9))="X",9,IF(RIGHT(LEFT(F6,9))=RIGHT(LEFT(D6,9)),1,0)))))) -> 9 | X6: =IF(F6="","",IF(RIGHT(LEFT(F6,10))=".","B",IF(RIGHT(LEFT(F6,10))="*","M",IF(RIGHT(LEFT(D6,10))="Z",8,IF(RIGHT(LEFT(D6,10))="X",9,IF(RIGHT(LEFT(F6,10))=RIGHT(LEFT(D6,10)),1,0)))))) -> 0 | Y6: =IF(F6="","",IF(RIGHT(LEFT(F6,11))=".","B",IF(RIGHT(LEFT(F6,11))="*","M",IF(RIGHT(LEFT(D6,11))="Z",8,IF(RIGHT(LEFT(D6,11))="X",9,IF(RIGHT(LEFT(F6,11))=RIGHT(LEFT(D6,11)),1,0)))))) -> 1 | Z6: =IF(F6="","",IF(RIGHT(LEFT(F6,12))=".","B",IF(RIGHT(LEFT(F6,12))="*","M",IF(RIGHT(LEFT(D6,12))="Z",8,IF(RIGHT(LEFT(D6,12))="X",9,IF(RIGHT(LEFT(F6,12))=RIGHT(LEFT(D6,12)),1,0)))))) -> 0 | AA6: =IF(F6="","",IF(RIGHT(LEFT(F6,13))=".","B",IF(RIGHT(LEFT(F6,13))="*","M",IF(RIGHT(LEFT(D6,13))="Z",8,IF(RIGHT(LEFT(D6,13))="X",9,IF(RIGHT(LEFT(F6,13))=RIGHT(LEFT(D6,13)),1,0)))))) -> 8 | AB6: =IF(F6="","",IF(RIGHT(LEFT(F6,14))=".","B",IF(RIGHT(LEFT(F6,14))="*","M",IF(RIGHT(LEFT(D6,14))="Z",8,IF(RIGHT(LEFT(D6,14))="X",9,IF(RIGHT(LEFT(F6,14))=RIGHT(LEFT(D6,14)),1,0)))))) -> 9 | AC6: =IF(F6="","",IF(RIGHT(LEFT(F6,15))=".","B",IF(RIGHT(LEFT(F6,15))="*","M",IF(RIGHT(LEFT(D6,15))="Z",8,IF(RIGHT(LEFT(D6,15))="X",9,IF(RIGHT(LEFT(F6,15))=RIGHT(LEFT(D6,15)),1,0)))))) -> 0 | AD6: =IF(F6="","",IF(RIGHT(LEFT(F6,16))=".","B",IF(RIGHT(LEFT(F6,16))="*","M",IF(RIGHT(LEFT(D6,16))="Z",8,IF(RIGHT(LEFT(D6,16))="X",9,IF(RIGHT(LEFT(F6,16))=RIGHT(LEFT(D6,16)),1,0)))))) -> 0 | AE6: =IF(F6="","",IF(RIGHT(LEFT(F6,17))=".","B",IF(RIGHT(LEFT(F6,17))="*","M",IF(RIGHT(LEFT(D6,17))="Z",8,IF(RIGHT(LEFT(D6,17))="X",9,IF(RIGHT(LEFT(F6,17))=RIGHT(LEFT(D6,17)),1,0)))))) -> 9 | AF6: =IF(F6="","",IF(RIGHT(LEFT(F6,18))=".","B",IF(RIGHT(LEFT(F6,18))="*","M",IF(RIGHT(LEFT(D6,18))="Z",8,IF(RIGHT(LEFT(D6,18))="X",9,IF(RIGHT(LEFT(F6,18))=RIGHT(LEFT(D6,18)),1,0)))))) -> 0 | AG6: =IF(F6="","",IF(RIGHT(LEFT(F6,19))=".","B",IF(RIGHT(LEFT(F6,19))="*","M",IF(RIGHT(LEFT(D6,19))="Z",8,IF(RIGHT(LEFT(D6,19))="X",9,IF(RIGHT(LEFT(F6,19))=RIGHT(LEFT(D6,19)),1,0)))))) -> 0 | AH6: =IF(F6="","",IF(RIGHT(LEFT(F6,20))=".","B",IF(RIGHT(LEFT(F6,20))="*","M",IF(RIGHT(LEFT(D6,20))="Z",8,IF(RIGHT(LEFT(D6,20))="X",9,IF(RIGHT(LEFT(F6,20))=RIGHT(LEFT(D6,20)),1,0)))))) -> 8 | AI6: =IF(F6="","",IF(RIGHT(LEFT(F6,21))=".","B",IF(RIGHT(LEFT(F6,21))="*","M",IF(RIGHT(LEFT(D6,21))="Z",8,IF(RIGHT(LEFT(D6,21))="X",9,IF(RIGHT(LEFT(F6,21))=RIGHT(LEFT(D6,21)),1,0)))))) -> 0 | AJ6: =IF(F6="","",IF(RIGHT(LEFT(F6,22))=".","B",IF(RIGHT(LEFT(F6,22))="*","M",IF(RIGHT(LEFT(D6,22))="Z",8,IF(RIGHT(LEFT(D6,22))="X",9,IF(RIGHT(LEFT(F6,22))=RIGHT(LEFT(D6,22)),1,0)))))) -> 0 | AK6: =IF(F6="","",IF(RIGHT(LEFT(F6,23))=".","B",IF(RIGHT(LEFT(F6,23))="*","M",IF(RIGHT(LEFT(D6,23))="Z",8,IF(RIGHT(LEFT(D6,23))="X",9,IF(RIGHT(LEFT(F6,23))=RIGHT(LEFT(D6,23)),1,0)))))) -> 1 | AL6: =IF(F6="","",IF(RIGHT(LEFT(F6,24))=".","B",IF(RIGHT(LEFT(F6,24))="*","M",IF(RIGHT(LEFT(D6,24))="Z",8,IF(RIGHT(LEFT(D6,24))="X",9,IF(RIGHT(LEFT(F6,24))=RIGHT(LEFT(D6,24)),1,0)))))) -> 0 | AM6: =IF(F6="","",IF(RIGHT(LEFT(F6,25))=".","B",IF(RIGHT(LEFT(F6,25))="*","M",IF(RIGHT(LEFT(D6,25))="Z",8,IF(RIGHT(LEFT(D6,25))="X",9,IF(RIGHT(LEFT(F6,25))=RIGHT(LEFT(D6,25)),1,0)))))) -> 0 | AN6: =IF(F6="","",IF(RIGHT(LEFT(F6,26))=".","B",IF(RIGHT(LEFT(F6,26))="*","M",IF(RIGHT(LEFT(D6,26))="Z",8,IF(RIGHT(LEFT(D6,26))="X",9,IF(RIGHT(LEFT(F6,26))=RIGHT(LEFT(D6,26)),1,0)))))) -> 9 | AO6: =IF(F6="","",IF(RIGHT(LEFT(F6,27))=".","B",IF(RIGHT(LEFT(F6,27))="*","M",IF(RIGHT(LEFT(D6,27))="Z",8,IF(RIGHT(LEFT(D6,27))="X",9,IF(RIGHT(LEFT(F6,27))=RIGHT(LEFT(D6,27)),1,0)))))) -> 0
A7: 2019 | B7: 1181819 | C7: ZDCBCCDB | D7: DBCDECEDACECCDDBCADACEAXEXD | E7: ADCAACDD | F7: CBCCBBCADDCEECCAABCBDDECBCD | G7: =IF(E7="","",IF(RIGHT(LEFT(E7,1))=".","B",IF(RIGHT(LEFT(E7,1))="*","M",IF(RIGHT(LEFT(C7,1))="Z",8,IF(RIGHT(LEFT(C7,1))="X",9,IF(RIGHT(LEFT(E7,1))=RIGHT(LEFT(C7,1)),1,0)))))) -> 8 | H7: =IF(E7="","",IF(RIGHT(LEFT(E7,2))=".","B",IF(RIGHT(LEFT(E7,2))="*","M",IF(RIGHT(LEFT(C7,2))="Z",8,IF(RIGHT(LEFT(C7,2))="X",9,IF(RIGHT(LEFT(E7,2))=RIGHT(LEFT(C7,2)),1,0)))))) -> 1 | I7: =IF(E7="","",IF(RIGHT(LEFT(E7,3))=".","B",IF(RIGHT(LEFT(E7,3))="*","M",IF(RIGHT(LEFT(C7,3))="Z",8,IF(RIGHT(LEFT(C7,3))="X",9,IF(RIGHT(LEFT(E7,3))=RIGHT(LEFT(C7,3)),1,0)))))) -> 1 | J7: =IF(E7="","",IF(RIGHT(LEFT(E7,4))=".","B",IF(RIGHT(LEFT(E7,4))="*","M",IF(RIGHT(LEFT(C7,4))="Z",8,IF(RIGHT(LEFT(C7,4))="X",9,IF(RIGHT(LEFT(E7,4))=RIGHT(LEFT(C7,4)),1,0)))))) -> 0 | K7: =IF(E7="","",IF(RIGHT(LEFT(E7,5))=".","B",IF(RIGHT(LEFT(E7,5))="*","M",IF(RIGHT(LEFT(C7,5))="Z",8,IF(RIGHT(LEFT(C7,5))="X",9,IF(RIGHT(LEFT(E7,5))=RIGHT(LEFT(C7,5)),1,0)))))) -> 0 | L7: =IF(E7="","",IF(RIGHT(LEFT(E7,6))=".","B",IF(RIGHT(LEFT(E7,6))="*","M",IF(RIGHT(LEFT(C7,6))="Z",8,IF(RIGHT(LEFT(C7,6))="X",9,IF(RIGHT(LEFT(E7,6))=RIGHT(LEFT(C7,6)),1,0)))))) -> 1 | M7: =IF(E7="","",IF(RIGHT(LEFT(E7,7))=".","B",IF(RIGHT(LEFT(E7,7))="*","M",IF(RIGHT(LEFT(C7,7))="Z",8,IF(RIGHT(LEFT(C7,7))="X",9,IF(RIGHT(LEFT(E7,7))=RIGHT(LEFT(C7,7)),1,0)))))) -> 1 | N7: =IF(E7="","",IF(RIGHT(LEFT(E7,8))=".","B",IF(RIGHT(LEFT(E7,8))="*","M",IF(RIGHT(LEFT(C7,8))="Z",8,IF(RIGHT(LEFT(C7,8))="X",9,IF(RIGHT(LEFT(E7,8))=RIGHT(LEFT(C7,8)),1,0)))))) -> 0 | O7: =IF(F7="","",IF(RIGHT(LEFT(F7,1))=".","B",IF(RIGHT(LEFT(F7,1))="*","M",IF(RIGHT(LEFT(D7,1))="Z",8,IF(RIGHT(LEFT(D7,1))="X",9,IF(RIGHT(LEFT(F7,1))=RIGHT(LEFT(D7,1)),1,0)))))) -> 0 | P7: =IF(F7="","",IF(RIGHT(LEFT(F7,2))=".","B",IF(RIGHT(LEFT(F7,2))="*","M",IF(RIGHT(LEFT(D7,2))="Z",8,IF(RIGHT(LEFT(D7,2))="X",9,IF(RIGHT(LEFT(F7,2))=RIGHT(LEFT(D7,2)),1,0)))))) -> 1 | Q7: =IF(F7="","",IF(RIGHT(LEFT(F7,3))=".","B",IF(RIGHT(LEFT(F7,3))="*","M",IF(RIGHT(LEFT(D7,3))="Z",8,IF(RIGHT(LEFT(D7,3))="X",9,IF(RIGHT(LEFT(F7,3))=RIGHT(LEFT(D7,3)),1,0)))))) -> 1 | R7: =IF(F7="","",IF(RIGHT(LEFT(F7,4))=".","B",IF(RIGHT(LEFT(F7,4))="*","M",IF(RIGHT(LEFT(D7,4))="Z",8,IF(RIGHT(LEFT(D7,4))="X",9,IF(RIGHT(LEFT(F7,4))=RIGHT(LEFT(D7,4)),1,0)))))) -> 0 | S7: =IF(F7="","",IF(RIGHT(LEFT(F7,5))=".","B",IF(RIGHT(LEFT(F7,5))="*","M",IF(RIGHT(LEFT(D7,5))="Z",8,IF(RIGHT(LEFT(D7,5))="X",9,IF(RIGHT(LEFT(F7,5))=RIGHT(LEFT(D7,5)),1,0)))))) -> 0 | T7: =IF(F7="","",IF(RIGHT(LEFT(F7,6))=".","B",IF(RIGHT(LEFT(F7,6))="*","M",IF(RIGHT(LEFT(D7,6))="Z",8,IF(RIGHT(LEFT(D7,6))="X",9,IF(RIGHT(LEFT(F7,6))=RIGHT(LEFT(D7,6)),1,0)))))) -> 0 | U7: =IF(F7="","",IF(RIGHT(LEFT(F7,7))=".","B",IF(RIGHT(LEFT(F7,7))="*","M",IF(RIGHT(LEFT(D7,7))="Z",8,IF(RIGHT(LEFT(D7,7))="X",9,IF(RIGHT(LEFT(F7,7))=RIGHT(LEFT(D7,7)),1,0)))))) -> 0 | V7: =IF(F7="","",IF(RIGHT(LEFT(F7,8))=".","B",IF(RIGHT(LEFT(F7,8))="*","M",IF(RIGHT(LEFT(D7,8))="Z",8,IF(RIGHT(LEFT(D7,8))="X",9,IF(RIGHT(LEFT(F7,8))=RIGHT(LEFT(D7,8)),1,0)))))) -> 0 | W7: =IF(F7="","",IF(RIGHT(LEFT(F7,9))=".","B",IF(RIGHT(LEFT(F7,9))="*","M",IF(RIGHT(LEFT(D7,9))="Z",8,IF(RIGHT(LEFT(D7,9))="X",9,IF(RIGHT(LEFT(F7,9))=RIGHT(LEFT(D7,9)),1,0)))))) -> 0 | X7: =IF(F7="","",IF(RIGHT(LEFT(F7,10))=".","B",IF(RIGHT(LEFT(F7,10))="*","M",IF(RIGHT(LEFT(D7,10))="Z",8,IF(RIGHT(LEFT(D7,10))="X",9,IF(RIGHT(LEFT(F7,10))=RIGHT(LEFT(D7,10)),1,0)))))) -> 0 | Y7: =IF(F7="","",IF(RIGHT(LEFT(F7,11))=".","B",IF(RIGHT(LEFT(F7,11))="*","M",IF(RIGHT(LEFT(D7,11))="Z",8,IF(RIGHT(LEFT(D7,11))="X",9,IF(RIGHT(LEFT(F7,11))=RIGHT(LEFT(D7,11)),1,0)))))) -> 0 | Z7: =IF(F7="","",IF(RIGHT(LEFT(F7,12))=".","B",IF(RIGHT(LEFT(F7,12))="*","M",IF(RIGHT(LEFT(D7,12))="Z",8,IF(RIGHT(LEFT(D7,12))="X",9,IF(RIGHT(LEFT(F7,12))=RIGHT(LEFT(D7,12)),1,0)))))) -> 0 | AA7: =IF(F7="","",IF(RIGHT(LEFT(F7,13))=".","B",IF(RIGHT(LEFT(F7,13))="*","M",IF(RIGHT(LEFT(D7,13))="Z",8,IF(RIGHT(LEFT(D7,13))="X",9,IF(RIGHT(LEFT(F7,13))=RIGHT(LEFT(D7,13)),1,0)))))) -> 0 | AB7: =IF(F7="","",IF(RIGHT(LEFT(F7,14))=".","B",IF(RIGHT(LEFT(F7,14))="*","M",IF(RIGHT(LEFT(D7,14))="Z",8,IF(RIGHT(LEFT(D7,14))="X",9,IF(RIGHT(LEFT(F7,14))=RIGHT(LEFT(D7,14)),1,0)))))) -> 0 | AC7: =IF(F7="","",IF(RIGHT(LEFT(F7,15))=".","B",IF(RIGHT(LEFT(F7,15))="*","M",IF(RIGHT(LEFT(D7,15))="Z",8,IF(RIGHT(LEFT(D7,15))="X",9,IF(RIGHT(LEFT(F7,15))=RIGHT(LEFT(D7,15)),1,0)))))) -> 0 | AD7: =IF(F7="","",IF(RIGHT(LEFT(F7,16))=".","B",IF(RIGHT(LEFT(F7,16))="*","M",IF(RIGHT(LEFT(D7,16))="Z",8,IF(RIGHT(LEFT(D7,16))="X",9,IF(RIGHT(LEFT(F7,16))=RIGHT(LEFT(D7,16)),1,0)))))) -> 0 | AE7: =IF(F7="","",IF(RIGHT(LEFT(F7,17))=".","B",IF(RIGHT(LEFT(F7,17))="*","M",IF(RIGHT(LEFT(D7,17))="Z",8,IF(RIGHT(LEFT(D7,17))="X",9,IF(RIGHT(LEFT(F7,17))=RIGHT(LEFT(D7,17)),1,0)))))) -> 0 | AF7: =IF(F7="","",IF(RIGHT(LEFT(F7,18))=".","B",IF(RIGHT(LEFT(F7,18))="*","M",IF(RIGHT(LEFT(D7,18))="Z",8,IF(RIGHT(LEFT(D7,18))="X",9,IF(RIGHT(LEFT(F7,18))=RIGHT(LEFT(D7,18)),1,0)))))) -> 0 | AG7: =IF(F7="","",IF(RIGHT(LEFT(F7,19))=".","B",IF(RIGHT(LEFT(F7,19))="*","M",IF(RIGHT(LEFT(D7,19))="Z",8,IF(RIGHT(LEFT(D7,19))="X",9,IF(RIGHT(LEFT(F7,19))=RIGHT(LEFT(D7,19)),1,0)))))) -> 0 | AH7: =IF(F7="","",IF(RIGHT(LEFT(F7,20))=".","B",IF(RIGHT(LEFT(F7,20))="*","M",IF(RIGHT(LEFT(D7,20))="Z",8,IF(RIGHT(LEFT(D7,20))="X",9,IF(RIGHT(LEFT(F7,20))=RIGHT(LEFT(D7,20)),1,0)))))) -> 0 | AI7: =IF(F7="","",IF(RIGHT(LEFT(F7,21))=".","B",IF(RIGHT(LEFT(F7,21))="*","M",IF(RIGHT(LEFT(D7,21))="Z",8,IF(RIGHT(LEFT(D7,21))="X",9,IF(RIGHT(LEFT(F7,21))=RIGHT(LEFT(D7,21)),1,0)))))) -> 0 | AJ7: =IF(F7="","",IF(RIGHT(LEFT(F7,22))=".","B",IF(RIGHT(LEFT(F7,22))="*","M",IF(RIGHT(LEFT(D7,22))="Z",8,IF(RIGHT(LEFT(D7,22))="X",9,IF(RIGHT(LEFT(F7,22))=RIGHT(LEFT(D7,22)),1,0)))))) -> 0 | AK7: =IF(F7="","",IF(RIGHT(LEFT(F7,23))=".","B",IF(RIGHT(LEFT(F7,23))="*","M",IF(RIGHT(LEFT(D7,23))="Z",8,IF(RIGHT(LEFT(D7,23))="X",9,IF(RIGHT(LEFT(F7,23))=RIGHT(LEFT(D7,23)),1,0)))))) -> 0 | AL7: =IF(F7="","",IF(RIGHT(LEFT(F7,24))=".","B",IF(RIGHT(LEFT(F7,24))="*","M",IF(RIGHT(LEFT(D7,24))="Z",8,IF(RIGHT(LEFT(D7,24))="X",9,IF(RIGHT(LEFT(F7,24))=RIGHT(LEFT(D7,24)),1,0)))))) -> 9 | AM7: =IF(F7="","",IF(RIGHT(LEFT(F7,25))=".","B",IF(RIGHT(LEFT(F7,25))="*","M",IF(RIGHT(LEFT(D7,25))="Z",8,IF(RIGHT(LEFT(D7,25))="X",9,IF(RIGHT(LEFT(F7,25))=RIGHT(LEFT(D7,25)),1,0)))))) -> 0 | AN7: =IF(F7="","",IF(RIGHT(LEFT(F7,26))=".","B",IF(RIGHT(LEFT(F7,26))="*","M",IF(RIGHT(LEFT(D7,26))="Z",8,IF(RIGHT(LEFT(D7,26))="X",9,IF(RIGHT(LEFT(F7,26))=RIGHT(LEFT(D7,26)),1,0)))))) -> 9 | AO7: =IF(F7="","",IF(RIGHT(LEFT(F7,27))=".","B",IF(RIGHT(LEFT(F7,27))="*","M",IF(RIGHT(LEFT(D7,27))="Z",8,IF(RIGHT(LEFT(D7,27))="X",9,IF(RIGHT(LEFT(F7,27))=RIGHT(LEFT(D7,27)),1,0)))))) -> 1
A8: 2019 | B8: 123569 | C8: ZDCBCCDB | D8: ZDEBDAEBXDACZXCBXDCZABBEDXC | E8: BBCAABCD | F8: AE*DBDDEECAADBCBCCDDAABCBAC | G8: =IF(E8="","",IF(RIGHT(LEFT(E8,1))=".","B",IF(RIGHT(LEFT(E8,1))="*","M",IF(RIGHT(LEFT(C8,1))="Z",8,IF(RIGHT(LEFT(C8,1))="X",9,IF(RIGHT(LEFT(E8,1))=RIGHT(LEFT(C8,1)),1,0)))))) -> 8 | H8: =IF(E8="","",IF(RIGHT(LEFT(E8,2))=".","B",IF(RIGHT(LEFT(E8,2))="*","M",IF(RIGHT(LEFT(C8,2))="Z",8,IF(RIGHT(LEFT(C8,2))="X",9,IF(RIGHT(LEFT(E8,2))=RIGHT(LEFT(C8,2)),1,0)))))) -> 0 | I8: =IF(E8="","",IF(RIGHT(LEFT(E8,3))=".","B",IF(RIGHT(LEFT(E8,3))="*","M",IF(RIGHT(LEFT(C8,3))="Z",8,IF(RIGHT(LEFT(C8,3))="X",9,IF(RIGHT(LEFT(E8,3))=RIGHT(LEFT(C8,3)),1,0)))))) -> 1 | J8: =IF(E8="","",IF(RIGHT(LEFT(E8,4))=".","B",IF(RIGHT(LEFT(E8,4))="*","M",IF(RIGHT(LEFT(C8,4))="Z",8,IF(RIGHT(LEFT(C8,4))="X",9,IF(RIGHT(LEFT(E8,4))=RIGHT(LEFT(C8,4)),1,0)))))) -> 0 | K8: =IF(E8="","",IF(RIGHT(LEFT(E8,5))=".","B",IF(RIGHT(LEFT(E8,5))="*","M",IF(RIGHT(LEFT(C8,5))="Z",8,IF(RIGHT(LEFT(C8,5))="X",9,IF(RIGHT(LEFT(E8,5))=RIGHT(LEFT(C8,5)),1,0)))))) -> 0 | L8: =IF(E8="","",IF(RIGHT(LEFT(E8,6))=".","B",IF(RIGHT(LEFT(E8,6))="*","M",IF(RIGHT(LEFT(C8,6))="Z",8,IF(RIGHT(LEFT(C8,6))="X",9,IF(RIGHT(LEFT(E8,6))=RIGHT(LEFT(C8,6)),1,0)))))) -> 0 | M8: =IF(E8="","",IF(RIGHT(LEFT(E8,7))=".","B",IF(RIGHT(LEFT(E8,7))="*","M",IF(RIGHT(LEFT(C8,7))="Z",8,IF(RIGHT(LEFT(C8,7))="X",9,IF(RIGHT(LEFT(E8,7))=RIGHT(LEFT(C8,7)),1,0)))))) -> 0 | N8: =IF(E8="","",IF(RIGHT(LEFT(E8,8))=".","B",IF(RIGHT(LEFT(E8,8))="*","M",IF(RIGHT(LEFT(C8,8))="Z",8,IF(RIGHT(LEFT(C8,8))="X",9,IF(RIGHT(LEFT(E8,8))=RIGHT(LEFT(C8,8)),1,0)))))) -> 0 | O8: =IF(F8="","",IF(RIGHT(LEFT(F8,1))=".","B",IF(RIGHT(LEFT(F8,1))="*","M",IF(RIGHT(LEFT(D8,1))="Z",8,IF(RIGHT(LEFT(D8,1))="X",9,IF(RIGHT(LEFT(F8,1))=RIGHT(LEFT(D8,1)),1,0)))))) -> 8 | P8: =IF(F8="","",IF(RIGHT(LEFT(F8,2))=".","B",IF(RIGHT(LEFT(F8,2))="*","M",IF(RIGHT(LEFT(D8,2))="Z",8,IF(RIGHT(LEFT(D8,2))="X",9,IF(RIGHT(LEFT(F8,2))=RIGHT(LEFT(D8,2)),1,0)))))) -> 0 | Q8: =IF(F8="","",IF(RIGHT(LEFT(F8,3))=".","B",IF(RIGHT(LEFT(F8,3))="*","M",IF(RIGHT(LEFT(D8,3))="Z",8,IF(RIGHT(LEFT(D8,3))="X",9,IF(RIGHT(LEFT(F8,3))=RIGHT(LEFT(D8,3)),1,0)))))) -> M | R8: =IF(F8="","",IF(RIGHT(LEFT(F8,4))=".","B",IF(RIGHT(LEFT(F8,4))="*","M",IF(RIGHT(LEFT(D8,4))="Z",8,IF(RIGHT(LEFT(D8,4))="X",9,IF(RIGHT(LEFT(F8,4))=RIGHT(LEFT(D8,4)),1,0)))))) -> 0 | S8: =IF(F8="","",IF(RIGHT(LEFT(F8,5))=".","B",IF(RIGHT(LEFT(F8,5))="*","M",IF(RIGHT(LEFT(D8,5))="Z",8,IF(RIGHT(LEFT(D8,5))="X",9,IF(RIGHT(LEFT(F8,5))=RIGHT(LEFT(D8,5)),1,0)))))) -> 0 | T8: =IF(F8="","",IF(RIGHT(LEFT(F8,6))=".","B",IF(RIGHT(LEFT(F8,6))="*","M",IF(RIGHT(LEFT(D8,6))="Z",8,IF(RIGHT(LEFT(D8,6))="X",9,IF(RIGHT(LEFT(F8,6))=RIGHT(LEFT(D8,6)),1,0)))))) -> 0 | U8: =IF(F8="","",IF(RIGHT(LEFT(F8,7))=".","B",IF(RIGHT(LEFT(F8,7))="*","M",IF(RIGHT(LEFT(D8,7))="Z",8,IF(RIGHT(LEFT(D8,7))="X",9,IF(RIGHT(LEFT(F8,7))=RIGHT(LEFT(D8,7)),1,0)))))) -> 0 | V8: =IF(F8="","",IF(RIGHT(LEFT(F8,8))=".","B",IF(RIGHT(LEFT(F8,8))="*","M",IF(RIGHT(LEFT(D8,8))="Z",8,IF(RIGHT(LEFT(D8,8))="X",9,IF(RIGHT(LEFT(F8,8))=RIGHT(LEFT(D8,8)),1,0)))))) -> 0 | W8: =IF(F8="","",IF(RIGHT(LEFT(F8,9))=".","B",IF(RIGHT(LEFT(F8,9))="*","M",IF(RIGHT(LEFT(D8,9))="Z",8,IF(RIGHT(LEFT(D8,9))="X",9,IF(RIGHT(LEFT(F8,9))=RIGHT(LEFT(D8,9)),1,0)))))) -> 9 | X8: =IF(F8="","",IF(RIGHT(LEFT(F8,10))=".","B",IF(RIGHT(LEFT(F8,10))="*","M",IF(RIGHT(LEFT(D8,10))="Z",8,IF(RIGHT(LEFT(D8,10))="X",9,IF(RIGHT(LEFT(F8,10))=RIGHT(LEFT(D8,10)),1,0)))))) -> 0 | Y8: =IF(F8="","",IF(RIGHT(LEFT(F8,11))=".","B",IF(RIGHT(LEFT(F8,11))="*","M",IF(RIGHT(LEFT(D8,11))="Z",8,IF(RIGHT(LEFT(D8,11))="X",9,IF(RIGHT(LEFT(F8,11))=RIGHT(LEFT(D8,11)),1,0)))))) -> 1 | Z8: =IF(F8="","",IF(RIGHT(LEFT(F8,12))=".","B",IF(RIGHT(LEFT(F8,12))="*","M",IF(RIGHT(LEFT(D8,12))="Z",8,IF(RIGHT(LEFT(D8,12))="X",9,IF(RIGHT(LEFT(F8,12))=RIGHT(LEFT(D8,12)),1,0)))))) -> 0 | AA8: =IF(F8="","",IF(RIGHT(LEFT(F8,13))=".","B",IF(RIGHT(LEFT(F8,13))="*","M",IF(RIGHT(LEFT(D8,13))="Z",8,IF(RIGHT(LEFT(D8,13))="X",9,IF(RIGHT(LEFT(F8,13))=RIGHT(LEFT(D8,13)),1,0)))))) -> 8 | AB8: =IF(F8="","",IF(RIGHT(LEFT(F8,14))=".","B",IF(RIGHT(LEFT(F8,14))="*","M",IF(RIGHT(LEFT(D8,14))="Z",8,IF(RIGHT(LEFT(D8,14))="X",9,IF(RIGHT(LEFT(F8,14))=RIGHT(LEFT(D8,14)),1,0)))))) -> 9 | AC8: =IF(F8="","",IF(RIGHT(LEFT(F8,15))=".","B",IF(RIGHT(LEFT(F8,15))="*","M",IF(RIGHT(LEFT(D8,15))="Z",8,IF(RIGHT(LEFT(D8,15))="X",9,IF(RIGHT(LEFT(F8,15))=RIGHT(LEFT(D8,15)),1,0)))))) -> 1 | AD8: =IF(F8="","",IF(RIGHT(LEFT(F8,16))=".","B",IF(RIGHT(LEFT(F8,16))="*","M",IF(RIGHT(LEFT(D8,16))="Z",8,IF(RIGHT(LEFT(D8,16))="X",9,IF(RIGHT(LEFT(F8,16))=RIGHT(LEFT(D8,16)),1,0)))))) -> 1 | AE8: =IF(F8="","",IF(RIGHT(LEFT(F8,17))=".","B",IF(RIGHT(LEFT(F8,17))="*","M",IF(RIGHT(LEFT(D8,17))="Z",8,IF(RIGHT(LEFT(D8,17))="X",9,IF(RIGHT(LEFT(F8,17))=RIGHT(LEFT(D8,17)),1,0)))))) -> 9 | AF8: =IF(F8="","",IF(RIGHT(LEFT(F8,18))=".","B",IF(RIGHT(LEFT(F8,18))="*","M",IF(RIGHT(LEFT(D8,18))="Z",8,IF(RIGHT(LEFT(D8,18))="X",9,IF(RIGHT(LEFT(F8,18))=RIGHT(LEFT(D8,18)),1,0)))))) -> 0 | AG8: =IF(F8="","",IF(RIGHT(LEFT(F8,19))=".","B",IF(RIGHT(LEFT(F8,19))="*","M",IF(RIGHT(LEFT(D8,19))="Z",8,IF(RIGHT(LEFT(D8,19))="X",9,IF(RIGHT(LEFT(F8,19))=RIGHT(LEFT(D8,19)),1,0)))))) -> 0 | AH8: =IF(F8="","",IF(RIGHT(LEFT(F8,20))=".","B",IF(RIGHT(LEFT(F8,20))="*","M",IF(RIGHT(LEFT(D8,20))="Z",8,IF(RIGHT(LEFT(D8,20))="X",9,IF(RIGHT(LEFT(F8,20))=RIGHT(LEFT(D8,20)),1,0)))))) -> 8 | AI8: =IF(F8="","",IF(RIGHT(LEFT(F8,21))=".","B",IF(RIGHT(LEFT(F8,21))="*","M",IF(RIGHT(LEFT(D8,21))="Z",8,IF(RIGHT(LEFT(D8,21))="X",9,IF(RIGHT(LEFT(F8,21))=RIGHT(LEFT(D8,21)),1,0)))))) -> 1 | AJ8: =IF(F8="","",IF(RIGHT(LEFT(F8,22))=".","B",IF(RIGHT(LEFT(F8,22))="*","M",IF(RIGHT(LEFT(D8,22))="Z",8,IF(RIGHT(LEFT(D8,22))="X",9,IF(RIGHT(LEFT(F8,22))=RIGHT(LEFT(D8,22)),1,0)))))) -> 0 | AK8: =IF(F8="","",IF(RIGHT(LEFT(F8,23))=".","B",IF(RIGHT(LEFT(F8,23))="*","M",IF(RIGHT(LEFT(D8,23))="Z",8,IF(RIGHT(LEFT(D8,23))="X",9,IF(RIGHT(LEFT(F8,23))=RIGHT(LEFT(D8,23)),1,0)))))) -> 1 | AL8: =IF(F8="","",IF(RIGHT(LEFT(F8,24))=".","B",IF(RIGHT(LEFT(F8,24))="*","M",IF(RIGHT(LEFT(D8,24))="Z",8,IF(RIGHT(LEFT(D8,24))="X",9,IF(RIGHT(LEFT(F8,24))=RIGHT(LEFT(D8,24)),1,0)))))) -> 0 | AM8: =IF(F8="","",IF(RIGHT(LEFT(F8,25))=".","B",IF(RIGHT(LEFT(F8,25))="*","M",IF(RIGHT(LEFT(D8,25))="Z",8,IF(RIGHT(LEFT(D8,25))="X",9,IF(RIGHT(LEFT(F8,25))=RIGHT(LEFT(D8,25)),1,0)))))) -> 0 | AN8: =IF(F8="","",IF(RIGHT(LEFT(F8,26))=".","B",IF(RIGHT(LEFT(F8,26))="*","M",IF(RIGHT(LEFT(D8,26))="Z",8,IF(RIGHT(LEFT(D8,26))="X",9,IF(RIGHT(LEFT(F8,26))=RIGHT(LEFT(D8,26)),1,0)))))) -> 9 | AO8: =IF(F8="","",IF(RIGHT(LEFT(F8,27))=".","B",IF(RIGHT(LEFT(F8,27))="*","M",IF(RIGHT(LEFT(D8,27))="Z",8,IF(RIGHT(LEFT(D8,27))="X",9,IF(RIGHT(LEFT(F8,27))=RIGHT(LEFT(D8,27)),1,0)))))) -> 1
A9: 2019 | B9: 123569 | C9: ZDCBCCDB | D9: ZDEBDAEBXDACZXCBXDCZABBEDXC | E9: CDCDCCCC | F9: EDDDEBDBCDBBDCCCADBCCCCCCCD | G9: =IF(E9="","",IF(RIGHT(LEFT(E9,1))=".","B",IF(RIGHT(LEFT(E9,1))="*","M",IF(RIGHT(LEFT(C9,1))="Z",8,IF(RIGHT(LEFT(C9,1))="X",9,IF(RIGHT(LEFT(E9,1))=RIGHT(LEFT(C9,1)),1,0)))))) -> 8 | H9: =IF(E9="","",IF(RIGHT(LEFT(E9,2))=".","B",IF(RIGHT(LEFT(E9,2))="*","M",IF(RIGHT(LEFT(C9,2))="Z",8,IF(RIGHT(LEFT(C9,2))="X",9,IF(RIGHT(LEFT(E9,2))=RIGHT(LEFT(C9,2)),1,0)))))) -> 1 | I9: =IF(E9="","",IF(RIGHT(LEFT(E9,3))=".","B",IF(RIGHT(LEFT(E9,3))="*","M",IF(RIGHT(LEFT(C9,3))="Z",8,IF(RIGHT(LEFT(C9,3))="X",9,IF(RIGHT(LEFT(E9,3))=RIGHT(LEFT(C9,3)),1,0)))))) -> 1 | J9: =IF(E9="","",IF(RIGHT(LEFT(E9,4))=".","B",IF(RIGHT(LEFT(E9,4))="*","M",IF(RIGHT(LEFT(C9,4))="Z",8,IF(RIGHT(LEFT(C9,4))="X",9,IF(RIGHT(LEFT(E9,4))=RIGHT(LEFT(C9,4)),1,0)))))) -> 0 | K9: =IF(E9="","",IF(RIGHT(LEFT(E9,5))=".","B",IF(RIGHT(LEFT(E9,5))="*","M",IF(RIGHT(LEFT(C9,5))="Z",8,IF(RIGHT(LEFT(C9,5))="X",9,IF(RIGHT(LEFT(E9,5))=RIGHT(LEFT(C9,5)),1,0)))))) -> 1 | L9: =IF(E9="","",IF(RIGHT(LEFT(E9,6))=".","B",IF(RIGHT(LEFT(E9,6))="*","M",IF(RIGHT(LEFT(C9,6))="Z",8,IF(RIGHT(LEFT(C9,6))="X",9,IF(RIGHT(LEFT(E9,6))=RIGHT(LEFT(C9,6)),1,0)))))) -> 1 | M9: =IF(E9="","",IF(RIGHT(LEFT(E9,7))=".","B",IF(RIGHT(LEFT(E9,7))="*","M",IF(RIGHT(LEFT(C9,7))="Z",8,IF(RIGHT(LEFT(C9,7))="X",9,IF(RIGHT(LEFT(E9,7))=RIGHT(LEFT(C9,7)),1,0)))))) -> 0 | N9: =IF(E9="","",IF(RIGHT(LEFT(E9,8))=".","B",IF(RIGHT(LEFT(E9,8))="*","M",IF(RIGHT(LEFT(C9,8))="Z",8,IF(RIGHT(LEFT(C9,8))="X",9,IF(RIGHT(LEFT(E9,8))=RIGHT(LEFT(C9,8)),1,0)))))) -> 0 | O9: =IF(F9="","",IF(RIGHT(LEFT(F9,1))=".","B",IF(RIGHT(LEFT(F9,1))="*","M",IF(RIGHT(LEFT(D9,1))="Z",8,IF(RIGHT(LEFT(D9,1))="X",9,IF(RIGHT(LEFT(F9,1))=RIGHT(LEFT(D9,1)),1,0)))))) -> 8 | P9: =IF(F9="","",IF(RIGHT(LEFT(F9,2))=".","B",IF(RIGHT(LEFT(F9,2))="*","M",IF(RIGHT(LEFT(D9,2))="Z",8,IF(RIGHT(LEFT(D9,2))="X",9,IF(RIGHT(LEFT(F9,2))=RIGHT(LEFT(D9,2)),1,0)))))) -> 1 | Q9: =IF(F9="","",IF(RIGHT(LEFT(F9,3))=".","B",IF(RIGHT(LEFT(F9,3))="*","M",IF(RIGHT(LEFT(D9,3))="Z",8,IF(RIGHT(LEFT(D9,3))="X",9,IF(RIGHT(LEFT(F9,3))=RIGHT(LEFT(D9,3)),1,0)))))) -> 0 | R9: =IF(F9="","",IF(RIGHT(LEFT(F9,4))=".","B",IF(RIGHT(LEFT(F9,4))="*","M",IF(RIGHT(LEFT(D9,4))="Z",8,IF(RIGHT(LEFT(D9,4))="X",9,IF(RIGHT(LEFT(F9,4))=RIGHT(LEFT(D9,4)),1,0)))))) -> 0 | S9: =IF(F9="","",IF(RIGHT(LEFT(F9,5))=".","B",IF(RIGHT(LEFT(F9,5))="*","M",IF(RIGHT(LEFT(D9,5))="Z",8,IF(RIGHT(LEFT(D9,5))="X",9,IF(RIGHT(LEFT(F9,5))=RIGHT(LEFT(D9,5)),1,0)))))) -> 0 | T9: =IF(F9="","",IF(RIGHT(LEFT(F9,6))=".","B",IF(RIGHT(LEFT(F9,6))="*","M",IF(RIGHT(LEFT(D9,6))="Z",8,IF(RIGHT(LEFT(D9,6))="X",9,IF(RIGHT(LEFT(F9,6))=RIGHT(LEFT(D9,6)),1,0)))))) -> 0 | U9: =IF(F9="","",IF(RIGHT(LEFT(F9,7))=".","B",IF(RIGHT(LEFT(F9,7))="*","M",IF(RIGHT(LEFT(D9,7))="Z",8,IF(RIGHT(LEFT(D9,7))="X",9,IF(RIGHT(LEFT(F9,7))=RIGHT(LEFT(D9,7)),1,0)))))) -> 0 | V9: =IF(F9="","",IF(RIGHT(LEFT(F9,8))=".","B",IF(RIGHT(LEFT(F9,8))="*","M",IF(RIGHT(LEFT(D9,8))="Z",8,IF(RIGHT(LEFT(D9,8))="X",9,IF(RIGHT(LEFT(F9,8))=RIGHT(LEFT(D9,8)),1,0)))))) -> 1 | W9: =IF(F9="","",IF(RIGHT(LEFT(F9,9))=".","B",IF(RIGHT(LEFT(F9,9))="*","M",IF(RIGHT(LEFT(D9,9))="Z",8,IF(RIGHT(LEFT(D9,9))="X",9,IF(RIGHT(LEFT(F9,9))=RIGHT(LEFT(D9,9)),1,0)))))) -> 9 | X9: =IF(F9="","",IF(RIGHT(LEFT(F9,10))=".","B",IF(RIGHT(LEFT(F9,10))="*","M",IF(RIGHT(LEFT(D9,10))="Z",8,IF(RIGHT(LEFT(D9,10))="X",9,IF(RIGHT(LEFT(F9,10))=RIGHT(LEFT(D9,10)),1,0)))))) -> 1 | Y9: =IF(F9="","",IF(RIGHT(LEFT(F9,11))=".","B",IF(RIGHT(LEFT(F9,11))="*","M",IF(RIGHT(LEFT(D9,11))="Z",8,IF(RIGHT(LEFT(D9,11))="X",9,IF(RIGHT(LEFT(F9,11))=RIGHT(LEFT(D9,11)),1,0)))))) -> 0 | Z9: =IF(F9="","",IF(RIGHT(LEFT(F9,12))=".","B",IF(RIGHT(LEFT(F9,12))="*","M",IF(RIGHT(LEFT(D9,12))="Z",8,IF(RIGHT(LEFT(D9,12))="X",9,IF(RIGHT(LEFT(F9,12))=RIGHT(LEFT(D9,12)),1,0)))))) -> 0 | AA9: =IF(F9="","",IF(RIGHT(LEFT(F9,13))=".","B",IF(RIGHT(LEFT(F9,13))="*","M",IF(RIGHT(LEFT(D9,13))="Z",8,IF(RIGHT(LEFT(D9,13))="X",9,IF(RIGHT(LEFT(F9,13))=RIGHT(LEFT(D9,13)),1,0)))))) -> 8 | AB9: =IF(F9="","",IF(RIGHT(LEFT(F9,14))=".","B",IF(RIGHT(LEFT(F9,14))="*","M",IF(RIGHT(LEFT(D9,14))="Z",8,IF(RIGHT(LEFT(D9,14))="X",9,IF(RIGHT(LEFT(F9,14))=RIGHT(LEFT(D9,14)),1,0)))))) -> 9 | AC9: =IF(F9="","",IF(RIGHT(LEFT(F9,15))=".","B",IF(RIGHT(LEFT(F9,15))="*","M",IF(RIGHT(LEFT(D9,15))="Z",8,IF(RIGHT(LEFT(D9,15))="X",9,IF(RIGHT(LEFT(F9,15))=RIGHT(LEFT(D9,15)),1,0)))))) -> 1 | AD9: =IF(F9="","",IF(RIGHT(LEFT(F9,16))=".","B",IF(RIGHT(LEFT(F9,16))="*","M",IF(RIGHT(LEFT(D9,16))="Z",8,IF(RIGHT(LEFT(D9,16))="X",9,IF(RIGHT(LEFT(F9,16))=RIGHT(LEFT(D9,16)),1,0)))))) -> 0 | AE9: =IF(F9="","",IF(RIGHT(LEFT(F9,17))=".","B",IF(RIGHT(LEFT(F9,17))="*","M",IF(RIGHT(LEFT(D9,17))="Z",8,IF(RIGHT(LEFT(D9,17))="X",9,IF(RIGHT(LEFT(F9,17))=RIGHT(LEFT(D9,17)),1,0)))))) -> 9 | AF9: =IF(F9="","",IF(RIGHT(LEFT(F9,18))=".","B",IF(RIGHT(LEFT(F9,18))="*","M",IF(RIGHT(LEFT(D9,18))="Z",8,IF(RIGHT(LEFT(D9,18))="X",9,IF(RIGHT(LEFT(F9,18))=RIGHT(LEFT(D9,18)),1,0)))))) -> 1 | AG9: =IF(F9="","",IF(RIGHT(LEFT(F9,19))=".","B",IF(RIGHT(LEFT(F9,19))="*","M",IF(RIGHT(LEFT(D9,19))="Z",8,IF(RIGHT(LEFT(D9,19))="X",9,IF(RIGHT(LEFT(F9,19))=RIGHT(LEFT(D9,19)),1,0)))))) -> 0 | AH9: =IF(F9="","",IF(RIGHT(LEFT(F9,20))=".","B",IF(RIGHT(LEFT(F9,20))="*","M",IF(RIGHT(LEFT(D9,20))="Z",8,IF(RIGHT(LEFT(D9,20))="X",9,IF(RIGHT(LEFT(F9,20))=RIGHT(LEFT(D9,20)),1,0)))))) -> 8 | AI9: =IF(F9="","",IF(RIGHT(LEFT(F9,21))=".","B",IF(RIGHT(LEFT(F9,21))="*","M",IF(RIGHT(LEFT(D9,21))="Z",8,IF(RIGHT(LEFT(D9,21))="X",9,IF(RIGHT(LEFT(F9,21))=RIGHT(LEFT(D9,21)),1,0)))))) -> 0 | AJ9: =IF(F9="","",IF(RIGHT(LEFT(F9,22))=".","B",IF(RIGHT(LEFT(F9,22))="*","M",IF(RIGHT(LEFT(D9,22))="Z",8,IF(RIGHT(LEFT(D9,22))="X",9,IF(RIGHT(LEFT(F9,22))=RIGHT(LEFT(D9,22)),1,0)))))) -> 0 | AK9: =IF(F9="","",IF(RIGHT(LEFT(F9,23))=".","B",IF(RIGHT(LEFT(F9,23))="*","M",IF(RIGHT(LEFT(D9,23))="Z",8,IF(RIGHT(LEFT(D9,23))="X",9,IF(RIGHT(LEFT(F9,23))=RIGHT(LEFT(D9,23)),1,0)))))) -> 0 | AL9: =IF(F9="","",IF(RIGHT(LEFT(F9,24))=".","B",IF(RIGHT(LEFT(F9,24))="*","M",IF(RIGHT(LEFT(D9,24))="Z",8,IF(RIGHT(LEFT(D9,24))="X",9,IF(RIGHT(LEFT(F9,24))=RIGHT(LEFT(D9,24)),1,0)))))) -> 0 | AM9: =IF(F9="","",IF(RIGHT(LEFT(F9,25))=".","B",IF(RIGHT(LEFT(F9,25))="*","M",IF(RIGHT(LEFT(D9,25))="Z",8,IF(RIGHT(LEFT(D9,25))="X",9,IF(RIGHT(LEFT(F9,25))=RIGHT(LEFT(D9,25)),1,0)))))) -> 0 | AN9: =IF(F9="","",IF(RIGHT(LEFT(F9,26))=".","B",IF(RIGHT(LEFT(F9,26))="*","M",IF(RIGHT(LEFT(D9,26))="Z",8,IF(RIGHT(LEFT(D9,26))="X",9,IF(RIGHT(LEFT(F9,26))=RIGHT(LEFT(D9,26)),1,0)))))) -> 9 | AO9: =IF(F9="","",IF(RIGHT(LEFT(F9,27))=".","B",IF(RIGHT(LEFT(F9,27))="*","M",IF(RIGHT(LEFT(D9,27))="Z",8,IF(RIGHT(LEFT(D9,27))="X",9,IF(RIGHT(LEFT(F9,27))=RIGHT(LEFT(D9,27)),1,0)))))) -> 0
A10: 2019 | B10: 1103831 | C10: ZDCBCCDB | D10: ZBBZBEBEDDEDDAZXCDEECACAXAB | E10: ADDBCDDC | F10: EBABDEDBCADBECDADBCEADBECAE | G10: =IF(E10="","",IF(RIGHT(LEFT(E10,1))=".","B",IF(RIGHT(LEFT(E10,1))="*","M",IF(RIGHT(LEFT(C10,1))="Z",8,IF(RIGHT(LEFT(C10,1))="X",9,IF(RIGHT(LEFT(E10,1))=RIGHT(LEFT(C10,1)),1,0)))))) -> 8 | H10: =IF(E10="","",IF(RIGHT(LEFT(E10,2))=".","B",IF(RIGHT(LEFT(E10,2))="*","M",IF(RIGHT(LEFT(C10,2))="Z",8,IF(RIGHT(LEFT(C10,2))="X",9,IF(RIGHT(LEFT(E10,2))=RIGHT(LEFT(C10,2)),1,0)))))) -> 1 | I10: =IF(E10="","",IF(RIGHT(LEFT(E10,3))=".","B",IF(RIGHT(LEFT(E10,3))="*","M",IF(RIGHT(LEFT(C10,3))="Z",8,IF(RIGHT(LEFT(C10,3))="X",9,IF(RIGHT(LEFT(E10,3))=RIGHT(LEFT(C10,3)),1,0)))))) -> 0 | J10: =IF(E10="","",IF(RIGHT(LEFT(E10,4))=".","B",IF(RIGHT(LEFT(E10,4))="*","M",IF(RIGHT(LEFT(C10,4))="Z",8,IF(RIGHT(LEFT(C10,4))="X",9,IF(RIGHT(LEFT(E10,4))=RIGHT(LEFT(C10,4)),1,0)))))) -> 1 | K10: =IF(E10="","",IF(RIGHT(LEFT(E10,5))=".","B",IF(RIGHT(LEFT(E10,5))="*","M",IF(RIGHT(LEFT(C10,5))="Z",8,IF(RIGHT(LEFT(C10,5))="X",9,IF(RIGHT(LEFT(E10,5))=RIGHT(LEFT(C10,5)),1,0)))))) -> 1 | L10: =IF(E10="","",IF(RIGHT(LEFT(E10,6))=".","B",IF(RIGHT(LEFT(E10,6))="*","M",IF(RIGHT(LEFT(C10,6))="Z",8,IF(RIGHT(LEFT(C10,6))="X",9,IF(RIGHT(LEFT(E10,6))=RIGHT(LEFT(C10,6)),1,0)))))) -> 0 | M10: =IF(E10="","",IF(RIGHT(LEFT(E10,7))=".","B",IF(RIGHT(LEFT(E10,7))="*","M",IF(RIGHT(LEFT(C10,7))="Z",8,IF(RIGHT(LEFT(C10,7))="X",9,IF(RIGHT(LEFT(E10,7))=RIGHT(LEFT(C10,7)),1,0)))))) -> 1 | N10: =IF(E10="","",IF(RIGHT(LEFT(E10,8))=".","B",IF(RIGHT(LEFT(E10,8))="*","M",IF(RIGHT(LEFT(C10,8))="Z",8,IF(RIGHT(LEFT(C10,8))="X",9,IF(RIGHT(LEFT(E10,8))=RIGHT(LEFT(C10,8)),1,0)))))) -> 0 | O10: =IF(F10="","",IF(RIGHT(LEFT(F10,1))=".","B",IF(RIGHT(LEFT(F10,1))="*","M",IF(RIGHT(LEFT(D10,1))="Z",8,IF(RIGHT(LEFT(D10,1))="X",9,IF(RIGHT(LEFT(F10,1))=RIGHT(LEFT(D10,1)),1,0)))))) -> 8 | P10: =IF(F10="","",IF(RIGHT(LEFT(F10,2))=".","B",IF(RIGHT(LEFT(F10,2))="*","M",IF(RIGHT(LEFT(D10,2))="Z",8,IF(RIGHT(LEFT(D10,2))="X",9,IF(RIGHT(LEFT(F10,2))=RIGHT(LEFT(D10,2)),1,0)))))) -> 1 | Q10: =IF(F10="","",IF(RIGHT(LEFT(F10,3))=".","B",IF(RIGHT(LEFT(F10,3))="*","M",IF(RIGHT(LEFT(D10,3))="Z",8,IF(RIGHT(LEFT(D10,3))="X",9,IF(RIGHT(LEFT(F10,3))=RIGHT(LEFT(D10,3)),1,0)))))) -> 0 | R10: =IF(F10="","",IF(RIGHT(LEFT(F10,4))=".","B",IF(RIGHT(LEFT(F10,4))="*","M",IF(RIGHT(LEFT(D10,4))="Z",8,IF(RIGHT(LEFT(D10,4))="X",9,IF(RIGHT(LEFT(F10,4))=RIGHT(LEFT(D10,4)),1,0)))))) -> 8 | S10: =IF(F10="","",IF(RIGHT(LEFT(F10,5))=".","B",IF(RIGHT(LEFT(F10,5))="*","M",IF(RIGHT(LEFT(D10,5))="Z",8,IF(RIGHT(LEFT(D10,5))="X",9,IF(RIGHT(LEFT(F10,5))=RIGHT(LEFT(D10,5)),1,0)))))) -> 0 | T10: =IF(F10="","",IF(RIGHT(LEFT(F10,6))=".","B",IF(RIGHT(LEFT(F10,6))="*","M",IF(RIGHT(LEFT(D10,6))="Z",8,IF(RIGHT(LEFT(D10,6))="X",9,IF(RIGHT(LEFT(F10,6))=RIGHT(LEFT(D10,6)),1,0)))))) -> 1 | U10: =IF(F10="","",IF(RIGHT(LEFT(F10,7))=".","B",IF(RIGHT(LEFT(F10,7))="*","M",IF(RIGHT(LEFT(D10,7))="Z",8,IF(RIGHT(LEFT(D10,7))="X",9,IF(RIGHT(LEFT(F10,7))=RIGHT(LEFT(D10,7)),1,0)))))) -> 0 | V10: =IF(F10="","",IF(RIGHT(LEFT(F10,8))=".","B",IF(RIGHT(LEFT(F10,8))="*","M",IF(RIGHT(LEFT(D10,8))="Z",8,IF(RIGHT(LEFT(D10,8))="X",9,IF(RIGHT(LEFT(F10,8))=RIGHT(LEFT(D10,8)),1,0)))))) -> 0 | W10: =IF(F10="","",IF(RIGHT(LEFT(F10,9))=".","B",IF(RIGHT(LEFT(F10,9))="*","M",IF(RIGHT(LEFT(D10,9))="Z",8,IF(RIGHT(LEFT(D10,9))="X",9,IF(RIGHT(LEFT(F10,9))=RIGHT(LEFT(D10,9)),1,0)))))) -> 0 | X10: =IF(F10="","",IF(RIGHT(LEFT(F10,10))=".","B",IF(RIGHT(LEFT(F10,10))="*","M",IF(RIGHT(LEFT(D10,10))="Z",8,IF(RIGHT(LEFT(D10,10))="X",9,IF(RIGHT(LEFT(F10,10))=RIGHT(LEFT(D10,10)),1,0)))))) -> 0 | Y10: =IF(F10="","",IF(RIGHT(LEFT(F10,11))=".","B",IF(RIGHT(LEFT(F10,11))="*","M",IF(RIGHT(LEFT(D10,11))="Z",8,IF(RIGHT(LEFT(D10,11))="X",9,IF(RIGHT(LEFT(F10,11))=RIGHT(LEFT(D10,11)),1,0)))))) -> 0 | Z10: =IF(F10="","",IF(RIGHT(LEFT(F10,12))=".","B",IF(RIGHT(LEFT(F10,12))="*","M",IF(RIGHT(LEFT(D10,12))="Z",8,IF(RIGHT(LEFT(D10,12))="X",9,IF(RIGHT(LEFT(F10,12))=RIGHT(LEFT(D10,12)),1,0)))))) -> 0 | AA10: =IF(F10="","",IF(RIGHT(LEFT(F10,13))=".","B",IF(RIGHT(LEFT(F10,13))="*","M",IF(RIGHT(LEFT(D10,13))="Z",8,IF(RIGHT(LEFT(D10,13))="X",9,IF(RIGHT(LEFT(F10,13))=RIGHT(LEFT(D10,13)),1,0)))))) -> 0 | AB10: =IF(F10="","",IF(RIGHT(LEFT(F10,14))=".","B",IF(RIGHT(LEFT(F10,14))="*","M",IF(RIGHT(LEFT(D10,14))="Z",8,IF(RIGHT(LEFT(D10,14))="X",9,IF(RIGHT(LEFT(F10,14))=RIGHT(LEFT(D10,14)),1,0)))))) -> 0 | AC10: =IF(F10="","",IF(RIGHT(LEFT(F10,15))=".","B",IF(RIGHT(LEFT(F10,15))="*","M",IF(RIGHT(LEFT(D10,15))="Z",8,IF(RIGHT(LEFT(D10,15))="X",9,IF(RIGHT(LEFT(F10,15))=RIGHT(LEFT(D10,15)),1,0)))))) -> 8 | AD10: =IF(F10="","",IF(RIGHT(LEFT(F10,16))=".","B",IF(RIGHT(LEFT(F10,16))="*","M",IF(RIGHT(LEFT(D10,16))="Z",8,IF(RIGHT(LEFT(D10,16))="X",9,IF(RIGHT(LEFT(F10,16))=RIGHT(LEFT(D10,16)),1,0)))))) -> 9 | AE10: =IF(F10="","",IF(RIGHT(LEFT(F10,17))=".","B",IF(RIGHT(LEFT(F10,17))="*","M",IF(RIGHT(LEFT(D10,17))="Z",8,IF(RIGHT(LEFT(D10,17))="X",9,IF(RIGHT(LEFT(F10,17))=RIGHT(LEFT(D10,17)),1,0)))))) -> 0 | AF10: =IF(F10="","",IF(RIGHT(LEFT(F10,18))=".","B",IF(RIGHT(LEFT(F10,18))="*","M",IF(RIGHT(LEFT(D10,18))="Z",8,IF(RIGHT(LEFT(D10,18))="X",9,IF(RIGHT(LEFT(F10,18))=RIGHT(LEFT(D10,18)),1,0)))))) -> 0 | AG10: =IF(F10="","",IF(RIGHT(LEFT(F10,19))=".","B",IF(RIGHT(LEFT(F10,19))="*","M",IF(RIGHT(LEFT(D10,19))="Z",8,IF(RIGHT(LEFT(D10,19))="X",9,IF(RIGHT(LEFT(F10,19))=RIGHT(LEFT(D10,19)),1,0)))))) -> 0 | AH10: =IF(F10="","",IF(RIGHT(LEFT(F10,20))=".","B",IF(RIGHT(LEFT(F10,20))="*","M",IF(RIGHT(LEFT(D10,20))="Z",8,IF(RIGHT(LEFT(D10,20))="X",9,IF(RIGHT(LEFT(F10,20))=RIGHT(LEFT(D10,20)),1,0)))))) -> 1 | AI10: =IF(F10="","",IF(RIGHT(LEFT(F10,21))=".","B",IF(RIGHT(LEFT(F10,21))="*","M",IF(RIGHT(LEFT(D10,21))="Z",8,IF(RIGHT(LEFT(D10,21))="X",9,IF(RIGHT(LEFT(F10,21))=RIGHT(LEFT(D10,21)),1,0)))))) -> 0 | AJ10: =IF(F10="","",IF(RIGHT(LEFT(F10,22))=".","B",IF(RIGHT(LEFT(F10,22))="*","M",IF(RIGHT(LEFT(D10,22))="Z",8,IF(RIGHT(LEFT(D10,22))="X",9,IF(RIGHT(LEFT(F10,22))=RIGHT(LEFT(D10,22)),1,0)))))) -> 0 | AK10: =IF(F10="","",IF(RIGHT(LEFT(F10,23))=".","B",IF(RIGHT(LEFT(F10,23))="*","M",IF(RIGHT(LEFT(D10,23))="Z",8,IF(RIGHT(LEFT(D10,23))="X",9,IF(RIGHT(LEFT(F10,23))=RIGHT(LEFT(D10,23)),1,0)))))) -> 0 | AL10: =IF(F10="","",IF(RIGHT(LEFT(F10,24))=".","B",IF(RIGHT(LEFT(F10,24))="*","M",IF(RIGHT(LEFT(D10,24))="Z",8,IF(RIGHT(LEFT(D10,24))="X",9,IF(RIGHT(LEFT(F10,24))=RIGHT(LEFT(D10,24)),1,0)))))) -> 0 | AM10: =IF(F10="","",IF(RIGHT(LEFT(F10,25))=".","B",IF(RIGHT(LEFT(F10,25))="*","M",IF(RIGHT(LEFT(D10,25))="Z",8,IF(RIGHT(LEFT(D10,25))="X",9,IF(RIGHT(LEFT(F10,25))=RIGHT(LEFT(D10,25)),1,0)))))) -> 9 | AN10: =IF(F10="","",IF(RIGHT(LEFT(F10,26))=".","B",IF(RIGHT(LEFT(F10,26))="*","M",IF(RIGHT(LEFT(D10,26))="Z",8,IF(RIGHT(LEFT(D10,26))="X",9,IF(RIGHT(LEFT(F10,26))=RIGHT(LEFT(D10,26)),1,0)))))) -> 1 | AO10: =IF(F10="","",IF(RIGHT(LEFT(F10,27))=".","B",IF(RIGHT(LEFT(F10,27))="*","M",IF(RIGHT(LEFT(D10,27))="Z",8,IF(RIGHT(LEFT(D10,27))="X",9,IF(RIGHT(LEFT(F10,27))=RIGHT(LEFT(D10,27)),1,0)))))) -> 0
A11: 2019 | B11: 121880 | C11: ZDCBCCDB | D11: BXCAXDEXCBECDACEDACADEBXBBE | E11: ADDAEBDA | F11: ABBAABCDCECCDADECACBBBDCDCD | G11: =IF(E11="","",IF(RIGHT(LEFT(E11,1))=".","B",IF(RIGHT(LEFT(E11,1))="*","M",IF(RIGHT(LEFT(C11,1))="Z",8,IF(RIGHT(LEFT(C11,1))="X",9,IF(RIGHT(LEFT(E11,1))=RIGHT(LEFT(C11,1)),1,0)))))) -> 8 | H11: =IF(E11="","",IF(RIGHT(LEFT(E11,2))=".","B",IF(RIGHT(LEFT(E11,2))="*","M",IF(RIGHT(LEFT(C11,2))="Z",8,IF(RIGHT(LEFT(C11,2))="X",9,IF(RIGHT(LEFT(E11,2))=RIGHT(LEFT(C11,2)),1,0)))))) -> 1 | I11: =IF(E11="","",IF(RIGHT(LEFT(E11,3))=".","B",IF(RIGHT(LEFT(E11,3))="*","M",IF(RIGHT(LEFT(C11,3))="Z",8,IF(RIGHT(LEFT(C11,3))="X",9,IF(RIGHT(LEFT(E11,3))=RIGHT(LEFT(C11,3)),1,0)))))) -> 0 | J11: =IF(E11="","",IF(RIGHT(LEFT(E11,4))=".","B",IF(RIGHT(LEFT(E11,4))="*","M",IF(RIGHT(LEFT(C11,4))="Z",8,IF(RIGHT(LEFT(C11,4))="X",9,IF(RIGHT(LEFT(E11,4))=RIGHT(LEFT(C11,4)),1,0)))))) -> 0 | K11: =IF(E11="","",IF(RIGHT(LEFT(E11,5))=".","B",IF(RIGHT(LEFT(E11,5))="*","M",IF(RIGHT(LEFT(C11,5))="Z",8,IF(RIGHT(LEFT(C11,5))="X",9,IF(RIGHT(LEFT(E11,5))=RIGHT(LEFT(C11,5)),1,0)))))) -> 0 | L11: =IF(E11="","",IF(RIGHT(LEFT(E11,6))=".","B",IF(RIGHT(LEFT(E11,6))="*","M",IF(RIGHT(LEFT(C11,6))="Z",8,IF(RIGHT(LEFT(C11,6))="X",9,IF(RIGHT(LEFT(E11,6))=RIGHT(LEFT(C11,6)),1,0)))))) -> 0 | M11: =IF(E11="","",IF(RIGHT(LEFT(E11,7))=".","B",IF(RIGHT(LEFT(E11,7))="*","M",IF(RIGHT(LEFT(C11,7))="Z",8,IF(RIGHT(LEFT(C11,7))="X",9,IF(RIGHT(LEFT(E11,7))=RIGHT(LEFT(C11,7)),1,0)))))) -> 1 | N11: =IF(E11="","",IF(RIGHT(LEFT(E11,8))=".","B",IF(RIGHT(LEFT(E11,8))="*","M",IF(RIGHT(LEFT(C11,8))="Z",8,IF(RIGHT(LEFT(C11,8))="X",9,IF(RIGHT(LEFT(E11,8))=RIGHT(LEFT(C11,8)),1,0)))))) -> 0 | O11: =IF(F11="","",IF(RIGHT(LEFT(F11,1))=".","B",IF(RIGHT(LEFT(F11,1))="*","M",IF(RIGHT(LEFT(D11,1))="Z",8,IF(RIGHT(LEFT(D11,1))="X",9,IF(RIGHT(LEFT(F11,1))=RIGHT(LEFT(D11,1)),1,0)))))) -> 0 | P11: =IF(F11="","",IF(RIGHT(LEFT(F11,2))=".","B",IF(RIGHT(LEFT(F11,2))="*","M",IF(RIGHT(LEFT(D11,2))="Z",8,IF(RIGHT(LEFT(D11,2))="X",9,IF(RIGHT(LEFT(F11,2))=RIGHT(LEFT(D11,2)),1,0)))))) -> 9 | Q11: =IF(F11="","",IF(RIGHT(LEFT(F11,3))=".","B",IF(RIGHT(LEFT(F11,3))="*","M",IF(RIGHT(LEFT(D11,3))="Z",8,IF(RIGHT(LEFT(D11,3))="X",9,IF(RIGHT(LEFT(F11,3))=RIGHT(LEFT(D11,3)),1,0)))))) -> 0 | R11: =IF(F11="","",IF(RIGHT(LEFT(F11,4))=".","B",IF(RIGHT(LEFT(F11,4))="*","M",IF(RIGHT(LEFT(D11,4))="Z",8,IF(RIGHT(LEFT(D11,4))="X",9,IF(RIGHT(LEFT(F11,4))=RIGHT(LEFT(D11,4)),1,0)))))) -> 1 | S11: =IF(F11="","",IF(RIGHT(LEFT(F11,5))=".","B",IF(RIGHT(LEFT(F11,5))="*","M",IF(RIGHT(LEFT(D11,5))="Z",8,IF(RIGHT(LEFT(D11,5))="X",9,IF(RIGHT(LEFT(F11,5))=RIGHT(LEFT(D11,5)),1,0)))))) -> 9 | T11: =IF(F11="","",IF(RIGHT(LEFT(F11,6))=".","B",IF(RIGHT(LEFT(F11,6))="*","M",IF(RIGHT(LEFT(D11,6))="Z",8,IF(RIGHT(LEFT(D11,6))="X",9,IF(RIGHT(LEFT(F11,6))=RIGHT(LEFT(D11,6)),1,0)))))) -> 0 | U11: =IF(F11="","",IF(RIGHT(LEFT(F11,7))=".","B",IF(RIGHT(LEFT(F11,7))="*","M",IF(RIGHT(LEFT(D11,7))="Z",8,IF(RIGHT(LEFT(D11,7))="X",9,IF(RIGHT(LEFT(F11,7))=RIGHT(LEFT(D11,7)),1,0)))))) -> 0 | V11: =IF(F11="","",IF(RIGHT(LEFT(F11,8))=".","B",IF(RIGHT(LEFT(F11,8))="*","M",IF(RIGHT(LEFT(D11,8))="Z",8,IF(RIGHT(LEFT(D11,8))="X",9,IF(RIGHT(LEFT(F11,8))=RIGHT(LEFT(D11,8)),1,0)))))) -> 9 | W11: =IF(F11="","",IF(RIGHT(LEFT(F11,9))=".","B",IF(RIGHT(LEFT(F11,9))="*","M",IF(RIGHT(LEFT(D11,9))="Z",8,IF(RIGHT(LEFT(D11,9))="X",9,IF(RIGHT(LEFT(F11,9))=RIGHT(LEFT(D11,9)),1,0)))))) -> 1 | X11: =IF(F11="","",IF(RIGHT(LEFT(F11,10))=".","B",IF(RIGHT(LEFT(F11,10))="*","M",IF(RIGHT(LEFT(D11,10))="Z",8,IF(RIGHT(LEFT(D11,10))="X",9,IF(RIGHT(LEFT(F11,10))=RIGHT(LEFT(D11,10)),1,0)))))) -> 0 | Y11: =IF(F11="","",IF(RIGHT(LEFT(F11,11))=".","B",IF(RIGHT(LEFT(F11,11))="*","M",IF(RIGHT(LEFT(D11,11))="Z",8,IF(RIGHT(LEFT(D11,11))="X",9,IF(RIGHT(LEFT(F11,11))=RIGHT(LEFT(D11,11)),1,0)))))) -> 0 | Z11: =IF(F11="","",IF(RIGHT(LEFT(F11,12))=".","B",IF(RIGHT(LEFT(F11,12))="*","M",IF(RIGHT(LEFT(D11,12))="Z",8,IF(RIGHT(LEFT(D11,12))="X",9,IF(RIGHT(LEFT(F11,12))=RIGHT(LEFT(D11,12)),1,0)))))) -> 1 | AA11: =IF(F11="","",IF(RIGHT(LEFT(F11,13))=".","B",IF(RIGHT(LEFT(F11,13))="*","M",IF(RIGHT(LEFT(D11,13))="Z",8,IF(RIGHT(LEFT(D11,13))="X",9,IF(RIGHT(LEFT(F11,13))=RIGHT(LEFT(D11,13)),1,0)))))) -> 1 | AB11: =IF(F11="","",IF(RIGHT(LEFT(F11,14))=".","B",IF(RIGHT(LEFT(F11,14))="*","M",IF(RIGHT(LEFT(D11,14))="Z",8,IF(RIGHT(LEFT(D11,14))="X",9,IF(RIGHT(LEFT(F11,14))=RIGHT(LEFT(D11,14)),1,0)))))) -> 1 | AC11: =IF(F11="","",IF(RIGHT(LEFT(F11,15))=".","B",IF(RIGHT(LEFT(F11,15))="*","M",IF(RIGHT(LEFT(D11,15))="Z",8,IF(RIGHT(LEFT(D11,15))="X",9,IF(RIGHT(LEFT(F11,15))=RIGHT(LEFT(D11,15)),1,0)))))) -> 0 | AD11: =IF(F11="","",IF(RIGHT(LEFT(F11,16))=".","B",IF(RIGHT(LEFT(F11,16))="*","M",IF(RIGHT(LEFT(D11,16))="Z",8,IF(RIGHT(LEFT(D11,16))="X",9,IF(RIGHT(LEFT(F11,16))=RIGHT(LEFT(D11,16)),1,0)))))) -> 1 | AE11: =IF(F11="","",IF(RIGHT(LEFT(F11,17))=".","B",IF(RIGHT(LEFT(F11,17))="*","M",IF(RIGHT(LEFT(D11,17))="Z",8,IF(RIGHT(LEFT(D11,17))="X",9,IF(RIGHT(LEFT(F11,17))=RIGHT(LEFT(D11,17)),1,0)))))) -> 0 | AF11: =IF(F11="","",IF(RIGHT(LEFT(F11,18))=".","B",IF(RIGHT(LEFT(F11,18))="*","M",IF(RIGHT(LEFT(D11,18))="Z",8,IF(RIGHT(LEFT(D11,18))="X",9,IF(RIGHT(LEFT(F11,18))=RIGHT(LEFT(D11,18)),1,0)))))) -> 1 | AG11: =IF(F11="","",IF(RIGHT(LEFT(F11,19))=".","B",IF(RIGHT(LEFT(F11,19))="*","M",IF(RIGHT(LEFT(D11,19))="Z",8,IF(RIGHT(LEFT(D11,19))="X",9,IF(RIGHT(LEFT(F11,19))=RIGHT(LEFT(D11,19)),1,0)))))) -> 1 | AH11: =IF(F11="","",IF(RIGHT(LEFT(F11,20))=".","B",IF(RIGHT(LEFT(F11,20))="*","M",IF(RIGHT(LEFT(D11,20))="Z",8,IF(RIGHT(LEFT(D11,20))="X",9,IF(RIGHT(LEFT(F11,20))=RIGHT(LEFT(D11,20)),1,0)))))) -> 0 | AI11: =IF(F11="","",IF(RIGHT(LEFT(F11,21))=".","B",IF(RIGHT(LEFT(F11,21))="*","M",IF(RIGHT(LEFT(D11,21))="Z",8,IF(RIGHT(LEFT(D11,21))="X",9,IF(RIGHT(LEFT(F11,21))=RIGHT(LEFT(D11,21)),1,0)))))) -> 0 | AJ11: =IF(F11="","",IF(RIGHT(LEFT(F11,22))=".","B",IF(RIGHT(LEFT(F11,22))="*","M",IF(RIGHT(LEFT(D11,22))="Z",8,IF(RIGHT(LEFT(D11,22))="X",9,IF(RIGHT(LEFT(F11,22))=RIGHT(LEFT(D11,22)),1,0)))))) -> 0 | AK11: =IF(F11="","",IF(RIGHT(LEFT(F11,23))=".","B",IF(RIGHT(LEFT(F11,23))="*","M",IF(RIGHT(LEFT(D11,23))="Z",8,IF(RIGHT(LEFT(D11,23))="X",9,IF(RIGHT(LEFT(F11,23))=RIGHT(LEFT(D11,23)),1,0)))))) -> 0 | AL11: =IF(F11="","",IF(RIGHT(LEFT(F11,24))=".","B",IF(RIGHT(LEFT(F11,24))="*","M",IF(RIGHT(LEFT(D11,24))="Z",8,IF(RIGHT(LEFT(D11,24))="X",9,IF(RIGHT(LEFT(F11,24))=RIGHT(LEFT(D11,24)),1,0)))))) -> 9 | AM11: =IF(F11="","",IF(RIGHT(LEFT(F11,25))=".","B",IF(RIGHT(LEFT(F11,25))="*","M",IF(RIGHT(LEFT(D11,25))="Z",8,IF(RIGHT(LEFT(D11,25))="X",9,IF(RIGHT(LEFT(F11,25))=RIGHT(LEFT(D11,25)),1,0)))))) -> 0 | AN11: =IF(F11="","",IF(RIGHT(LEFT(F11,26))=".","B",IF(RIGHT(LEFT(F11,26))="*","M",IF(RIGHT(LEFT(D11,26))="Z",8,IF(RIGHT(LEFT(D11,26))="X",9,IF(RIGHT(LEFT(F11,26))=RIGHT(LEFT(D11,26)),1,0)))))) -> 0 | AO11: =IF(F11="","",IF(RIGHT(LEFT(F11,27))=".","B",IF(RIGHT(LEFT(F11,27))="*","M",IF(RIGHT(LEFT(D11,27))="Z",8,IF(RIGHT(LEFT(D11,27))="X",9,IF(RIGHT(LEFT(F11,27))=RIGHT(LEFT(D11,27)),1,0)))))) -> 0
A12: 2019 | B12: 1181815 | C12: ZDCBCCDB | D12: ZDEBDAEBXDACZXCBXDCZABBEDXC | E12: BDCADEEE | F12: CCADDACBBAEBEDDADECCBACEADC | G12: =IF(E12="","",IF(RIGHT(LEFT(E12,1))=".","B",IF(RIGHT(LEFT(E12,1))="*","M",IF(RIGHT(LEFT(C12,1))="Z",8,IF(RIGHT(LEFT(C12,1))="X",9,IF(RIGHT(LEFT(E12,1))=RIGHT(LEFT(C12,1)),1,0)))))) -> 8 | H12: =IF(E12="","",IF(RIGHT(LEFT(E12,2))=".","B",IF(RIGHT(LEFT(E12,2))="*","M",IF(RIGHT(LEFT(C12,2))="Z",8,IF(RIGHT(LEFT(C12,2))="X",9,IF(RIGHT(LEFT(E12,2))=RIGHT(LEFT(C12,2)),1,0)))))) -> 1 | I12: =IF(E12="","",IF(RIGHT(LEFT(E12,3))=".","B",IF(RIGHT(LEFT(E12,3))="*","M",IF(RIGHT(LEFT(C12,3))="Z",8,IF(RIGHT(LEFT(C12,3))="X",9,IF(RIGHT(LEFT(E12,3))=RIGHT(LEFT(C12,3)),1,0)))))) -> 1 | J12: =IF(E12="","",IF(RIGHT(LEFT(E12,4))=".","B",IF(RIGHT(LEFT(E12,4))="*","M",IF(RIGHT(LEFT(C12,4))="Z",8,IF(RIGHT(LEFT(C12,4))="X",9,IF(RIGHT(LEFT(E12,4))=RIGHT(LEFT(C12,4)),1,0)))))) -> 0 | K12: =IF(E12="","",IF(RIGHT(LEFT(E12,5))=".","B",IF(RIGHT(LEFT(E12,5))="*","M",IF(RIGHT(LEFT(C12,5))="Z",8,IF(RIGHT(LEFT(C12,5))="X",9,IF(RIGHT(LEFT(E12,5))=RIGHT(LEFT(C12,5)),1,0)))))) -> 0 | L12: =IF(E12="","",IF(RIGHT(LEFT(E12,6))=".","B",IF(RIGHT(LEFT(E12,6))="*","M",IF(RIGHT(LEFT(C12,6))="Z",8,IF(RIGHT(LEFT(C12,6))="X",9,IF(RIGHT(LEFT(E12,6))=RIGHT(LEFT(C12,6)),1,0)))))) -> 0 | M12: =IF(E12="","",IF(RIGHT(LEFT(E12,7))=".","B",IF(RIGHT(LEFT(E12,7))="*","M",IF(RIGHT(LEFT(C12,7))="Z",8,IF(RIGHT(LEFT(C12,7))="X",9,IF(RIGHT(LEFT(E12,7))=RIGHT(LEFT(C12,7)),1,0)))))) -> 0 | N12: =IF(E12="","",IF(RIGHT(LEFT(E12,8))=".","B",IF(RIGHT(LEFT(E12,8))="*","M",IF(RIGHT(LEFT(C12,8))="Z",8,IF(RIGHT(LEFT(C12,8))="X",9,IF(RIGHT(LEFT(E12,8))=RIGHT(LEFT(C12,8)),1,0)))))) -> 0 | O12: =IF(F12="","",IF(RIGHT(LEFT(F12,1))=".","B",IF(RIGHT(LEFT(F12,1))="*","M",IF(RIGHT(LEFT(D12,1))="Z",8,IF(RIGHT(LEFT(D12,1))="X",9,IF(RIGHT(LEFT(F12,1))=RIGHT(LEFT(D12,1)),1,0)))))) -> 8 | P12: =IF(F12="","",IF(RIGHT(LEFT(F12,2))=".","B",IF(RIGHT(LEFT(F12,2))="*","M",IF(RIGHT(LEFT(D12,2))="Z",8,IF(RIGHT(LEFT(D12,2))="X",9,IF(RIGHT(LEFT(F12,2))=RIGHT(LEFT(D12,2)),1,0)))))) -> 0 | Q12: =IF(F12="","",IF(RIGHT(LEFT(F12,3))=".","B",IF(RIGHT(LEFT(F12,3))="*","M",IF(RIGHT(LEFT(D12,3))="Z",8,IF(RIGHT(LEFT(D12,3))="X",9,IF(RIGHT(LEFT(F12,3))=RIGHT(LEFT(D12,3)),1,0)))))) -> 0 | R12: =IF(F12="","",IF(RIGHT(LEFT(F12,4))=".","B",IF(RIGHT(LEFT(F12,4))="*","M",IF(RIGHT(LEFT(D12,4))="Z",8,IF(RIGHT(LEFT(D12,4))="X",9,IF(RIGHT(LEFT(F12,4))=RIGHT(LEFT(D12,4)),1,0)))))) -> 0 | S12: =IF(F12="","",IF(RIGHT(LEFT(F12,5))=".","B",IF(RIGHT(LEFT(F12,5))="*","M",IF(RIGHT(LEFT(D12,5))="Z",8,IF(RIGHT(LEFT(D12,5))="X",9,IF(RIGHT(LEFT(F12,5))=RIGHT(LEFT(D12,5)),1,0)))))) -> 1 | T12: =IF(F12="","",IF(RIGHT(LEFT(F12,6))=".","B",IF(RIGHT(LEFT(F12,6))="*","M",IF(RIGHT(LEFT(D12,6))="Z",8,IF(RIGHT(LEFT(D12,6))="X",9,IF(RIGHT(LEFT(F12,6))=RIGHT(LEFT(D12,6)),1,0)))))) -> 1 | U12: =IF(F12="","",IF(RIGHT(LEFT(F12,7))=".","B",IF(RIGHT(LEFT(F12,7))="*","M",IF(RIGHT(LEFT(D12,7))="Z",8,IF(RIGHT(LEFT(D12,7))="X",9,IF(RIGHT(LEFT(F12,7))=RIGHT(LEFT(D12,7)),1,0)))))) -> 0 | V12: =IF(F12="","",IF(RIGHT(LEFT(F12,8))=".","B",IF(RIGHT(LEFT(F12,8))="*","M",IF(RIGHT(LEFT(D12,8))="Z",8,IF(RIGHT(LEFT(D12,8))="X",9,IF(RIGHT(LEFT(F12,8))=RIGHT(LEFT(D12,8)),1,0)))))) -> 1 | W12: =IF(F12="","",IF(RIGHT(LEFT(F12,9))=".","B",IF(RIGHT(LEFT(F12,9))="*","M",IF(RIGHT(LEFT(D12,9))="Z",8,IF(RIGHT(LEFT(D12,9))="X",9,IF(RIGHT(LEFT(F12,9))=RIGHT(LEFT(D12,9)),1,0)))))) -> 9 | X12: =IF(F12="","",IF(RIGHT(LEFT(F12,10))=".","B",IF(RIGHT(LEFT(F12,10))="*","M",IF(RIGHT(LEFT(D12,10))="Z",8,IF(RIGHT(LEFT(D12,10))="X",9,IF(RIGHT(LEFT(F12,10))=RIGHT(LEFT(D12,10)),1,0)))))) -> 0 | Y12: =IF(F12="","",IF(RIGHT(LEFT(F12,11))=".","B",IF(RIGHT(LEFT(F12,11))="*","M",IF(RIGHT(LEFT(D12,11))="Z",8,IF(RIGHT(LEFT(D12,11))="X",9,IF(RIGHT(LEFT(F12,11))=RIGHT(LEFT(D12,11)),1,0)))))) -> 0 | Z12: =IF(F12="","",IF(RIGHT(LEFT(F12,12))=".","B",IF(RIGHT(LEFT(F12,12))="*","M",IF(RIGHT(LEFT(D12,12))="Z",8,IF(RIGHT(LEFT(D12,12))="X",9,IF(RIGHT(LEFT(F12,12))=RIGHT(LEFT(D12,12)),1,0)))))) -> 0 | AA12: =IF(F12="","",IF(RIGHT(LEFT(F12,13))=".","B",IF(RIGHT(LEFT(F12,13))="*","M",IF(RIGHT(LEFT(D12,13))="Z",8,IF(RIGHT(LEFT(D12,13))="X",9,IF(RIGHT(LEFT(F12,13))=RIGHT(LEFT(D12,13)),1,0)))))) -> 8 | AB12: =IF(F12="","",IF(RIGHT(LEFT(F12,14))=".","B",IF(RIGHT(LEFT(F12,14))="*","M",IF(RIGHT(LEFT(D12,14))="Z",8,IF(RIGHT(LEFT(D12,14))="X",9,IF(RIGHT(LEFT(F12,14))=RIGHT(LEFT(D12,14)),1,0)))))) -> 9 | AC12: =IF(F12="","",IF(RIGHT(LEFT(F12,15))=".","B",IF(RIGHT(LEFT(F12,15))="*","M",IF(RIGHT(LEFT(D12,15))="Z",8,IF(RIGHT(LEFT(D12,15))="X",9,IF(RIGHT(LEFT(F12,15))=RIGHT(LEFT(D12,15)),1,0)))))) -> 0 | AD12: =IF(F12="","",IF(RIGHT(LEFT(F12,16))=".","B",IF(RIGHT(LEFT(F12,16))="*","M",IF(RIGHT(LEFT(D12,16))="Z",8,IF(RIGHT(LEFT(D12,16))="X",9,IF(RIGHT(LEFT(F12,16))=RIGHT(LEFT(D12,16)),1,0)))))) -> 0 | AE12: =IF(F12="","",IF(RIGHT(LEFT(F12,17))=".","B",IF(RIGHT(LEFT(F12,17))="*","M",IF(RIGHT(LEFT(D12,17))="Z",8,IF(RIGHT(LEFT(D12,17))="X",9,IF(RIGHT(LEFT(F12,17))=RIGHT(LEFT(D12,17)),1,0)))))) -> 9 | AF12: =IF(F12="","",IF(RIGHT(LEFT(F12,18))=".","B",IF(RIGHT(LEFT(F12,18))="*","M",IF(RIGHT(LEFT(D12,18))="Z",8,IF(RIGHT(LEFT(D12,18))="X",9,IF(RIGHT(LEFT(F12,18))=RIGHT(LEFT(D12,18)),1,0)))))) -> 0 | AG12: =IF(F12="","",IF(RIGHT(LEFT(F12,19))=".","B",IF(RIGHT(LEFT(F12,19))="*","M",IF(RIGHT(LEFT(D12,19))="Z",8,IF(RIGHT(LEFT(D12,19))="X",9,IF(RIGHT(LEFT(F12,19))=RIGHT(LEFT(D12,19)),1,0)))))) -> 1 | AH12: =IF(F12="","",IF(RIGHT(LEFT(F12,20))=".","B",IF(RIGHT(LEFT(F12,20))="*","M",IF(RIGHT(LEFT(D12,20))="Z",8,IF(RIGHT(LEFT(D12,20))="X",9,IF(RIGHT(LEFT(F12,20))=RIGHT(LEFT(D12,20)),1,0)))))) -> 8 | AI12: =IF(F12="","",IF(RIGHT(LEFT(F12,21))=".","B",IF(RIGHT(LEFT(F12,21))="*","M",IF(RIGHT(LEFT(D12,21))="Z",8,IF(RIGHT(LEFT(D12,21))="X",9,IF(RIGHT(LEFT(F12,21))=RIGHT(LEFT(D12,21)),1,0)))))) -> 0 | AJ12: =IF(F12="","",IF(RIGHT(LEFT(F12,22))=".","B",IF(RIGHT(LEFT(F12,22))="*","M",IF(RIGHT(LEFT(D12,22))="Z",8,IF(RIGHT(LEFT(D12,22))="X",9,IF(RIGHT(LEFT(F12,22))=RIGHT(LEFT(D12,22)),1,0)))))) -> 0 | AK12: =IF(F12="","",IF(RIGHT(LEFT(F12,23))=".","B",IF(RIGHT(LEFT(F12,23))="*","M",IF(RIGHT(LEFT(D12,23))="Z",8,IF(RIGHT(LEFT(D12,23))="X",9,IF(RIGHT(LEFT(F12,23))=RIGHT(LEFT(D12,23)),1,0)))))) -> 0 | AL12: =IF(F12="","",IF(RIGHT(LEFT(F12,24))=".","B",IF(RIGHT(LEFT(F12,24))="*","M",IF(RIGHT(LEFT(D12,24))="Z",8,IF(RIGHT(LEFT(D12,24))="X",9,IF(RIGHT(LEFT(F12,24))=RIGHT(LEFT(D12,24)),1,0)))))) -> 1 | AM12: =IF(F12="","",IF(RIGHT(LEFT(F12,25))=".","B",IF(RIGHT(LEFT(F12,25))="*","M",IF(RIGHT(LEFT(D12,25))="Z",8,IF(RIGHT(LEFT(D12,25))="X",9,IF(RIGHT(LEFT(F12,25))=RIGHT(LEFT(D12,25)),1,0)))))) -> 0 | AN12: =IF(F12="","",IF(RIGHT(LEFT(F12,26))=".","B",IF(RIGHT(LEFT(F12,26))="*","M",IF(RIGHT(LEFT(D12,26))="Z",8,IF(RIGHT(LEFT(D12,26))="X",9,IF(RIGHT(LEFT(F12,26))=RIGHT(LEFT(D12,26)),1,0)))))) -> 9 | AO12: =IF(F12="","",IF(RIGHT(LEFT(F12,27))=".","B",IF(RIGHT(LEFT(F12,27))="*","M",IF(RIGHT(LEFT(D12,27))="Z",8,IF(RIGHT(LEFT(D12,27))="X",9,IF(RIGHT(LEFT(F12,27))=RIGHT(LEFT(D12,27)),1,0)))))) -> 1
A13: 2019 | B13: 123569 | C13: ZDCBCCDB | D13: ZDEBDAEBXDACZXCBXDCZABBEDXC | E13: ADBCEABB | F13: EBEDEDAACDABCDCBDBECACCBABA | G13: =IF(E13="","",IF(RIGHT(LEFT(E13,1))=".","B",IF(RIGHT(LEFT(E13,1))="*","M",IF(RIGHT(LEFT(C13,1))="Z",8,IF(RIGHT(LEFT(C13,1))="X",9,IF(RIGHT(LEFT(E13,1))=RIGHT(LEFT(C13,1)),1,0)))))) -> 8 | H13: =IF(E13="","",IF(RIGHT(LEFT(E13,2))=".","B",IF(RIGHT(LEFT(E13,2))="*","M",IF(RIGHT(LEFT(C13,2))="Z",8,IF(RIGHT(LEFT(C13,2))="X",9,IF(RIGHT(LEFT(E13,2))=RIGHT(LEFT(C13,2)),1,0)))))) -> 1 | I13: =IF(E13="","",IF(RIGHT(LEFT(E13,3))=".","B",IF(RIGHT(LEFT(E13,3))="*","M",IF(RIGHT(LEFT(C13,3))="Z",8,IF(RIGHT(LEFT(C13,3))="X",9,IF(RIGHT(LEFT(E13,3))=RIGHT(LEFT(C13,3)),1,0)))))) -> 0 | J13: =IF(E13="","",IF(RIGHT(LEFT(E13,4))=".","B",IF(RIGHT(LEFT(E13,4))="*","M",IF(RIGHT(LEFT(C13,4))="Z",8,IF(RIGHT(LEFT(C13,4))="X",9,IF(RIGHT(LEFT(E13,4))=RIGHT(LEFT(C13,4)),1,0)))))) -> 0 | K13: =IF(E13="","",IF(RIGHT(LEFT(E13,5))=".","B",IF(RIGHT(LEFT(E13,5))="*","M",IF(RIGHT(LEFT(C13,5))="Z",8,IF(RIGHT(LEFT(C13,5))="X",9,IF(RIGHT(LEFT(E13,5))=RIGHT(LEFT(C13,5)),1,0)))))) -> 0 | L13: =IF(E13="","",IF(RIGHT(LEFT(E13,6))=".","B",IF(RIGHT(LEFT(E13,6))="*","M",IF(RIGHT(LEFT(C13,6))="Z",8,IF(RIGHT(LEFT(C13,6))="X",9,IF(RIGHT(LEFT(E13,6))=RIGHT(LEFT(C13,6)),1,0)))))) -> 0 | M13: =IF(E13="","",IF(RIGHT(LEFT(E13,7))=".","B",IF(RIGHT(LEFT(E13,7))="*","M",IF(RIGHT(LEFT(C13,7))="Z",8,IF(RIGHT(LEFT(C13,7))="X",9,IF(RIGHT(LEFT(E13,7))=RIGHT(LEFT(C13,7)),1,0)))))) -> 0 | N13: =IF(E13="","",IF(RIGHT(LEFT(E13,8))=".","B",IF(RIGHT(LEFT(E13,8))="*","M",IF(RIGHT(LEFT(C13,8))="Z",8,IF(RIGHT(LEFT(C13,8))="X",9,IF(RIGHT(LEFT(E13,8))=RIGHT(LEFT(C13,8)),1,0)))))) -> 1 | O13: =IF(F13="","",IF(RIGHT(LEFT(F13,1))=".","B",IF(RIGHT(LEFT(F13,1))="*","M",IF(RIGHT(LEFT(D13,1))="Z",8,IF(RIGHT(LEFT(D13,1))="X",9,IF(RIGHT(LEFT(F13,1))=RIGHT(LEFT(D13,1)),1,0)))))) -> 8 | P13: =IF(F13="","",IF(RIGHT(LEFT(F13,2))=".","B",IF(RIGHT(LEFT(F13,2))="*","M",IF(RIGHT(LEFT(D13,2))="Z",8,IF(RIGHT(LEFT(D13,2))="X",9,IF(RIGHT(LEFT(F13,2))=RIGHT(LEFT(D13,2)),1,0)))))) -> 0 | Q13: =IF(F13="","",IF(RIGHT(LEFT(F13,3))=".","B",IF(RIGHT(LEFT(F13,3))="*","M",IF(RIGHT(LEFT(D13,3))="Z",8,IF(RIGHT(LEFT(D13,3))="X",9,IF(RIGHT(LEFT(F13,3))=RIGHT(LEFT(D13,3)),1,0)))))) -> 1 | R13: =IF(F13="","",IF(RIGHT(LEFT(F13,4))=".","B",IF(RIGHT(LEFT(F13,4))="*","M",IF(RIGHT(LEFT(D13,4))="Z",8,IF(RIGHT(LEFT(D13,4))="X",9,IF(RIGHT(LEFT(F13,4))=RIGHT(LEFT(D13,4)),1,0)))))) -> 0 | S13: =IF(F13="","",IF(RIGHT(LEFT(F13,5))=".","B",IF(RIGHT(LEFT(F13,5))="*","M",IF(RIGHT(LEFT(D13,5))="Z",8,IF(RIGHT(LEFT(D13,5))="X",9,IF(RIGHT(LEFT(F13,5))=RIGHT(LEFT(D13,5)),1,0)))))) -> 0 | T13: =IF(F13="","",IF(RIGHT(LEFT(F13,6))=".","B",IF(RIGHT(LEFT(F13,6))="*","M",IF(RIGHT(LEFT(D13,6))="Z",8,IF(RIGHT(LEFT(D13,6))="X",9,IF(RIGHT(LEFT(F13,6))=RIGHT(LEFT(D13,6)),1,0)))))) -> 0 | U13: =IF(F13="","",IF(RIGHT(LEFT(F13,7))=".","B",IF(RIGHT(LEFT(F13,7))="*","M",IF(RIGHT(LEFT(D13,7))="Z",8,IF(RIGHT(LEFT(D13,7))="X",9,IF(RIGHT(LEFT(F13,7))=RIGHT(LEFT(D13,7)),1,0)))))) -> 0 | V13: =IF(F13="","",IF(RIGHT(LEFT(F13,8))=".","B",IF(RIGHT(LEFT(F13,8))="*","M",IF(RIGHT(LEFT(D13,8))="Z",8,IF(RIGHT(LEFT(D13,8))="X",9,IF(RIGHT(LEFT(F13,8))=RIGHT(LEFT(D13,8)),1,0)))))) -> 0 | W13: =IF(F13="","",IF(RIGHT(LEFT(F13,9))=".","B",IF(RIGHT(LEFT(F13,9))="*","M",IF(RIGHT(LEFT(D13,9))="Z",8,IF(RIGHT(LEFT(D13,9))="X",9,IF(RIGHT(LEFT(F13,9))=RIGHT(LEFT(D13,9)),1,0)))))) -> 9 | X13: =IF(F13="","",IF(RIGHT(LEFT(F13,10))=".","B",IF(RIGHT(LEFT(F13,10))="*","M",IF(RIGHT(LEFT(D13,10))="Z",8,IF(RIGHT(LEFT(D13,10))="X",9,IF(RIGHT(LEFT(F13,10))=RIGHT(LEFT(D13,10)),1,0)))))) -> 1 | Y13: =IF(F13="","",IF(RIGHT(LEFT(F13,11))=".","B",IF(RIGHT(LEFT(F13,11))="*","M",IF(RIGHT(LEFT(D13,11))="Z",8,IF(RIGHT(LEFT(D13,11))="X",9,IF(RIGHT(LEFT(F13,11))=RIGHT(LEFT(D13,11)),1,0)))))) -> 1 | Z13: =IF(F13="","",IF(RIGHT(LEFT(F13,12))=".","B",IF(RIGHT(LEFT(F13,12))="*","M",IF(RIGHT(LEFT(D13,12))="Z",8,IF(RIGHT(LEFT(D13,12))="X",9,IF(RIGHT(LEFT(F13,12))=RIGHT(LEFT(D13,12)),1,0)))))) -> 0 | AA13: =IF(F13="","",IF(RIGHT(LEFT(F13,13))=".","B",IF(RIGHT(LEFT(F13,13))="*","M",IF(RIGHT(LEFT(D13,13))="Z",8,IF(RIGHT(LEFT(D13,13))="X",9,IF(RIGHT(LEFT(F13,13))=RIGHT(LEFT(D13,13)),1,0)))))) -> 8 | AB13: =IF(F13="","",IF(RIGHT(LEFT(F13,14))=".","B",IF(RIGHT(LEFT(F13,14))="*","M",IF(RIGHT(LEFT(D13,14))="Z",8,IF(RIGHT(LEFT(D13,14))="X",9,IF(RIGHT(LEFT(F13,14))=RIGHT(LEFT(D13,14)),1,0)))))) -> 9 | AC13: =IF(F13="","",IF(RIGHT(LEFT(F13,15))=".","B",IF(RIGHT(LEFT(F13,15))="*","M",IF(RIGHT(LEFT(D13,15))="Z",8,IF(RIGHT(LEFT(D13,15))="X",9,IF(RIGHT(LEFT(F13,15))=RIGHT(LEFT(D13,15)),1,0)))))) -> 1 | AD13: =IF(F13="","",IF(RIGHT(LEFT(F13,16))=".","B",IF(RIGHT(LEFT(F13,16))="*","M",IF(RIGHT(LEFT(D13,16))="Z",8,IF(RIGHT(LEFT(D13,16))="X",9,IF(RIGHT(LEFT(F13,16))=RIGHT(LEFT(D13,16)),1,0)))))) -> 1 | AE13: =IF(F13="","",IF(RIGHT(LEFT(F13,17))=".","B",IF(RIGHT(LEFT(F13,17))="*","M",IF(RIGHT(LEFT(D13,17))="Z",8,IF(RIGHT(LEFT(D13,17))="X",9,IF(RIGHT(LEFT(F13,17))=RIGHT(LEFT(D13,17)),1,0)))))) -> 9 | AF13: =IF(F13="","",IF(RIGHT(LEFT(F13,18))=".","B",IF(RIGHT(LEFT(F13,18))="*","M",IF(RIGHT(LEFT(D13,18))="Z",8,IF(RIGHT(LEFT(D13,18))="X",9,IF(RIGHT(LEFT(F13,18))=RIGHT(LEFT(D13,18)),1,0)))))) -> 0 | AG13: =IF(F13="","",IF(RIGHT(LEFT(F13,19))=".","B",IF(RIGHT(LEFT(F13,19))="*","M",IF(RIGHT(LEFT(D13,19))="Z",8,IF(RIGHT(LEFT(D13,19))="X",9,IF(RIGHT(LEFT(F13,19))=RIGHT(LEFT(D13,19)),1,0)))))) -> 0 | AH13: =IF(F13="","",IF(RIGHT(LEFT(F13,20))=".","B",IF(RIGHT(LEFT(F13,20))="*","M",IF(RIGHT(LEFT(D13,20))="Z",8,IF(RIGHT(LEFT(D13,20))="X",9,IF(RIGHT(LEFT(F13,20))=RIGHT(LEFT(D13,20)),1,0)))))) -> 8 | AI13: =IF(F13="","",IF(RIGHT(LEFT(F13,21))=".","B",IF(RIGHT(LEFT(F13,21))="*","M",IF(RIGHT(LEFT(D13,21))="Z",8,IF(RIGHT(LEFT(D13,21))="X",9,IF(RIGHT(LEFT(F13,21))=RIGHT(LEFT(D13,21)),1,0)))))) -> 1 | AJ13: =IF(F13="","",IF(RIGHT(LEFT(F13,22))=".","B",IF(RIGHT(LEFT(F13,22))="*","M",IF(RIGHT(LEFT(D13,22))="Z",8,IF(RIGHT(LEFT(D13,22))="X",9,IF(RIGHT(LEFT(F13,22))=RIGHT(LEFT(D13,22)),1,0)))))) -> 0 | AK13: =IF(F13="","",IF(RIGHT(LEFT(F13,23))=".","B",IF(RIGHT(LEFT(F13,23))="*","M",IF(RIGHT(LEFT(D13,23))="Z",8,IF(RIGHT(LEFT(D13,23))="X",9,IF(RIGHT(LEFT(F13,23))=RIGHT(LEFT(D13,23)),1,0)))))) -> 0 | AL13: =IF(F13="","",IF(RIGHT(LEFT(F13,24))=".","B",IF(RIGHT(LEFT(F13,24))="*","M",IF(RIGHT(LEFT(D13,24))="Z",8,IF(RIGHT(LEFT(D13,24))="X",9,IF(RIGHT(LEFT(F13,24))=RIGHT(LEFT(D13,24)),1,0)))))) -> 0 | AM13: =IF(F13="","",IF(RIGHT(LEFT(F13,25))=".","B",IF(RIGHT(LEFT(F13,25))="*","M",IF(RIGHT(LEFT(D13,25))="Z",8,IF(RIGHT(LEFT(D13,25))="X",9,IF(RIGHT(LEFT(F13,25))=RIGHT(LEFT(D13,25)),1,0)))))) -> 0 | AN13: =IF(F13="","",IF(RIGHT(LEFT(F13,26))=".","B",IF(RIGHT(LEFT(F13,26))="*","M",IF(RIGHT(LEFT(D13,26))="Z",8,IF(RIGHT(LEFT(D13,26))="X",9,IF(RIGHT(LEFT(F13,26))=RIGHT(LEFT(D13,26)),1,0)))))) -> 9 | AO13: =IF(F13="","",IF(RIGHT(LEFT(F13,27))=".","B",IF(RIGHT(LEFT(F13,27))="*","M",IF(RIGHT(LEFT(D13,27))="Z",8,IF(RIGHT(LEFT(D13,27))="X",9,IF(RIGHT(LEFT(F13,27))=RIGHT(LEFT(D13,27)),1,0)))))) -> 0
... A334: 2019 | B334: 88399 | C334: ZDCBCCDB | D334: ZAXDBBAXDABEEZECZAEZBCXBZBC | E334: BDCBCCDB | F334: AACDBBADDABEEDBCBAEDBCABBBA | G334: =IF(E334="","",IF(RIGHT(LEFT(E334,1))=".","B",IF(RIGHT(LEFT(E334,1))="*","M",IF(RIGHT(LEFT(C334,1))="Z",8,IF(RIGHT(LEFT(C334,1))="X",9,IF(RIGHT(LEFT(E334,1))=RIGHT(LEFT(C334,1)),1,0)))))) -> 8 | H334: =IF(E334="","",IF(RIGHT(LEFT(E334,2))=".","B",IF(RIGHT(LEFT(E334,2))="*","M",IF(RIGHT(LEFT(C334,2))="Z",8,IF(RIGHT(LEFT(C334,2))="X",9,IF(RIGHT(LEFT(E334,2))=RIGHT(LEFT(C334,2)),1,0)))))) -> 1 | I334: =IF(E334="","",IF(RIGHT(LEFT(E334,3))=".","B",IF(RIGHT(LEFT(E334,3))="*","M",IF(RIGHT(LEFT(C334,3))="Z",8,IF(RIGHT(LEFT(C334,3))="X",9,IF(RIGHT(LEFT(E334,3))=RIGHT(LEFT(C334,3)),1,0)))))) -> 1 | J334: =IF(E334="","",IF(RIGHT(LEFT(E334,4))=".","B",IF(RIGHT(LEFT(E334,4))="*","M",IF(RIGHT(LEFT(C334,4))="Z",8,IF(RIGHT(LEFT(C334,4))="X",9,IF(RIGHT(LEFT(E334,4))=RIGHT(LEFT(C334,4)),1,0)))))) -> 1 | K334: =IF(E334="","",IF(RIGHT(LEFT(E334,5))=".","B",IF(RIGHT(LEFT(E334,5))="*","M",IF(RIGHT(LEFT(C334,5))="Z",8,IF(RIGHT(LEFT(C334,5))="X",9,IF(RIGHT(LEFT(E334,5))=RIGHT(LEFT(C334,5)),1,0)))))) -> 1 | L334: =IF(E334="","",IF(RIGHT(LEFT(E334,6))=".","B",IF(RIGHT(LEFT(E334,6))="*","M",IF(RIGHT(LEFT(C334,6))="Z",8,IF(RIGHT(LEFT(C334,6))="X",9,IF(RIGHT(LEFT(E334,6))=RIGHT(LEFT(C334,6)),1,0)))))) -> 1 | M334: =IF(E334="","",IF(RIGHT(LEFT(E334,7))=".","B",IF(RIGHT(LEFT(E334,7))="*","M",IF(RIGHT(LEFT(C334,7))="Z",8,IF(RIGHT(LEFT(C334,7))="X",9,IF(RIGHT(LEFT(E334,7))=RIGHT(LEFT(C334,7)),1,0)))))) -> 1 | N334: =IF(E334="","",IF(RIGHT(LEFT(E334,8))=".","B",IF(RIGHT(LEFT(E334,8))="*","M",IF(RIGHT(LEFT(C334,8))="Z",8,IF(RIGHT(LEFT(C334,8))="X",9,IF(RIGHT(LEFT(E334,8))=RIGHT(LEFT(C334,8)),1,0)))))) -> 1 | O334: =IF(F334="","",IF(RIGHT(LEFT(F334,1))=".","B",IF(RIGHT(LEFT(F334,1))="*","M",IF(RIGHT(LEFT(D334,1))="Z",8,IF(RIGHT(LEFT(D334,1))="X",9,IF(RIGHT(LEFT(F334,1))=RIGHT(LEFT(D334,1)),1,0)))))) -> 8 | P334: =IF(F334="","",IF(RIGHT(LEFT(F334,2))=".","B",IF(RIGHT(LEFT(F334,2))="*","M",IF(RIGHT(LEFT(D334,2))="Z",8,IF(RIGHT(LEFT(D334,2))="X",9,IF(RIGHT(LEFT(F334,2))=RIGHT(LEFT(D334,2)),1,0)))))) -> 1 | Q334: =IF(F334="","",IF(RIGHT(LEFT(F334,3))=".","B",IF(RIGHT(LEFT(F334,3))="*","M",IF(RIGHT(LEFT(D334,3))="Z",8,IF(RIGHT(LEFT(D334,3))="X",9,IF(RIGHT(LEFT(F334,3))=RIGHT(LEFT(D334,3)),1,0)))))) -> 9 | R334: =IF(F334="","",IF(RIGHT(LEFT(F334,4))=".","B",IF(RIGHT(LEFT(F334,4))="*","M",IF(RIGHT(LEFT(D334,4))="Z",8,IF(RIGHT(LEFT(D334,4))="X",9,IF(RIGHT(LEFT(F334,4))=RIGHT(LEFT(D334,4)),1,0)))))) -> 1 | S334: =IF(F334="","",IF(RIGHT(LEFT(F334,5))=".","B",IF(RIGHT(LEFT(F334,5))="*","M",IF(RIGHT(LEFT(D334,5))="Z",8,IF(RIGHT(LEFT(D334,5))="X",9,IF(RIGHT(LEFT(F334,5))=RIGHT(LEFT(D334,5)),1,0)))))) -> 1 | T334: =IF(F334="","",IF(RIGHT(LEFT(F334,6))=".","B",IF(RIGHT(LEFT(F334,6))="*","M",IF(RIGHT(LEFT(D334,6))="Z",8,IF(RIGHT(LEFT(D334,6))="X",9,IF(RIGHT(LEFT(F334,6))=RIGHT(LEFT(D334,6)),1,0)))))) -> 1 | U334: =IF(F334="","",IF(RIGHT(LEFT(F334,7))=".","B",IF(RIGHT(LEFT(F334,7))="*","M",IF(RIGHT(LEFT(D334,7))="Z",8,IF(RIGHT(LEFT(D334,7))="X",9,IF(RIGHT(LEFT(F334,7))=RIGHT(LEFT(D334,7)),1,0)))))) -> 1 | V334: =IF(F334="","",IF(RIGHT(LEFT(F334,8))=".","B",IF(RIGHT(LEFT(F334,8))="*","M",IF(RIGHT(LEFT(D334,8))="Z",8,IF(RIGHT(LEFT(D334,8))="X",9,IF(RIGHT(LEFT(F334,8))=RIGHT(LEFT(D334,8)),1,0)))))) -> 9 | W334: =IF(F334="","",IF(RIGHT(LEFT(F334,9))=".","B",IF(RIGHT(LEFT(F334,9))="*","M",IF(RIGHT(LEFT(D334,9))="Z",8,IF(RIGHT(LEFT(D334,9))="X",9,IF(RIGHT(LEFT(F334,9))=RIGHT(LEFT(D334,9)),1,0)))))) -> 1 | X334: =IF(F334="","",IF(RIGHT(LEFT(F334,10))=".","B",IF(RIGHT(LEFT(F334,10))="*","M",IF(RIGHT(LEFT(D334,10))="Z",8,IF(RIGHT(LEFT(D334,10))="X",9,IF(RIGHT(LEFT(F334,10))=RIGHT(LEFT(D334,10)),1,0)))))) -> 1 | Y334: =IF(F334="","",IF(RIGHT(LEFT(F334,11))=".","B",IF(RIGHT(LEFT(F334,11))="*","M",IF(RIGHT(LEFT(D334,11))="Z",8,IF(RIGHT(LEFT(D334,11))="X",9,IF(RIGHT(LEFT(F334,11))=RIGHT(LEFT(D334,11)),1,0)))))) -> 1 | Z334: =IF(F334="","",IF(RIGHT(LEFT(F334,12))=".","B",IF(RIGHT(LEFT(F334,12))="*","M",IF(RIGHT(LEFT(D334,12))="Z",8,IF(RIGHT(LEFT(D334,12))="X",9,IF(RIGHT(LEFT(F334,12))=RIGHT(LEFT(D334,12)),1,0)))))) -> 1 | AA334: =IF(F334="","",IF(RIGHT(LEFT(F334,13))=".","B",IF(RIGHT(LEFT(F334,13))="*","M",IF(RIGHT(LEFT(D334,13))="Z",8,IF(RIGHT(LEFT(D334,13))="X",9,IF(RIGHT(LEFT(F334,13))=RIGHT(LEFT(D334,13)),1,0)))))) -> 1 | AB334: =IF(F334="","",IF(RIGHT(LEFT(F334,14))=".","B",IF(RIGHT(LEFT(F334,14))="*","M",IF(RIGHT(LEFT(D334,14))="Z",8,IF(RIGHT(LEFT(D334,14))="X",9,IF(RIGHT(LEFT(F334,14))=RIGHT(LEFT(D334,14)),1,0)))))) -> 8 | AC334: =IF(F334="","",IF(RIGHT(LEFT(F334,15))=".","B",IF(RIGHT(LEFT(F334,15))="*","M",IF(RIGHT(LEFT(D334,15))="Z",8,IF(RIGHT(LEFT(D334,15))="X",9,IF(RIGHT(LEFT(F334,15))=RIGHT(LEFT(D334,15)),1,0)))))) -> 0 | AD334: =IF(F334="","",IF(RIGHT(LEFT(F334,16))=".","B",IF(RIGHT(LEFT(F334,16))="*","M",IF(RIGHT(LEFT(D334,16))="Z",8,IF(RIGHT(LEFT(D334,16))="X",9,IF(RIGHT(LEFT(F334,16))=RIGHT(LEFT(D334,16)),1,0)))))) -> 1 | AE334: =IF(F334="","",IF(RIGHT(LEFT(F334,17))=".","B",IF(RIGHT(LEFT(F334,17))="*","M",IF(RIGHT(LEFT(D334,17))="Z",8,IF(RIGHT(LEFT(D334,17))="X",9,IF(RIGHT(LEFT(F334,17))=RIGHT(LEFT(D334,17)),1,0)))))) -> 8 | AF334: =IF(F334="","",IF(RIGHT(LEFT(F334,18))=".","B",IF(RIGHT(LEFT(F334,18))="*","M",IF(RIGHT(LEFT(D334,18))="Z",8,IF(RIGHT(LEFT(D334,18))="X",9,IF(RIGHT(LEFT(F334,18))=RIGHT(LEFT(D334,18)),1,0)))))) -> 1 | AG334: =IF(F334="","",IF(RIGHT(LEFT(F334,19))=".","B",IF(RIGHT(LEFT(F334,19))="*","M",IF(RIGHT(LEFT(D334,19))="Z",8,IF(RIGHT(LEFT(D334,19))="X",9,IF(RIGHT(LEFT(F334,19))=RIGHT(LEFT(D334,19)),1,0)))))) -> 1 | AH334: =IF(F334="","",IF(RIGHT(LEFT(F334,20))=".","B",IF(RIGHT(LEFT(F334,20))="*","M",IF(RIGHT(LEFT(D334,20))="Z",8,IF(RIGHT(LEFT(D334,20))="X",9,IF(RIGHT(LEFT(F334,20))=RIGHT(LEFT(D334,20)),1,0)))))) -> 8 | AI334: =IF(F334="","",IF(RIGHT(LEFT(F334,21))=".","B",IF(RIGHT(LEFT(F334,21))="*","M",IF(RIGHT(LEFT(D334,21))="Z",8,IF(RIGHT(LEFT(D334,21))="X",9,IF(RIGHT(LEFT(F334,21))=RIGHT(LEFT(D334,21)),1,0)))))) -> 1 | AJ334: =IF(F334="","",IF(RIGHT(LEFT(F334,22))=".","B",IF(RIGHT(LEFT(F334,22))="*","M",IF(RIGHT(LEFT(D334,22))="Z",8,IF(RIGHT(LEFT(D334,22))="X",9,IF(RIGHT(LEFT(F334,22))=RIGHT(LEFT(D334,22)),1,0)))))) -> 1 | AK334: =IF(F334="","",IF(RIGHT(LEFT(F334,23))=".","B",IF(RIGHT(LEFT(F334,23))="*","M",IF(RIGHT(LEFT(D334,23))="Z",8,IF(RIGHT(LEFT(D334,23))="X",9,IF(RIGHT(LEFT(F334,23))=RIGHT(LEFT(D334,23)),1,0)))))) -> 9 | AL334: =IF(F334="","",IF(RIGHT(LEFT(F334,24))=".","B",IF(RIGHT(LEFT(F334,24))="*","M",IF(RIGHT(LEFT(D334,24))="Z",8,IF(RIGHT(LEFT(D334,24))="X",9,IF(RIGHT(LEFT(F334,24))=RIGHT(LEFT(D334,24)),1,0)))))) -> 1 | AM334: =IF(F334="","",IF(RIGHT(LEFT(F334,25))=".","B",IF(RIGHT(LEFT(F334,25))="*","M",IF(RIGHT(LEFT(D334,25))="Z",8,IF(RIGHT(LEFT(D334,25))="X",9,IF(RIGHT(LEFT(F334,25))=RIGHT(LEFT(D334,25)),1,0)))))) -> 8 | AN334: =IF(F334="","",IF(RIGHT(LEFT(F334,26))=".","B",IF(RIGHT(LEFT(F334,26))="*","M",IF(RIGHT(LEFT(D334,26))="Z",8,IF(RIGHT(LEFT(D334,26))="X",9,IF(RIGHT(LEFT(F334,26))=RIGHT(LEFT(D334,26)),1,0)))))) -> 1 | AO334: =IF(F334="","",IF(RIGHT(LEFT(F334,27))=".","B",IF(RIGHT(LEFT(F334,27))="*","M",IF(RIGHT(LEFT(D334,27))="Z",8,IF(RIGHT(LEFT(D334,27))="X",9,IF(RIGHT(LEFT(F334,27))=RIGHT(LEFT(D334,27)),1,0)))))) -> 0
A335: 2019 | B335: 88399 | C335: ZDCBCCDB | D335: ZAXDBBAXDABEEZECZAEZBCXBZBC | G335: =IF(E335="","",IF(RIGHT(LEFT(E335,1))=".","B",IF(RIGHT(LEFT(E335,1))="*","M",IF(RIGHT(LEFT(C335,1))="Z",8,IF(RIGHT(LEFT(C335,1))="X",9,IF(RIGHT(LEFT(E335,1))=RIGHT(LEFT(C335,1)),1,0)))))) | H335: =IF(E335="","",IF(RIGHT(LEFT(E335,2))=".","B",IF(RIGHT(LEFT(E335,2))="*","M",IF(RIGHT(LEFT(C335,2))="Z",8,IF(RIGHT(LEFT(C335,2))="X",9,IF(RIGHT(LEFT(E335,2))=RIGHT(LEFT(C335,2)),1,0)))))) | I335: =IF(E335="","",IF(RIGHT(LEFT(E335,3))=".","B",IF(RIGHT(LEFT(E335,3))="*","M",IF(RIGHT(LEFT(C335,3))="Z",8,IF(RIGHT(LEFT(C335,3))="X",9,IF(RIGHT(LEFT(E335,3))=RIGHT(LEFT(C335,3)),1,0)))))) | J335: =IF(E335="","",IF(RIGHT(LEFT(E335,4))=".","B",IF(RIGHT(LEFT(E335,4))="*","M",IF(RIGHT(LEFT(C335,4))="Z",8,IF(RIGHT(LEFT(C335,4))="X",9,IF(RIGHT(LEFT(E335,4))=RIGHT(LEFT(C335,4)),1,0)))))) | K335: =IF(E335="","",IF(RIGHT(LEFT(E335,5))=".","B",IF(RIGHT(LEFT(E335,5))="*","M",IF(RIGHT(LEFT(C335,5))="Z",8,IF(RIGHT(LEFT(C335,5))="X",9,IF(RIGHT(LEFT(E335,5))=RIGHT(LEFT(C335,5)),1,0)))))) | L335: =IF(E335="","",IF(RIGHT(LEFT(E335,6))=".","B",IF(RIGHT(LEFT(E335,6))="*","M",IF(RIGHT(LEFT(C335,6))="Z",8,IF(RIGHT(LEFT(C335,6))="X",9,IF(RIGHT(LEFT(E335,6))=RIGHT(LEFT(C335,6)),1,0)))))) | M335: =IF(E335="","",IF(RIGHT(LEFT(E335,7))=".","B",IF(RIGHT(LEFT(E335,7))="*","M",IF(RIGHT(LEFT(C335,7))="Z",8,IF(RIGHT(LEFT(C335,7))="X",9,IF(RIGHT(LEFT(E335,7))=RIGHT(LEFT(C335,7)),1,0)))))) | N335: =IF(E335="","",IF(RIGHT(LEFT(E335,8))=".","B",IF(RIGHT(LEFT(E335,8))="*","M",IF(RIGHT(LEFT(C335,8))="Z",8,IF(RIGHT(LEFT(C335,8))="X",9,IF(RIGHT(LEFT(E335,8))=RIGHT(LEFT(C335,8)),1,0)))))) | O335: =IF(F335="","",IF(RIGHT(LEFT(F335,1))=".","B",IF(RIGHT(LEFT(F335,1))="*","M",IF(RIGHT(LEFT(D335,1))="Z",8,IF(RIGHT(LEFT(D335,1))="X",9,IF(RIGHT(LEFT(F335,1))=RIGHT(LEFT(D335,1)),1,0)))))) | P335: =IF(F335="","",IF(RIGHT(LEFT(F335,2))=".","B",IF(RIGHT(LEFT(F335,2))="*","M",IF(RIGHT(LEFT(D335,2))="Z",8,IF(RIGHT(LEFT(D335,2))="X",9,IF(RIGHT(LEFT(F335,2))=RIGHT(LEFT(D335,2)),1,0)))))) | Q335: =IF(F335="","",IF(RIGHT(LEFT(F335,3))=".","B",IF(RIGHT(LEFT(F335,3))="*","M",IF(RIGHT(LEFT(D335,3))="Z",8,IF(RIGHT(LEFT(D335,3))="X",9,IF(RIGHT(LEFT(F335,3))=RIGHT(LEFT(D335,3)),1,0)))))) | R335: =IF(F335="","",IF(RIGHT(LEFT(F335,4))=".","B",IF(RIGHT(LEFT(F335,4))="*","M",IF(RIGHT(LEFT(D335,4))="Z",8,IF(RIGHT(LEFT(D335,4))="X",9,IF(RIGHT(LEFT(F335,4))=RIGHT(LEFT(D335,4)),1,0)))))) | S335: =IF(F335="","",IF(RIGHT(LEFT(F335,5))=".","B",IF(RIGHT(LEFT(F335,5))="*","M",IF(RIGHT(LEFT(D335,5))="Z",8,IF(RIGHT(LEFT(D335,5))="X",9,IF(RIGHT(LEFT(F335,5))=RIGHT(LEFT(D335,5)),1,0)))))) | T335: =IF(F335="","",IF(RIGHT(LEFT(F335,6))=".","B",IF(RIGHT(LEFT(F335,6))="*","M",IF(RIGHT(LEFT(D335,6))="Z",8,IF(RIGHT(LEFT(D335,6))="X",9,IF(RIGHT(LEFT(F335,6))=RIGHT(LEFT(D335,6)),1,0)))))) | U335: =IF(F335="","",IF(RIGHT(LEFT(F335,7))=".","B",IF(RIGHT(LEFT(F335,7))="*","M",IF(RIGHT(LEFT(D335,7))="Z",8,IF(RIGHT(LEFT(D335,7))="X",9,IF(RIGHT(LEFT(F335,7))=RIGHT(LEFT(D335,7)),1,0)))))) | V335: =IF(F335="","",IF(RIGHT(LEFT(F335,8))=".","B",IF(RIGHT(LEFT(F335,8))="*","M",IF(RIGHT(LEFT(D335,8))="Z",8,IF(RIGHT(LEFT(D335,8))="X",9,IF(RIGHT(LEFT(F335,8))=RIGHT(LEFT(D335,8)),1,0)))))) | W335: =IF(F335="","",IF(RIGHT(LEFT(F335,9))=".","B",IF(RIGHT(LEFT(F335,9))="*","M",IF(RIGHT(LEFT(D335,9))="Z",8,IF(RIGHT(LEFT(D335,9))="X",9,IF(RIGHT(LEFT(F335,9))=RIGHT(LEFT(D335,9)),1,0)))))) | X335: =IF(F335="","",IF(RIGHT(LEFT(F335,10))=".","B",IF(RIGHT(LEFT(F335,10))="*","M",IF(RIGHT(LEFT(D335,10))="Z",8,IF(RIGHT(LEFT(D335,10))="X",9,IF(RIGHT(LEFT(F335,10))=RIGHT(LEFT(D335,10)),1,0)))))) | Y335: =IF(F335="","",IF(RIGHT(LEFT(F335,11))=".","B",IF(RIGHT(LEFT(F335,11))="*","M",IF(RIGHT(LEFT(D335,11))="Z",8,IF(RIGHT(LEFT(D335,11))="X",9,IF(RIGHT(LEFT(F335,11))=RIGHT(LEFT(D335,11)),1,0)))))) | Z335: =IF(F335="","",IF(RIGHT(LEFT(F335,12))=".","B",IF(RIGHT(LEFT(F335,12))="*","M",IF(RIGHT(LEFT(D335,12))="Z",8,IF(RIGHT(LEFT(D335,12))="X",9,IF(RIGHT(LEFT(F335,12))=RIGHT(LEFT(D335,12)),1,0)))))) | AA335: =IF(F335="","",IF(RIGHT(LEFT(F335,13))=".","B",IF(RIGHT(LEFT(F335,13))="*","M",IF(RIGHT(LEFT(D335,13))="Z",8,IF(RIGHT(LEFT(D335,13))="X",9,IF(RIGHT(LEFT(F335,13))=RIGHT(LEFT(D335,13)),1,0)))))) | AB335: =IF(F335="","",IF(RIGHT(LEFT(F335,14))=".","B",IF(RIGHT(LEFT(F335,14))="*","M",IF(RIGHT(LEFT(D335,14))="Z",8,IF(RIGHT(LEFT(D335,14))="X",9,IF(RIGHT(LEFT(F335,14))=RIGHT(LEFT(D335,14)),1,0)))))) | AC335: =IF(F335="","",IF(RIGHT(LEFT(F335,15))=".","B",IF(RIGHT(LEFT(F335,15))="*","M",IF(RIGHT(LEFT(D335,15))="Z",8,IF(RIGHT(LEFT(D335,15))="X",9,IF(RIGHT(LEFT(F335,15))=RIGHT(LEFT(D335,15)),1,0)))))) | AD335: =IF(F335="","",IF(RIGHT(LEFT(F335,16))=".","B",IF(RIGHT(LEFT(F335,16))="*","M",IF(RIGHT(LEFT(D335,16))="Z",8,IF(RIGHT(LEFT(D335,16))="X",9,IF(RIGHT(LEFT(F335,16))=RIGHT(LEFT(D335,16)),1,0)))))) | AE335: =IF(F335="","",IF(RIGHT(LEFT(F335,17))=".","B",IF(RIGHT(LEFT(F335,17))="*","M",IF(RIGHT(LEFT(D335,17))="Z",8,IF(RIGHT(LEFT(D335,17))="X",9,IF(RIGHT(LEFT(F335,17))=RIGHT(LEFT(D335,17)),1,0)))))) | AF335: =IF(F335="","",IF(RIGHT(LEFT(F335,18))=".","B",IF(RIGHT(LEFT(F335,18))="*","M",IF(RIGHT(LEFT(D335,18))="Z",8,IF(RIGHT(LEFT(D335,18))="X",9,IF(RIGHT(LEFT(F335,18))=RIGHT(LEFT(D335,18)),1,0)))))) | AG335: =IF(F335="","",IF(RIGHT(LEFT(F335,19))=".","B",IF(RIGHT(LEFT(F335,19))="*","M",IF(RIGHT(LEFT(D335,19))="Z",8,IF(RIGHT(LEFT(D335,19))="X",9,IF(RIGHT(LEFT(F335,19))=RIGHT(LEFT(D335,19)),1,0)))))) | AH335: =IF(F335="","",IF(RIGHT(LEFT(F335,20))=".","B",IF(RIGHT(LEFT(F335,20))="*","M",IF(RIGHT(LEFT(D335,20))="Z",8,IF(RIGHT(LEFT(D335,20))="X",9,IF(RIGHT(LEFT(F335,20))=RIGHT(LEFT(D335,20)),1,0)))))) | AI335: =IF(F335="","",IF(RIGHT(LEFT(F335,21))=".","B",IF(RIGHT(LEFT(F335,21))="*","M",IF(RIGHT(LEFT(D335,21))="Z",8,IF(RIGHT(LEFT(D335,21))="X",9,IF(RIGHT(LEFT(F335,21))=RIGHT(LEFT(D335,21)),1,0)))))) | AJ335: =IF(F335="","",IF(RIGHT(LEFT(F335,22))=".","B",IF(RIGHT(LEFT(F335,22))="*","M",IF(RIGHT(LEFT(D335,22))="Z",8,IF(RIGHT(LEFT(D335,22))="X",9,IF(RIGHT(LEFT(F335,22))=RIGHT(LEFT(D335,22)),1,0)))))) | AK335: =IF(F335="","",IF(RIGHT(LEFT(F335,23))=".","B",IF(RIGHT(LEFT(F335,23))="*","M",IF(RIGHT(LEFT(D335,23))="Z",8,IF(RIGHT(LEFT(D335,23))="X",9,IF(RIGHT(LEFT(F335,23))=RIGHT(LEFT(D335,23)),1,0)))))) | AL335: =IF(F335="","",IF(RIGHT(LEFT(F335,24))=".","B",IF(RIGHT(LEFT(F335,24))="*","M",IF(RIGHT(LEFT(D335,24))="Z",8,IF(RIGHT(LEFT(D335,24))="X",9,IF(RIGHT(LEFT(F335,24))=RIGHT(LEFT(D335,24)),1,0)))))) | AM335: =IF(F335="","",IF(RIGHT(LEFT(F335,25))=".","B",IF(RIGHT(LEFT(F335,25))="*","M",IF(RIGHT(LEFT(D335,25))="Z",8,IF(RIGHT(LEFT(D335,25))="X",9,IF(RIGHT(LEFT(F335,25))=RIGHT(LEFT(D335,25)),1,0)))))) | AN335: =IF(F335="","",IF(RIGHT(LEFT(F335,26))=".","B",IF(RIGHT(LEFT(F335,26))="*","M",IF(RIGHT(LEFT(D335,26))="Z",8,IF(RIGHT(LEFT(D335,26))="X",9,IF(RIGHT(LEFT(F335,26))=RIGHT(LEFT(D335,26)),1,0)))))) | AO335: =IF(F335="","",IF(RIGHT(LEFT(F335,27))=".","B",IF(RIGHT(LEFT(F335,27))="*","M",IF(RIGHT(LEFT(D335,27))="Z",8,IF(RIGHT(LEFT(D335,27))="X",9,IF(RIGHT(LEFT(F335,27))=RIGHT(LEFT(D335,27)),1,0))))))
A336: 2019 | B336: 88399 | C336: ZDCBCCDB | D336: ZAXDBBAXDABEEZECZAEZBCXBZBC | G336: =IF(E336="","",IF(RIGHT(LEFT(E336,1))=".","B",IF(RIGHT(LEFT(E336,1))="*","M",IF(RIGHT(LEFT(C336,1))="Z",8,IF(RIGHT(LEFT(C336,1))="X",9,IF(RIGHT(LEFT(E336,1))=RIGHT(LEFT(C336,1)),1,0)))))) | H336: =IF(E336="","",IF(RIGHT(LEFT(E336,2))=".","B",IF(RIGHT(LEFT(E336,2))="*","M",IF(RIGHT(LEFT(C336,2))="Z",8,IF(RIGHT(LEFT(C336,2))="X",9,IF(RIGHT(LEFT(E336,2))=RIGHT(LEFT(C336,2)),1,0)))))) | I336: =IF(E336="","",IF(RIGHT(LEFT(E336,3))=".","B",IF(RIGHT(LEFT(E336,3))="*","M",IF(RIGHT(LEFT(C336,3))="Z",8,IF(RIGHT(LEFT(C336,3))="X",9,IF(RIGHT(LEFT(E336,3))=RIGHT(LEFT(C336,3)),1,0)))))) | J336: =IF(E336="","",IF(RIGHT(LEFT(E336,4))=".","B",IF(RIGHT(LEFT(E336,4))="*","M",IF(RIGHT(LEFT(C336,4))="Z",8,IF(RIGHT(LEFT(C336,4))="X",9,IF(RIGHT(LEFT(E336,4))=RIGHT(LEFT(C336,4)),1,0)))))) | K336: =IF(E336="","",IF(RIGHT(LEFT(E336,5))=".","B",IF(RIGHT(LEFT(E336,5))="*","M",IF(RIGHT(LEFT(C336,5))="Z",8,IF(RIGHT(LEFT(C336,5))="X",9,IF(RIGHT(LEFT(E336,5))=RIGHT(LEFT(C336,5)),1,0)))))) | L336: =IF(E336="","",IF(RIGHT(LEFT(E336,6))=".","B",IF(RIGHT(LEFT(E336,6))="*","M",IF(RIGHT(LEFT(C336,6))="Z",8,IF(RIGHT(LEFT(C336,6))="X",9,IF(RIGHT(LEFT(E336,6))=RIGHT(LEFT(C336,6)),1,0)))))) | M336: =IF(E336="","",IF(RIGHT(LEFT(E336,7))=".","B",IF(RIGHT(LEFT(E336,7))="*","M",IF(RIGHT(LEFT(C336,7))="Z",8,IF(RIGHT(LEFT(C336,7))="X",9,IF(RIGHT(LEFT(E336,7))=RIGHT(LEFT(C336,7)),1,0)))))) | N336: =IF(E336="","",IF(RIGHT(LEFT(E336,8))=".","B",IF(RIGHT(LEFT(E336,8))="*","M",IF(RIGHT(LEFT(C336,8))="Z",8,IF(RIGHT(LEFT(C336,8))="X",9,IF(RIGHT(LEFT(E336,8))=RIGHT(LEFT(C336,8)),1,0)))))) | O336: =IF(F336="","",IF(RIGHT(LEFT(F336,1))=".","B",IF(RIGHT(LEFT(F336,1))="*","M",IF(RIGHT(LEFT(D336,1))="Z",8,IF(RIGHT(LEFT(D336,1))="X",9,IF(RIGHT(LEFT(F336,1))=RIGHT(LEFT(D336,1)),1,0)))))) | P336: =IF(F336="","",IF(RIGHT(LEFT(F336,2))=".","B",IF(RIGHT(LEFT(F336,2))="*","M",IF(RIGHT(LEFT(D336,2))="Z",8,IF(RIGHT(LEFT(D336,2))="X",9,IF(RIGHT(LEFT(F336,2))=RIGHT(LEFT(D336,2)),1,0)))))) | Q336: =IF(F336="","",IF(RIGHT(LEFT(F336,3))=".","B",IF(RIGHT(LEFT(F336,3))="*","M",IF(RIGHT(LEFT(D336,3))="Z",8,IF(RIGHT(LEFT(D336,3))="X",9,IF(RIGHT(LEFT(F336,3))=RIGHT(LEFT(D336,3)),1,0)))))) | R336: =IF(F336="","",IF(RIGHT(LEFT(F336,4))=".","B",IF(RIGHT(LEFT(F336,4))="*","M",IF(RIGHT(LEFT(D336,4))="Z",8,IF(RIGHT(LEFT(D336,4))="X",9,IF(RIGHT(LEFT(F336,4))=RIGHT(LEFT(D336,4)),1,0)))))) | S336: =IF(F336="","",IF(RIGHT(LEFT(F336,5))=".","B",IF(RIGHT(LEFT(F336,5))="*","M",IF(RIGHT(LEFT(D336,5))="Z",8,IF(RIGHT(LEFT(D336,5))="X",9,IF(RIGHT(LEFT(F336,5))=RIGHT(LEFT(D336,5)),1,0)))))) | T336: =IF(F336="","",IF(RIGHT(LEFT(F336,6))=".","B",IF(RIGHT(LEFT(F336,6))="*","M",IF(RIGHT(LEFT(D336,6))="Z",8,IF(RIGHT(LEFT(D336,6))="X",9,IF(RIGHT(LEFT(F336,6))=RIGHT(LEFT(D336,6)),1,0)))))) | U336: =IF(F336="","",IF(RIGHT(LEFT(F336,7))=".","B",IF(RIGHT(LEFT(F336,7))="*","M",IF(RIGHT(LEFT(D336,7))="Z",8,IF(RIGHT(LEFT(D336,7))="X",9,IF(RIGHT(LEFT(F336,7))=RIGHT(LEFT(D336,7)),1,0)))))) | V336: =IF(F336="","",IF(RIGHT(LEFT(F336,8))=".","B",IF(RIGHT(LEFT(F336,8))="*","M",IF(RIGHT(LEFT(D336,8))="Z",8,IF(RIGHT(LEFT(D336,8))="X",9,IF(RIGHT(LEFT(F336,8))=RIGHT(LEFT(D336,8)),1,0)))))) | W336: =IF(F336="","",IF(RIGHT(LEFT(F336,9))=".","B",IF(RIGHT(LEFT(F336,9))="*","M",IF(RIGHT(LEFT(D336,9))="Z",8,IF(RIGHT(LEFT(D336,9))="X",9,IF(RIGHT(LEFT(F336,9))=RIGHT(LEFT(D336,9)),1,0)))))) | X336: =IF(F336="","",IF(RIGHT(LEFT(F336,10))=".","B",IF(RIGHT(LEFT(F336,10))="*","M",IF(RIGHT(LEFT(D336,10))="Z",8,IF(RIGHT(LEFT(D336,10))="X",9,IF(RIGHT(LEFT(F336,10))=RIGHT(LEFT(D336,10)),1,0)))))) | Y336: =IF(F336="","",IF(RIGHT(LEFT(F336,11))=".","B",IF(RIGHT(LEFT(F336,11))="*","M",IF(RIGHT(LEFT(D336,11))="Z",8,IF(RIGHT(LEFT(D336,11))="X",9,IF(RIGHT(LEFT(F336,11))=RIGHT(LEFT(D336,11)),1,0)))))) | Z336: =IF(F336="","",IF(RIGHT(LEFT(F336,12))=".","B",IF(RIGHT(LEFT(F336,12))="*","M",IF(RIGHT(LEFT(D336,12))="Z",8,IF(RIGHT(LEFT(D336,12))="X",9,IF(RIGHT(LEFT(F336,12))=RIGHT(LEFT(D336,12)),1,0)))))) | AA336: =IF(F336="","",IF(RIGHT(LEFT(F336,13))=".","B",IF(RIGHT(LEFT(F336,13))="*","M",IF(RIGHT(LEFT(D336,13))="Z",8,IF(RIGHT(LEFT(D336,13))="X",9,IF(RIGHT(LEFT(F336,13))=RIGHT(LEFT(D336,13)),1,0)))))) | AB336: =IF(F336="","",IF(RIGHT(LEFT(F336,14))=".","B",IF(RIGHT(LEFT(F336,14))="*","M",IF(RIGHT(LEFT(D336,14))="Z",8,IF(RIGHT(LEFT(D336,14))="X",9,IF(RIGHT(LEFT(F336,14))=RIGHT(LEFT(D336,14)),1,0)))))) | AC336: =IF(F336="","",IF(RIGHT(LEFT(F336,15))=".","B",IF(RIGHT(LEFT(F336,15))="*","M",IF(RIGHT(LEFT(D336,15))="Z",8,IF(RIGHT(LEFT(D336,15))="X",9,IF(RIGHT(LEFT(F336,15))=RIGHT(LEFT(D336,15)),1,0)))))) | AD336: =IF(F336="","",IF(RIGHT(LEFT(F336,16))=".","B",IF(RIGHT(LEFT(F336,16))="*","M",IF(RIGHT(LEFT(D336,16))="Z",8,IF(RIGHT(LEFT(D336,16))="X",9,IF(RIGHT(LEFT(F336,16))=RIGHT(LEFT(D336,16)),1,0)))))) | AE336: =IF(F336="","",IF(RIGHT(LEFT(F336,17))=".","B",IF(RIGHT(LEFT(F336,17))="*","M",IF(RIGHT(LEFT(D336,17))="Z",8,IF(RIGHT(LEFT(D336,17))="X",9,IF(RIGHT(LEFT(F336,17))=RIGHT(LEFT(D336,17)),1,0)))))) | AF336: =IF(F336="","",IF(RIGHT(LEFT(F336,18))=".","B",IF(RIGHT(LEFT(F336,18))="*","M",IF(RIGHT(LEFT(D336,18))="Z",8,IF(RIGHT(LEFT(D336,18))="X",9,IF(RIGHT(LEFT(F336,18))=RIGHT(LEFT(D336,18)),1,0)))))) | AG336: =IF(F336="","",IF(RIGHT(LEFT(F336,19))=".","B",IF(RIGHT(LEFT(F336,19))="*","M",IF(RIGHT(LEFT(D336,19))="Z",8,IF(RIGHT(LEFT(D336,19))="X",9,IF(RIGHT(LEFT(F336,19))=RIGHT(LEFT(D336,19)),1,0)))))) | AH336: =IF(F336="","",IF(RIGHT(LEFT(F336,20))=".","B",IF(RIGHT(LEFT(F336,20))="*","M",IF(RIGHT(LEFT(D336,20))="Z",8,IF(RIGHT(LEFT(D336,20))="X",9,IF(RIGHT(LEFT(F336,20))=RIGHT(LEFT(D336,20)),1,0)))))) | AI336: =IF(F336="","",IF(RIGHT(LEFT(F336,21))=".","B",IF(RIGHT(LEFT(F336,21))="*","M",IF(RIGHT(LEFT(D336,21))="Z",8,IF(RIGHT(LEFT(D336,21))="X",9,IF(RIGHT(LEFT(F336,21))=RIGHT(LEFT(D336,21)),1,0)))))) | AJ336: =IF(F336="","",IF(RIGHT(LEFT(F336,22))=".","B",IF(RIGHT(LEFT(F336,22))="*","M",IF(RIGHT(LEFT(D336,22))="Z",8,IF(RIGHT(LEFT(D336,22))="X",9,IF(RIGHT(LEFT(F336,22))=RIGHT(LEFT(D336,22)),1,0)))))) | AK336: =IF(F336="","",IF(RIGHT(LEFT(F336,23))=".","B",IF(RIGHT(LEFT(F336,23))="*","M",IF(RIGHT(LEFT(D336,23))="Z",8,IF(RIGHT(LEFT(D336,23))="X",9,IF(RIGHT(LEFT(F336,23))=RIGHT(LEFT(D336,23)),1,0)))))) | AL336: =IF(F336="","",IF(RIGHT(LEFT(F336,24))=".","B",IF(RIGHT(LEFT(F336,24))="*","M",IF(RIGHT(LEFT(D336,24))="Z",8,IF(RIGHT(LEFT(D336,24))="X",9,IF(RIGHT(LEFT(F336,24))=RIGHT(LEFT(D336,24)),1,0)))))) | AM336: =IF(F336="","",IF(RIGHT(LEFT(F336,25))=".","B",IF(RIGHT(LEFT(F336,25))="*","M",IF(RIGHT(LEFT(D336,25))="Z",8,IF(RIGHT(LEFT(D336,25))="X",9,IF(RIGHT(LEFT(F336,25))=RIGHT(LEFT(D336,25)),1,0)))))) | AN336: =IF(F336="","",IF(RIGHT(LEFT(F336,26))=".","B",IF(RIGHT(LEFT(F336,26))="*","M",IF(RIGHT(LEFT(D336,26))="Z",8,IF(RIGHT(LEFT(D336,26))="X",9,IF(RIGHT(LEFT(F336,26))=RIGHT(LEFT(D336,26)),1,0)))))) | AO336: =IF(F336="","",IF(RIGHT(LEFT(F336,27))=".","B",IF(RIGHT(LEFT(F336,27))="*","M",IF(RIGHT(LEFT(D336,27))="Z",8,IF(RIGHT(LEFT(D336,27))="X",9,IF(RIGHT(LEFT(F336,27))=RIGHT(LEFT(D336,27)),1,0))))))
A337: 2019 | B337: 88399 | C337: ZDCBCCDB | D337: ZAXDBBAXDABEEZECZAEZBCXBZBC | G337: =IF(E337="","",IF(RIGHT(LEFT(E337,1))=".","B",IF(RIGHT(LEFT(E337,1))="*","M",IF(RIGHT(LEFT(C337,1))="Z",8,IF(RIGHT(LEFT(C337,1))="X",9,IF(RIGHT(LEFT(E337,1))=RIGHT(LEFT(C337,1)),1,0)))))) | H337: =IF(E337="","",IF(RIGHT(LEFT(E337,2))=".","B",IF(RIGHT(LEFT(E337,2))="*","M",IF(RIGHT(LEFT(C337,2))="Z",8,IF(RIGHT(LEFT(C337,2))="X",9,IF(RIGHT(LEFT(E337,2))=RIGHT(LEFT(C337,2)),1,0)))))) | I337: =IF(E337="","",IF(RIGHT(LEFT(E337,3))=".","B",IF(RIGHT(LEFT(E337,3))="*","M",IF(RIGHT(LEFT(C337,3))="Z",8,IF(RIGHT(LEFT(C337,3))="X",9,IF(RIGHT(LEFT(E337,3))=RIGHT(LEFT(C337,3)),1,0)))))) | J337: =IF(E337="","",IF(RIGHT(LEFT(E337,4))=".","B",IF(RIGHT(LEFT(E337,4))="*","M",IF(RIGHT(LEFT(C337,4))="Z",8,IF(RIGHT(LEFT(C337,4))="X",9,IF(RIGHT(LEFT(E337,4))=RIGHT(LEFT(C337,4)),1,0)))))) | K337: =IF(E337="","",IF(RIGHT(LEFT(E337,5))=".","B",IF(RIGHT(LEFT(E337,5))="*","M",IF(RIGHT(LEFT(C337,5))="Z",8,IF(RIGHT(LEFT(C337,5))="X",9,IF(RIGHT(LEFT(E337,5))=RIGHT(LEFT(C337,5)),1,0)))))) | L337: =IF(E337="","",IF(RIGHT(LEFT(E337,6))=".","B",IF(RIGHT(LEFT(E337,6))="*","M",IF(RIGHT(LEFT(C337,6))="Z",8,IF(RIGHT(LEFT(C337,6))="X",9,IF(RIGHT(LEFT(E337,6))=RIGHT(LEFT(C337,6)),1,0)))))) | M337: =IF(E337="","",IF(RIGHT(LEFT(E337,7))=".","B",IF(RIGHT(LEFT(E337,7))="*","M",IF(RIGHT(LEFT(C337,7))="Z",8,IF(RIGHT(LEFT(C337,7))="X",9,IF(RIGHT(LEFT(E337,7))=RIGHT(LEFT(C337,7)),1,0)))))) | N337: =IF(E337="","",IF(RIGHT(LEFT(E337,8))=".","B",IF(RIGHT(LEFT(E337,8))="*","M",IF(RIGHT(LEFT(C337,8))="Z",8,IF(RIGHT(LEFT(C337,8))="X",9,IF(RIGHT(LEFT(E337,8))=RIGHT(LEFT(C337,8)),1,0)))))) | O337: =IF(F337="","",IF(RIGHT(LEFT(F337,1))=".","B",IF(RIGHT(LEFT(F337,1))="*","M",IF(RIGHT(LEFT(D337,1))="Z",8,IF(RIGHT(LEFT(D337,1))="X",9,IF(RIGHT(LEFT(F337,1))=RIGHT(LEFT(D337,1)),1,0)))))) | P337: =IF(F337="","",IF(RIGHT(LEFT(F337,2))=".","B",IF(RIGHT(LEFT(F337,2))="*","M",IF(RIGHT(LEFT(D337,2))="Z",8,IF(RIGHT(LEFT(D337,2))="X",9,IF(RIGHT(LEFT(F337,2))=RIGHT(LEFT(D337,2)),1,0)))))) | Q337: =IF(F337="","",IF(RIGHT(LEFT(F337,3))=".","B",IF(RIGHT(LEFT(F337,3))="*","M",IF(RIGHT(LEFT(D337,3))="Z",8,IF(RIGHT(LEFT(D337,3))="X",9,IF(RIGHT(LEFT(F337,3))=RIGHT(LEFT(D337,3)),1,0)))))) | R337: =IF(F337="","",IF(RIGHT(LEFT(F337,4))=".","B",IF(RIGHT(LEFT(F337,4))="*","M",IF(RIGHT(LEFT(D337,4))="Z",8,IF(RIGHT(LEFT(D337,4))="X",9,IF(RIGHT(LEFT(F337,4))=RIGHT(LEFT(D337,4)),1,0)))))) | S337: =IF(F337="","",IF(RIGHT(LEFT(F337,5))=".","B",IF(RIGHT(LEFT(F337,5))="*","M",IF(RIGHT(LEFT(D337,5))="Z",8,IF(RIGHT(LEFT(D337,5))="X",9,IF(RIGHT(LEFT(F337,5))=RIGHT(LEFT(D337,5)),1,0)))))) | T337: =IF(F337="","",IF(RIGHT(LEFT(F337,6))=".","B",IF(RIGHT(LEFT(F337,6))="*","M",IF(RIGHT(LEFT(D337,6))="Z",8,IF(RIGHT(LEFT(D337,6))="X",9,IF(RIGHT(LEFT(F337,6))=RIGHT(LEFT(D337,6)),1,0)))))) | U337: =IF(F337="","",IF(RIGHT(LEFT(F337,7))=".","B",IF(RIGHT(LEFT(F337,7))="*","M",IF(RIGHT(LEFT(D337,7))="Z",8,IF(RIGHT(LEFT(D337,7))="X",9,IF(RIGHT(LEFT(F337,7))=RIGHT(LEFT(D337,7)),1,0)))))) | V337: =IF(F337="","",IF(RIGHT(LEFT(F337,8))=".","B",IF(RIGHT(LEFT(F337,8))="*","M",IF(RIGHT(LEFT(D337,8))="Z",8,IF(RIGHT(LEFT(D337,8))="X",9,IF(RIGHT(LEFT(F337,8))=RIGHT(LEFT(D337,8)),1,0)))))) | W337: =IF(F337="","",IF(RIGHT(LEFT(F337,9))=".","B",IF(RIGHT(LEFT(F337,9))="*","M",IF(RIGHT(LEFT(D337,9))="Z",8,IF(RIGHT(LEFT(D337,9))="X",9,IF(RIGHT(LEFT(F337,9))=RIGHT(LEFT(D337,9)),1,0)))))) | X337: =IF(F337="","",IF(RIGHT(LEFT(F337,10))=".","B",IF(RIGHT(LEFT(F337,10))="*","M",IF(RIGHT(LEFT(D337,10))="Z",8,IF(RIGHT(LEFT(D337,10))="X",9,IF(RIGHT(LEFT(F337,10))=RIGHT(LEFT(D337,10)),1,0)))))) | Y337: =IF(F337="","",IF(RIGHT(LEFT(F337,11))=".","B",IF(RIGHT(LEFT(F337,11))="*","M",IF(RIGHT(LEFT(D337,11))="Z",8,IF(RIGHT(LEFT(D337,11))="X",9,IF(RIGHT(LEFT(F337,11))=RIGHT(LEFT(D337,11)),1,0)))))) | Z337: =IF(F337="","",IF(RIGHT(LEFT(F337,12))=".","B",IF(RIGHT(LEFT(F337,12))="*","M",IF(RIGHT(LEFT(D337,12))="Z",8,IF(RIGHT(LEFT(D337,12))="X",9,IF(RIGHT(LEFT(F337,12))=RIGHT(LEFT(D337,12)),1,0)))))) | AA337: =IF(F337="","",IF(RIGHT(LEFT(F337,13))=".","B",IF(RIGHT(LEFT(F337,13))="*","M",IF(RIGHT(LEFT(D337,13))="Z",8,IF(RIGHT(LEFT(D337,13))="X",9,IF(RIGHT(LEFT(F337,13))=RIGHT(LEFT(D337,13)),1,0)))))) | AB337: =IF(F337="","",IF(RIGHT(LEFT(F337,14))=".","B",IF(RIGHT(LEFT(F337,14))="*","M",IF(RIGHT(LEFT(D337,14))="Z",8,IF(RIGHT(LEFT(D337,14))="X",9,IF(RIGHT(LEFT(F337,14))=RIGHT(LEFT(D337,14)),1,0)))))) | AC337: =IF(F337="","",IF(RIGHT(LEFT(F337,15))=".","B",IF(RIGHT(LEFT(F337,15))="*","M",IF(RIGHT(LEFT(D337,15))="Z",8,IF(RIGHT(LEFT(D337,15))="X",9,IF(RIGHT(LEFT(F337,15))=RIGHT(LEFT(D337,15)),1,0)))))) | AD337: =IF(F337="","",IF(RIGHT(LEFT(F337,16))=".","B",IF(RIGHT(LEFT(F337,16))="*","M",IF(RIGHT(LEFT(D337,16))="Z",8,IF(RIGHT(LEFT(D337,16))="X",9,IF(RIGHT(LEFT(F337,16))=RIGHT(LEFT(D337,16)),1,0)))))) | AE337: =IF(F337="","",IF(RIGHT(LEFT(F337,17))=".","B",IF(RIGHT(LEFT(F337,17))="*","M",IF(RIGHT(LEFT(D337,17))="Z",8,IF(RIGHT(LEFT(D337,17))="X",9,IF(RIGHT(LEFT(F337,17))=RIGHT(LEFT(D337,17)),1,0)))))) | AF337: =IF(F337="","",IF(RIGHT(LEFT(F337,18))=".","B",IF(RIGHT(LEFT(F337,18))="*","M",IF(RIGHT(LEFT(D337,18))="Z",8,IF(RIGHT(LEFT(D337,18))="X",9,IF(RIGHT(LEFT(F337,18))=RIGHT(LEFT(D337,18)),1,0)))))) | AG337: =IF(F337="","",IF(RIGHT(LEFT(F337,19))=".","B",IF(RIGHT(LEFT(F337,19))="*","M",IF(RIGHT(LEFT(D337,19))="Z",8,IF(RIGHT(LEFT(D337,19))="X",9,IF(RIGHT(LEFT(F337,19))=RIGHT(LEFT(D337,19)),1,0)))))) | AH337: =IF(F337="","",IF(RIGHT(LEFT(F337,20))=".","B",IF(RIGHT(LEFT(F337,20))="*","M",IF(RIGHT(LEFT(D337,20))="Z",8,IF(RIGHT(LEFT(D337,20))="X",9,IF(RIGHT(LEFT(F337,20))=RIGHT(LEFT(D337,20)),1,0)))))) | AI337: =IF(F337="","",IF(RIGHT(LEFT(F337,21))=".","B",IF(RIGHT(LEFT(F337,21))="*","M",IF(RIGHT(LEFT(D337,21))="Z",8,IF(RIGHT(LEFT(D337,21))="X",9,IF(RIGHT(LEFT(F337,21))=RIGHT(LEFT(D337,21)),1,0)))))) | AJ337: =IF(F337="","",IF(RIGHT(LEFT(F337,22))=".","B",IF(RIGHT(LEFT(F337,22))="*","M",IF(RIGHT(LEFT(D337,22))="Z",8,IF(RIGHT(LEFT(D337,22))="X",9,IF(RIGHT(LEFT(F337,22))=RIGHT(LEFT(D337,22)),1,0)))))) | AK337: =IF(F337="","",IF(RIGHT(LEFT(F337,23))=".","B",IF(RIGHT(LEFT(F337,23))="*","M",IF(RIGHT(LEFT(D337,23))="Z",8,IF(RIGHT(LEFT(D337,23))="X",9,IF(RIGHT(LEFT(F337,23))=RIGHT(LEFT(D337,23)),1,0)))))) | AL337: =IF(F337="","",IF(RIGHT(LEFT(F337,24))=".","B",IF(RIGHT(LEFT(F337,24))="*","M",IF(RIGHT(LEFT(D337,24))="Z",8,IF(RIGHT(LEFT(D337,24))="X",9,IF(RIGHT(LEFT(F337,24))=RIGHT(LEFT(D337,24)),1,0)))))) | AM337: =IF(F337="","",IF(RIGHT(LEFT(F337,25))=".","B",IF(RIGHT(LEFT(F337,25))="*","M",IF(RIGHT(LEFT(D337,25))="Z",8,IF(RIGHT(LEFT(D337,25))="X",9,IF(RIGHT(LEFT(F337,25))=RIGHT(LEFT(D337,25)),1,0)))))) | AN337: =IF(F337="","",IF(RIGHT(LEFT(F337,26))=".","B",IF(RIGHT(LEFT(F337,26))="*","M",IF(RIGHT(LEFT(D337,26))="Z",8,IF(RIGHT(LEFT(D337,26))="X",9,IF(RIGHT(LEFT(F337,26))=RIGHT(LEFT(D337,26)),1,0)))))) | AO337: =IF(F337="","",IF(RIGHT(LEFT(F337,27))=".","B",IF(RIGHT(LEFT(F337,27))="*","M",IF(RIGHT(LEFT(D337,27))="Z",8,IF(RIGHT(LEFT(D337,27))="X",9,IF(RIGHT(LEFT(F337,27))=RIGHT(LEFT(D337,27)),1,0))))))
A338: 2019 | B338: 88399 | C338: ZDCBCCDB | D338: ZAXDBBAXDABEEZECZAEZBCXBZBC | G338: =IF(E338="","",IF(RIGHT(LEFT(E338,1))=".","B",IF(RIGHT(LEFT(E338,1))="*","M",IF(RIGHT(LEFT(C338,1))="Z",8,IF(RIGHT(LEFT(C338,1))="X",9,IF(RIGHT(LEFT(E338,1))=RIGHT(LEFT(C338,1)),1,0)))))) | H338: =IF(E338="","",IF(RIGHT(LEFT(E338,2))=".","B",IF(RIGHT(LEFT(E338,2))="*","M",IF(RIGHT(LEFT(C338,2))="Z",8,IF(RIGHT(LEFT(C338,2))="X",9,IF(RIGHT(LEFT(E338,2))=RIGHT(LEFT(C338,2)),1,0)))))) | I338: =IF(E338="","",IF(RIGHT(LEFT(E338,3))=".","B",IF(RIGHT(LEFT(E338,3))="*","M",IF(RIGHT(LEFT(C338,3))="Z",8,IF(RIGHT(LEFT(C338,3))="X",9,IF(RIGHT(LEFT(E338,3))=RIGHT(LEFT(C338,3)),1,0)))))) | J338: =IF(E338="","",IF(RIGHT(LEFT(E338,4))=".","B",IF(RIGHT(LEFT(E338,4))="*","M",IF(RIGHT(LEFT(C338,4))="Z",8,IF(RIGHT(LEFT(C338,4))="X",9,IF(RIGHT(LEFT(E338,4))=RIGHT(LEFT(C338,4)),1,0)))))) | K338: =IF(E338="","",IF(RIGHT(LEFT(E338,5))=".","B",IF(RIGHT(LEFT(E338,5))="*","M",IF(RIGHT(LEFT(C338,5))="Z",8,IF(RIGHT(LEFT(C338,5))="X",9,IF(RIGHT(LEFT(E338,5))=RIGHT(LEFT(C338,5)),1,0)))))) | L338: =IF(E338="","",IF(RIGHT(LEFT(E338,6))=".","B",IF(RIGHT(LEFT(E338,6))="*","M",IF(RIGHT(LEFT(C338,6))="Z",8,IF(RIGHT(LEFT(C338,6))="X",9,IF(RIGHT(LEFT(E338,6))=RIGHT(LEFT(C338,6)),1,0)))))) | M338: =IF(E338="","",IF(RIGHT(LEFT(E338,7))=".","B",IF(RIGHT(LEFT(E338,7))="*","M",IF(RIGHT(LEFT(C338,7))="Z",8,IF(RIGHT(LEFT(C338,7))="X",9,IF(RIGHT(LEFT(E338,7))=RIGHT(LEFT(C338,7)),1,0)))))) | N338: =IF(E338="","",IF(RIGHT(LEFT(E338,8))=".","B",IF(RIGHT(LEFT(E338,8))="*","M",IF(RIGHT(LEFT(C338,8))="Z",8,IF(RIGHT(LEFT(C338,8))="X",9,IF(RIGHT(LEFT(E338,8))=RIGHT(LEFT(C338,8)),1,0)))))) | O338: =IF(F338="","",IF(RIGHT(LEFT(F338,1))=".","B",IF(RIGHT(LEFT(F338,1))="*","M",IF(RIGHT(LEFT(D338,1))="Z",8,IF(RIGHT(LEFT(D338,1))="X",9,IF(RIGHT(LEFT(F338,1))=RIGHT(LEFT(D338,1)),1,0)))))) | P338: =IF(F338="","",IF(RIGHT(LEFT(F338,2))=".","B",IF(RIGHT(LEFT(F338,2))="*","M",IF(RIGHT(LEFT(D338,2))="Z",8,IF(RIGHT(LEFT(D338,2))="X",9,IF(RIGHT(LEFT(F338,2))=RIGHT(LEFT(D338,2)),1,0)))))) | Q338: =IF(F338="","",IF(RIGHT(LEFT(F338,3))=".","B",IF(RIGHT(LEFT(F338,3))="*","M",IF(RIGHT(LEFT(D338,3))="Z",8,IF(RIGHT(LEFT(D338,3))="X",9,IF(RIGHT(LEFT(F338,3))=RIGHT(LEFT(D338,3)),1,0)))))) | R338: =IF(F338="","",IF(RIGHT(LEFT(F338,4))=".","B",IF(RIGHT(LEFT(F338,4))="*","M",IF(RIGHT(LEFT(D338,4))="Z",8,IF(RIGHT(LEFT(D338,4))="X",9,IF(RIGHT(LEFT(F338,4))=RIGHT(LEFT(D338,4)),1,0)))))) | S338: =IF(F338="","",IF(RIGHT(LEFT(F338,5))=".","B",IF(RIGHT(LEFT(F338,5))="*","M",IF(RIGHT(LEFT(D338,5))="Z",8,IF(RIGHT(LEFT(D338,5))="X",9,IF(RIGHT(LEFT(F338,5))=RIGHT(LEFT(D338,5)),1,0)))))) | T338: =IF(F338="","",IF(RIGHT(LEFT(F338,6))=".","B",IF(RIGHT(LEFT(F338,6))="*","M",IF(RIGHT(LEFT(D338,6))="Z",8,IF(RIGHT(LEFT(D338,6))="X",9,IF(RIGHT(LEFT(F338,6))=RIGHT(LEFT(D338,6)),1,0)))))) | U338: =IF(F338="","",IF(RIGHT(LEFT(F338,7))=".","B",IF(RIGHT(LEFT(F338,7))="*","M",IF(RIGHT(LEFT(D338,7))="Z",8,IF(RIGHT(LEFT(D338,7))="X",9,IF(RIGHT(LEFT(F338,7))=RIGHT(LEFT(D338,7)),1,0)))))) | V338: =IF(F338="","",IF(RIGHT(LEFT(F338,8))=".","B",IF(RIGHT(LEFT(F338,8))="*","M",IF(RIGHT(LEFT(D338,8))="Z",8,IF(RIGHT(LEFT(D338,8))="X",9,IF(RIGHT(LEFT(F338,8))=RIGHT(LEFT(D338,8)),1,0)))))) | W338: =IF(F338="","",IF(RIGHT(LEFT(F338,9))=".","B",IF(RIGHT(LEFT(F338,9))="*","M",IF(RIGHT(LEFT(D338,9))="Z",8,IF(RIGHT(LEFT(D338,9))="X",9,IF(RIGHT(LEFT(F338,9))=RIGHT(LEFT(D338,9)),1,0)))))) | X338: =IF(F338="","",IF(RIGHT(LEFT(F338,10))=".","B",IF(RIGHT(LEFT(F338,10))="*","M",IF(RIGHT(LEFT(D338,10))="Z",8,IF(RIGHT(LEFT(D338,10))="X",9,IF(RIGHT(LEFT(F338,10))=RIGHT(LEFT(D338,10)),1,0)))))) | Y338: =IF(F338="","",IF(RIGHT(LEFT(F338,11))=".","B",IF(RIGHT(LEFT(F338,11))="*","M",IF(RIGHT(LEFT(D338,11))="Z",8,IF(RIGHT(LEFT(D338,11))="X",9,IF(RIGHT(LEFT(F338,11))=RIGHT(LEFT(D338,11)),1,0)))))) | Z338: =IF(F338="","",IF(RIGHT(LEFT(F338,12))=".","B",IF(RIGHT(LEFT(F338,12))="*","M",IF(RIGHT(LEFT(D338,12))="Z",8,IF(RIGHT(LEFT(D338,12))="X",9,IF(RIGHT(LEFT(F338,12))=RIGHT(LEFT(D338,12)),1,0)))))) | AA338: =IF(F338="","",IF(RIGHT(LEFT(F338,13))=".","B",IF(RIGHT(LEFT(F338,13))="*","M",IF(RIGHT(LEFT(D338,13))="Z",8,IF(RIGHT(LEFT(D338,13))="X",9,IF(RIGHT(LEFT(F338,13))=RIGHT(LEFT(D338,13)),1,0)))))) | AB338: =IF(F338="","",IF(RIGHT(LEFT(F338,14))=".","B",IF(RIGHT(LEFT(F338,14))="*","M",IF(RIGHT(LEFT(D338,14))="Z",8,IF(RIGHT(LEFT(D338,14))="X",9,IF(RIGHT(LEFT(F338,14))=RIGHT(LEFT(D338,14)),1,0)))))) | AC338: =IF(F338="","",IF(RIGHT(LEFT(F338,15))=".","B",IF(RIGHT(LEFT(F338,15))="*","M",IF(RIGHT(LEFT(D338,15))="Z",8,IF(RIGHT(LEFT(D338,15))="X",9,IF(RIGHT(LEFT(F338,15))=RIGHT(LEFT(D338,15)),1,0)))))) | AD338: =IF(F338="","",IF(RIGHT(LEFT(F338,16))=".","B",IF(RIGHT(LEFT(F338,16))="*","M",IF(RIGHT(LEFT(D338,16))="Z",8,IF(RIGHT(LEFT(D338,16))="X",9,IF(RIGHT(LEFT(F338,16))=RIGHT(LEFT(D338,16)),1,0)))))) | AE338: =IF(F338="","",IF(RIGHT(LEFT(F338,17))=".","B",IF(RIGHT(LEFT(F338,17))="*","M",IF(RIGHT(LEFT(D338,17))="Z",8,IF(RIGHT(LEFT(D338,17))="X",9,IF(RIGHT(LEFT(F338,17))=RIGHT(LEFT(D338,17)),1,0)))))) | AF338: =IF(F338="","",IF(RIGHT(LEFT(F338,18))=".","B",IF(RIGHT(LEFT(F338,18))="*","M",IF(RIGHT(LEFT(D338,18))="Z",8,IF(RIGHT(LEFT(D338,18))="X",9,IF(RIGHT(LEFT(F338,18))=RIGHT(LEFT(D338,18)),1,0)))))) | AG338: =IF(F338="","",IF(RIGHT(LEFT(F338,19))=".","B",IF(RIGHT(LEFT(F338,19))="*","M",IF(RIGHT(LEFT(D338,19))="Z",8,IF(RIGHT(LEFT(D338,19))="X",9,IF(RIGHT(LEFT(F338,19))=RIGHT(LEFT(D338,19)),1,0)))))) | AH338: =IF(F338="","",IF(RIGHT(LEFT(F338,20))=".","B",IF(RIGHT(LEFT(F338,20))="*","M",IF(RIGHT(LEFT(D338,20))="Z",8,IF(RIGHT(LEFT(D338,20))="X",9,IF(RIGHT(LEFT(F338,20))=RIGHT(LEFT(D338,20)),1,0)))))) | AI338: =IF(F338="","",IF(RIGHT(LEFT(F338,21))=".","B",IF(RIGHT(LEFT(F338,21))="*","M",IF(RIGHT(LEFT(D338,21))="Z",8,IF(RIGHT(LEFT(D338,21))="X",9,IF(RIGHT(LEFT(F338,21))=RIGHT(LEFT(D338,21)),1,0)))))) | AJ338: =IF(F338="","",IF(RIGHT(LEFT(F338,22))=".","B",IF(RIGHT(LEFT(F338,22))="*","M",IF(RIGHT(LEFT(D338,22))="Z",8,IF(RIGHT(LEFT(D338,22))="X",9,IF(RIGHT(LEFT(F338,22))=RIGHT(LEFT(D338,22)),1,0)))))) | AK338: =IF(F338="","",IF(RIGHT(LEFT(F338,23))=".","B",IF(RIGHT(LEFT(F338,23))="*","M",IF(RIGHT(LEFT(D338,23))="Z",8,IF(RIGHT(LEFT(D338,23))="X",9,IF(RIGHT(LEFT(F338,23))=RIGHT(LEFT(D338,23)),1,0)))))) | AL338: =IF(F338="","",IF(RIGHT(LEFT(F338,24))=".","B",IF(RIGHT(LEFT(F338,24))="*","M",IF(RIGHT(LEFT(D338,24))="Z",8,IF(RIGHT(LEFT(D338,24))="X",9,IF(RIGHT(LEFT(F338,24))=RIGHT(LEFT(D338,24)),1,0)))))) | AM338: =IF(F338="","",IF(RIGHT(LEFT(F338,25))=".","B",IF(RIGHT(LEFT(F338,25))="*","M",IF(RIGHT(LEFT(D338,25))="Z",8,IF(RIGHT(LEFT(D338,25))="X",9,IF(RIGHT(LEFT(F338,25))=RIGHT(LEFT(D338,25)),1,0)))))) | AN338: =IF(F338="","",IF(RIGHT(LEFT(F338,26))=".","B",IF(RIGHT(LEFT(F338,26))="*","M",IF(RIGHT(LEFT(D338,26))="Z",8,IF(RIGHT(LEFT(D338,26))="X",9,IF(RIGHT(LEFT(F338,26))=RIGHT(LEFT(D338,26)),1,0)))))) | AO338: =IF(F338="","",IF(RIGHT(LEFT(F338,27))=".","B",IF(RIGHT(LEFT(F338,27))="*","M",IF(RIGHT(LEFT(D338,27))="Z",8,IF(RIGHT(LEFT(D338,27))="X",9,IF(RIGHT(LEFT(F338,27))=RIGHT(LEFT(D338,27)),1,0))))))
A339: 2019 | B339: 102499 | C339: ZDCBCCDB | D339: BXBCDXEBAAEDAABXECCCDXXCAAZ | G339: =IF(E339="","",IF(RIGHT(LEFT(E339,1))=".","B",IF(RIGHT(LEFT(E339,1))="*","M",IF(RIGHT(LEFT(C339,1))="Z",8,IF(RIGHT(LEFT(C339,1))="X",9,IF(RIGHT(LEFT(E339,1))=RIGHT(LEFT(C339,1)),1,0)))))) | H339: =IF(E339="","",IF(RIGHT(LEFT(E339,2))=".","B",IF(RIGHT(LEFT(E339,2))="*","M",IF(RIGHT(LEFT(C339,2))="Z",8,IF(RIGHT(LEFT(C339,2))="X",9,IF(RIGHT(LEFT(E339,2))=RIGHT(LEFT(C339,2)),1,0)))))) | I339: =IF(E339="","",IF(RIGHT(LEFT(E339,3))=".","B",IF(RIGHT(LEFT(E339,3))="*","M",IF(RIGHT(LEFT(C339,3))="Z",8,IF(RIGHT(LEFT(C339,3))="X",9,IF(RIGHT(LEFT(E339,3))=RIGHT(LEFT(C339,3)),1,0)))))) | J339: =IF(E339="","",IF(RIGHT(LEFT(E339,4))=".","B",IF(RIGHT(LEFT(E339,4))="*","M",IF(RIGHT(LEFT(C339,4))="Z",8,IF(RIGHT(LEFT(C339,4))="X",9,IF(RIGHT(LEFT(E339,4))=RIGHT(LEFT(C339,4)),1,0)))))) | K339: =IF(E339="","",IF(RIGHT(LEFT(E339,5))=".","B",IF(RIGHT(LEFT(E339,5))="*","M",IF(RIGHT(LEFT(C339,5))="Z",8,IF(RIGHT(LEFT(C339,5))="X",9,IF(RIGHT(LEFT(E339,5))=RIGHT(LEFT(C339,5)),1,0)))))) | L339: =IF(E339="","",IF(RIGHT(LEFT(E339,6))=".","B",IF(RIGHT(LEFT(E339,6))="*","M",IF(RIGHT(LEFT(C339,6))="Z",8,IF(RIGHT(LEFT(C339,6))="X",9,IF(RIGHT(LEFT(E339,6))=RIGHT(LEFT(C339,6)),1,0)))))) | M339: =IF(E339="","",IF(RIGHT(LEFT(E339,7))=".","B",IF(RIGHT(LEFT(E339,7))="*","M",IF(RIGHT(LEFT(C339,7))="Z",8,IF(RIGHT(LEFT(C339,7))="X",9,IF(RIGHT(LEFT(E339,7))=RIGHT(LEFT(C339,7)),1,0)))))) | N339: =IF(E339="","",IF(RIGHT(LEFT(E339,8))=".","B",IF(RIGHT(LEFT(E339,8))="*","M",IF(RIGHT(LEFT(C339,8))="Z",8,IF(RIGHT(LEFT(C339,8))="X",9,IF(RIGHT(LEFT(E339,8))=RIGHT(LEFT(C339,8)),1,0)))))) | O339: =IF(F339="","",IF(RIGHT(LEFT(F339,1))=".","B",IF(RIGHT(LEFT(F339,1))="*","M",IF(RIGHT(LEFT(D339,1))="Z",8,IF(RIGHT(LEFT(D339,1))="X",9,IF(RIGHT(LEFT(F339,1))=RIGHT(LEFT(D339,1)),1,0)))))) | P339: =IF(F339="","",IF(RIGHT(LEFT(F339,2))=".","B",IF(RIGHT(LEFT(F339,2))="*","M",IF(RIGHT(LEFT(D339,2))="Z",8,IF(RIGHT(LEFT(D339,2))="X",9,IF(RIGHT(LEFT(F339,2))=RIGHT(LEFT(D339,2)),1,0)))))) | Q339: =IF(F339="","",IF(RIGHT(LEFT(F339,3))=".","B",IF(RIGHT(LEFT(F339,3))="*","M",IF(RIGHT(LEFT(D339,3))="Z",8,IF(RIGHT(LEFT(D339,3))="X",9,IF(RIGHT(LEFT(F339,3))=RIGHT(LEFT(D339,3)),1,0)))))) | R339: =IF(F339="","",IF(RIGHT(LEFT(F339,4))=".","B",IF(RIGHT(LEFT(F339,4))="*","M",IF(RIGHT(LEFT(D339,4))="Z",8,IF(RIGHT(LEFT(D339,4))="X",9,IF(RIGHT(LEFT(F339,4))=RIGHT(LEFT(D339,4)),1,0)))))) | S339: =IF(F339="","",IF(RIGHT(LEFT(F339,5))=".","B",IF(RIGHT(LEFT(F339,5))="*","M",IF(RIGHT(LEFT(D339,5))="Z",8,IF(RIGHT(LEFT(D339,5))="X",9,IF(RIGHT(LEFT(F339,5))=RIGHT(LEFT(D339,5)),1,0)))))) | T339: =IF(F339="","",IF(RIGHT(LEFT(F339,6))=".","B",IF(RIGHT(LEFT(F339,6))="*","M",IF(RIGHT(LEFT(D339,6))="Z",8,IF(RIGHT(LEFT(D339,6))="X",9,IF(RIGHT(LEFT(F339,6))=RIGHT(LEFT(D339,6)),1,0)))))) | U339: =IF(F339="","",IF(RIGHT(LEFT(F339,7))=".","B",IF(RIGHT(LEFT(F339,7))="*","M",IF(RIGHT(LEFT(D339,7))="Z",8,IF(RIGHT(LEFT(D339,7))="X",9,IF(RIGHT(LEFT(F339,7))=RIGHT(LEFT(D339,7)),1,0)))))) | V339: =IF(F339="","",IF(RIGHT(LEFT(F339,8))=".","B",IF(RIGHT(LEFT(F339,8))="*","M",IF(RIGHT(LEFT(D339,8))="Z",8,IF(RIGHT(LEFT(D339,8))="X",9,IF(RIGHT(LEFT(F339,8))=RIGHT(LEFT(D339,8)),1,0)))))) | W339: =IF(F339="","",IF(RIGHT(LEFT(F339,9))=".","B",IF(RIGHT(LEFT(F339,9))="*","M",IF(RIGHT(LEFT(D339,9))="Z",8,IF(RIGHT(LEFT(D339,9))="X",9,IF(RIGHT(LEFT(F339,9))=RIGHT(LEFT(D339,9)),1,0)))))) | X339: =IF(F339="","",IF(RIGHT(LEFT(F339,10))=".","B",IF(RIGHT(LEFT(F339,10))="*","M",IF(RIGHT(LEFT(D339,10))="Z",8,IF(RIGHT(LEFT(D339,10))="X",9,IF(RIGHT(LEFT(F339,10))=RIGHT(LEFT(D339,10)),1,0)))))) | Y339: =IF(F339="","",IF(RIGHT(LEFT(F339,11))=".","B",IF(RIGHT(LEFT(F339,11))="*","M",IF(RIGHT(LEFT(D339,11))="Z",8,IF(RIGHT(LEFT(D339,11))="X",9,IF(RIGHT(LEFT(F339,11))=RIGHT(LEFT(D339,11)),1,0)))))) | Z339: =IF(F339="","",IF(RIGHT(LEFT(F339,12))=".","B",IF(RIGHT(LEFT(F339,12))="*","M",IF(RIGHT(LEFT(D339,12))="Z",8,IF(RIGHT(LEFT(D339,12))="X",9,IF(RIGHT(LEFT(F339,12))=RIGHT(LEFT(D339,12)),1,0)))))) | AA339: =IF(F339="","",IF(RIGHT(LEFT(F339,13))=".","B",IF(RIGHT(LEFT(F339,13))="*","M",IF(RIGHT(LEFT(D339,13))="Z",8,IF(RIGHT(LEFT(D339,13))="X",9,IF(RIGHT(LEFT(F339,13))=RIGHT(LEFT(D339,13)),1,0)))))) | AB339: =IF(F339="","",IF(RIGHT(LEFT(F339,14))=".","B",IF(RIGHT(LEFT(F339,14))="*","M",IF(RIGHT(LEFT(D339,14))="Z",8,IF(RIGHT(LEFT(D339,14))="X",9,IF(RIGHT(LEFT(F339,14))=RIGHT(LEFT(D339,14)),1,0)))))) | AC339: =IF(F339="","",IF(RIGHT(LEFT(F339,15))=".","B",IF(RIGHT(LEFT(F339,15))="*","M",IF(RIGHT(LEFT(D339,15))="Z",8,IF(RIGHT(LEFT(D339,15))="X",9,IF(RIGHT(LEFT(F339,15))=RIGHT(LEFT(D339,15)),1,0)))))) | AD339: =IF(F339="","",IF(RIGHT(LEFT(F339,16))=".","B",IF(RIGHT(LEFT(F339,16))="*","M",IF(RIGHT(LEFT(D339,16))="Z",8,IF(RIGHT(LEFT(D339,16))="X",9,IF(RIGHT(LEFT(F339,16))=RIGHT(LEFT(D339,16)),1,0)))))) | AE339: =IF(F339="","",IF(RIGHT(LEFT(F339,17))=".","B",IF(RIGHT(LEFT(F339,17))="*","M",IF(RIGHT(LEFT(D339,17))="Z",8,IF(RIGHT(LEFT(D339,17))="X",9,IF(RIGHT(LEFT(F339,17))=RIGHT(LEFT(D339,17)),1,0)))))) | AF339: =IF(F339="","",IF(RIGHT(LEFT(F339,18))=".","B",IF(RIGHT(LEFT(F339,18))="*","M",IF(RIGHT(LEFT(D339,18))="Z",8,IF(RIGHT(LEFT(D339,18))="X",9,IF(RIGHT(LEFT(F339,18))=RIGHT(LEFT(D339,18)),1,0)))))) | AG339: =IF(F339="","",IF(RIGHT(LEFT(F339,19))=".","B",IF(RIGHT(LEFT(F339,19))="*","M",IF(RIGHT(LEFT(D339,19))="Z",8,IF(RIGHT(LEFT(D339,19))="X",9,IF(RIGHT(LEFT(F339,19))=RIGHT(LEFT(D339,19)),1,0)))))) | AH339: =IF(F339="","",IF(RIGHT(LEFT(F339,20))=".","B",IF(RIGHT(LEFT(F339,20))="*","M",IF(RIGHT(LEFT(D339,20))="Z",8,IF(RIGHT(LEFT(D339,20))="X",9,IF(RIGHT(LEFT(F339,20))=RIGHT(LEFT(D339,20)),1,0)))))) | AI339: =IF(F339="","",IF(RIGHT(LEFT(F339,21))=".","B",IF(RIGHT(LEFT(F339,21))="*","M",IF(RIGHT(LEFT(D339,21))="Z",8,IF(RIGHT(LEFT(D339,21))="X",9,IF(RIGHT(LEFT(F339,21))=RIGHT(LEFT(D339,21)),1,0)))))) | AJ339: =IF(F339="","",IF(RIGHT(LEFT(F339,22))=".","B",IF(RIGHT(LEFT(F339,22))="*","M",IF(RIGHT(LEFT(D339,22))="Z",8,IF(RIGHT(LEFT(D339,22))="X",9,IF(RIGHT(LEFT(F339,22))=RIGHT(LEFT(D339,22)),1,0)))))) | AK339: =IF(F339="","",IF(RIGHT(LEFT(F339,23))=".","B",IF(RIGHT(LEFT(F339,23))="*","M",IF(RIGHT(LEFT(D339,23))="Z",8,IF(RIGHT(LEFT(D339,23))="X",9,IF(RIGHT(LEFT(F339,23))=RIGHT(LEFT(D339,23)),1,0)))))) | AL339: =IF(F339="","",IF(RIGHT(LEFT(F339,24))=".","B",IF(RIGHT(LEFT(F339,24))="*","M",IF(RIGHT(LEFT(D339,24))="Z",8,IF(RIGHT(LEFT(D339,24))="X",9,IF(RIGHT(LEFT(F339,24))=RIGHT(LEFT(D339,24)),1,0)))))) | AM339: =IF(F339="","",IF(RIGHT(LEFT(F339,25))=".","B",IF(RIGHT(LEFT(F339,25))="*","M",IF(RIGHT(LEFT(D339,25))="Z",8,IF(RIGHT(LEFT(D339,25))="X",9,IF(RIGHT(LEFT(F339,25))=RIGHT(LEFT(D339,25)),1,0)))))) | AN339: =IF(F339="","",IF(RIGHT(LEFT(F339,26))=".","B",IF(RIGHT(LEFT(F339,26))="*","M",IF(RIGHT(LEFT(D339,26))="Z",8,IF(RIGHT(LEFT(D339,26))="X",9,IF(RIGHT(LEFT(F339,26))=RIGHT(LEFT(D339,26)),1,0)))))) | AO339: =IF(F339="","",IF(RIGHT(LEFT(F339,27))=".","B",IF(RIGHT(LEFT(F339,27))="*","M",IF(RIGHT(LEFT(D339,27))="Z",8,IF(RIGHT(LEFT(D339,27))="X",9,IF(RIGHT(LEFT(F339,27))=RIGHT(LEFT(D339,27)),1,0))))))
A340: 2019 | B340: 102499 | C340: ZDCBCCDB | D340: BXBCDXEBAAEDAABXECCCDXXCAAZ | G340: =IF(E340="","",IF(RIGHT(LEFT(E340,1))=".","B",IF(RIGHT(LEFT(E340,1))="*","M",IF(RIGHT(LEFT(C340,1))="Z",8,IF(RIGHT(LEFT(C340,1))="X",9,IF(RIGHT(LEFT(E340,1))=RIGHT(LEFT(C340,1)),1,0)))))) | H340: =IF(E340="","",IF(RIGHT(LEFT(E340,2))=".","B",IF(RIGHT(LEFT(E340,2))="*","M",IF(RIGHT(LEFT(C340,2))="Z",8,IF(RIGHT(LEFT(C340,2))="X",9,IF(RIGHT(LEFT(E340,2))=RIGHT(LEFT(C340,2)),1,0)))))) | I340: =IF(E340="","",IF(RIGHT(LEFT(E340,3))=".","B",IF(RIGHT(LEFT(E340,3))="*","M",IF(RIGHT(LEFT(C340,3))="Z",8,IF(RIGHT(LEFT(C340,3))="X",9,IF(RIGHT(LEFT(E340,3))=RIGHT(LEFT(C340,3)),1,0)))))) | J340: =IF(E340="","",IF(RIGHT(LEFT(E340,4))=".","B",IF(RIGHT(LEFT(E340,4))="*","M",IF(RIGHT(LEFT(C340,4))="Z",8,IF(RIGHT(LEFT(C340,4))="X",9,IF(RIGHT(LEFT(E340,4))=RIGHT(LEFT(C340,4)),1,0)))))) | K340: =IF(E340="","",IF(RIGHT(LEFT(E340,5))=".","B",IF(RIGHT(LEFT(E340,5))="*","M",IF(RIGHT(LEFT(C340,5))="Z",8,IF(RIGHT(LEFT(C340,5))="X",9,IF(RIGHT(LEFT(E340,5))=RIGHT(LEFT(C340,5)),1,0)))))) | L340: =IF(E340="","",IF(RIGHT(LEFT(E340,6))=".","B",IF(RIGHT(LEFT(E340,6))="*","M",IF(RIGHT(LEFT(C340,6))="Z",8,IF(RIGHT(LEFT(C340,6))="X",9,IF(RIGHT(LEFT(E340,6))=RIGHT(LEFT(C340,6)),1,0)))))) | M340: =IF(E340="","",IF(RIGHT(LEFT(E340,7))=".","B",IF(RIGHT(LEFT(E340,7))="*","M",IF(RIGHT(LEFT(C340,7))="Z",8,IF(RIGHT(LEFT(C340,7))="X",9,IF(RIGHT(LEFT(E340,7))=RIGHT(LEFT(C340,7)),1,0)))))) | N340: =IF(E340="","",IF(RIGHT(LEFT(E340,8))=".","B",IF(RIGHT(LEFT(E340,8))="*","M",IF(RIGHT(LEFT(C340,8))="Z",8,IF(RIGHT(LEFT(C340,8))="X",9,IF(RIGHT(LEFT(E340,8))=RIGHT(LEFT(C340,8)),1,0)))))) | O340: =IF(F340="","",IF(RIGHT(LEFT(F340,1))=".","B",IF(RIGHT(LEFT(F340,1))="*","M",IF(RIGHT(LEFT(D340,1))="Z",8,IF(RIGHT(LEFT(D340,1))="X",9,IF(RIGHT(LEFT(F340,1))=RIGHT(LEFT(D340,1)),1,0)))))) | P340: =IF(F340="","",IF(RIGHT(LEFT(F340,2))=".","B",IF(RIGHT(LEFT(F340,2))="*","M",IF(RIGHT(LEFT(D340,2))="Z",8,IF(RIGHT(LEFT(D340,2))="X",9,IF(RIGHT(LEFT(F340,2))=RIGHT(LEFT(D340,2)),1,0)))))) | Q340: =IF(F340="","",IF(RIGHT(LEFT(F340,3))=".","B",IF(RIGHT(LEFT(F340,3))="*","M",IF(RIGHT(LEFT(D340,3))="Z",8,IF(RIGHT(LEFT(D340,3))="X",9,IF(RIGHT(LEFT(F340,3))=RIGHT(LEFT(D340,3)),1,0)))))) | R340: =IF(F340="","",IF(RIGHT(LEFT(F340,4))=".","B",IF(RIGHT(LEFT(F340,4))="*","M",IF(RIGHT(LEFT(D340,4))="Z",8,IF(RIGHT(LEFT(D340,4))="X",9,IF(RIGHT(LEFT(F340,4))=RIGHT(LEFT(D340,4)),1,0)))))) | S340: =IF(F340="","",IF(RIGHT(LEFT(F340,5))=".","B",IF(RIGHT(LEFT(F340,5))="*","M",IF(RIGHT(LEFT(D340,5))="Z",8,IF(RIGHT(LEFT(D340,5))="X",9,IF(RIGHT(LEFT(F340,5))=RIGHT(LEFT(D340,5)),1,0)))))) | T340: =IF(F340="","",IF(RIGHT(LEFT(F340,6))=".","B",IF(RIGHT(LEFT(F340,6))="*","M",IF(RIGHT(LEFT(D340,6))="Z",8,IF(RIGHT(LEFT(D340,6))="X",9,IF(RIGHT(LEFT(F340,6))=RIGHT(LEFT(D340,6)),1,0)))))) | U340: =IF(F340="","",IF(RIGHT(LEFT(F340,7))=".","B",IF(RIGHT(LEFT(F340,7))="*","M",IF(RIGHT(LEFT(D340,7))="Z",8,IF(RIGHT(LEFT(D340,7))="X",9,IF(RIGHT(LEFT(F340,7))=RIGHT(LEFT(D340,7)),1,0)))))) | V340: =IF(F340="","",IF(RIGHT(LEFT(F340,8))=".","B",IF(RIGHT(LEFT(F340,8))="*","M",IF(RIGHT(LEFT(D340,8))="Z",8,IF(RIGHT(LEFT(D340,8))="X",9,IF(RIGHT(LEFT(F340,8))=RIGHT(LEFT(D340,8)),1,0)))))) | W340: =IF(F340="","",IF(RIGHT(LEFT(F340,9))=".","B",IF(RIGHT(LEFT(F340,9))="*","M",IF(RIGHT(LEFT(D340,9))="Z",8,IF(RIGHT(LEFT(D340,9))="X",9,IF(RIGHT(LEFT(F340,9))=RIGHT(LEFT(D340,9)),1,0)))))) | X340: =IF(F340="","",IF(RIGHT(LEFT(F340,10))=".","B",IF(RIGHT(LEFT(F340,10))="*","M",IF(RIGHT(LEFT(D340,10))="Z",8,IF(RIGHT(LEFT(D340,10))="X",9,IF(RIGHT(LEFT(F340,10))=RIGHT(LEFT(D340,10)),1,0)))))) | Y340: =IF(F340="","",IF(RIGHT(LEFT(F340,11))=".","B",IF(RIGHT(LEFT(F340,11))="*","M",IF(RIGHT(LEFT(D340,11))="Z",8,IF(RIGHT(LEFT(D340,11))="X",9,IF(RIGHT(LEFT(F340,11))=RIGHT(LEFT(D340,11)),1,0)))))) | Z340: =IF(F340="","",IF(RIGHT(LEFT(F340,12))=".","B",IF(RIGHT(LEFT(F340,12))="*","M",IF(RIGHT(LEFT(D340,12))="Z",8,IF(RIGHT(LEFT(D340,12))="X",9,IF(RIGHT(LEFT(F340,12))=RIGHT(LEFT(D340,12)),1,0)))))) | AA340: =IF(F340="","",IF(RIGHT(LEFT(F340,13))=".","B",IF(RIGHT(LEFT(F340,13))="*","M",IF(RIGHT(LEFT(D340,13))="Z",8,IF(RIGHT(LEFT(D340,13))="X",9,IF(RIGHT(LEFT(F340,13))=RIGHT(LEFT(D340,13)),1,0)))))) | AB340: =IF(F340="","",IF(RIGHT(LEFT(F340,14))=".","B",IF(RIGHT(LEFT(F340,14))="*","M",IF(RIGHT(LEFT(D340,14))="Z",8,IF(RIGHT(LEFT(D340,14))="X",9,IF(RIGHT(LEFT(F340,14))=RIGHT(LEFT(D340,14)),1,0)))))) | AC340: =IF(F340="","",IF(RIGHT(LEFT(F340,15))=".","B",IF(RIGHT(LEFT(F340,15))="*","M",IF(RIGHT(LEFT(D340,15))="Z",8,IF(RIGHT(LEFT(D340,15))="X",9,IF(RIGHT(LEFT(F340,15))=RIGHT(LEFT(D340,15)),1,0)))))) | AD340: =IF(F340="","",IF(RIGHT(LEFT(F340,16))=".","B",IF(RIGHT(LEFT(F340,16))="*","M",IF(RIGHT(LEFT(D340,16))="Z",8,IF(RIGHT(LEFT(D340,16))="X",9,IF(RIGHT(LEFT(F340,16))=RIGHT(LEFT(D340,16)),1,0)))))) | AE340: =IF(F340="","",IF(RIGHT(LEFT(F340,17))=".","B",IF(RIGHT(LEFT(F340,17))="*","M",IF(RIGHT(LEFT(D340,17))="Z",8,IF(RIGHT(LEFT(D340,17))="X",9,IF(RIGHT(LEFT(F340,17))=RIGHT(LEFT(D340,17)),1,0)))))) | AF340: =IF(F340="","",IF(RIGHT(LEFT(F340,18))=".","B",IF(RIGHT(LEFT(F340,18))="*","M",IF(RIGHT(LEFT(D340,18))="Z",8,IF(RIGHT(LEFT(D340,18))="X",9,IF(RIGHT(LEFT(F340,18))=RIGHT(LEFT(D340,18)),1,0)))))) | AG340: =IF(F340="","",IF(RIGHT(LEFT(F340,19))=".","B",IF(RIGHT(LEFT(F340,19))="*","M",IF(RIGHT(LEFT(D340,19))="Z",8,IF(RIGHT(LEFT(D340,19))="X",9,IF(RIGHT(LEFT(F340,19))=RIGHT(LEFT(D340,19)),1,0)))))) | AH340: =IF(F340="","",IF(RIGHT(LEFT(F340,20))=".","B",IF(RIGHT(LEFT(F340,20))="*","M",IF(RIGHT(LEFT(D340,20))="Z",8,IF(RIGHT(LEFT(D340,20))="X",9,IF(RIGHT(LEFT(F340,20))=RIGHT(LEFT(D340,20)),1,0)))))) | AI340: =IF(F340="","",IF(RIGHT(LEFT(F340,21))=".","B",IF(RIGHT(LEFT(F340,21))="*","M",IF(RIGHT(LEFT(D340,21))="Z",8,IF(RIGHT(LEFT(D340,21))="X",9,IF(RIGHT(LEFT(F340,21))=RIGHT(LEFT(D340,21)),1,0)))))) | AJ340: =IF(F340="","",IF(RIGHT(LEFT(F340,22))=".","B",IF(RIGHT(LEFT(F340,22))="*","M",IF(RIGHT(LEFT(D340,22))="Z",8,IF(RIGHT(LEFT(D340,22))="X",9,IF(RIGHT(LEFT(F340,22))=RIGHT(LEFT(D340,22)),1,0)))))) | AK340: =IF(F340="","",IF(RIGHT(LEFT(F340,23))=".","B",IF(RIGHT(LEFT(F340,23))="*","M",IF(RIGHT(LEFT(D340,23))="Z",8,IF(RIGHT(LEFT(D340,23))="X",9,IF(RIGHT(LEFT(F340,23))=RIGHT(LEFT(D340,23)),1,0)))))) | AL340: =IF(F340="","",IF(RIGHT(LEFT(F340,24))=".","B",IF(RIGHT(LEFT(F340,24))="*","M",IF(RIGHT(LEFT(D340,24))="Z",8,IF(RIGHT(LEFT(D340,24))="X",9,IF(RIGHT(LEFT(F340,24))=RIGHT(LEFT(D340,24)),1,0)))))) | AM340: =IF(F340="","",IF(RIGHT(LEFT(F340,25))=".","B",IF(RIGHT(LEFT(F340,25))="*","M",IF(RIGHT(LEFT(D340,25))="Z",8,IF(RIGHT(LEFT(D340,25))="X",9,IF(RIGHT(LEFT(F340,25))=RIGHT(LEFT(D340,25)),1,0)))))) | AN340: =IF(F340="","",IF(RIGHT(LEFT(F340,26))=".","B",IF(RIGHT(LEFT(F340,26))="*","M",IF(RIGHT(LEFT(D340,26))="Z",8,IF(RIGHT(LEFT(D340,26))="X",9,IF(RIGHT(LEFT(F340,26))=RIGHT(LEFT(D340,26)),1,0)))))) | AO340: =IF(F340="","",IF(RIGHT(LEFT(F340,27))=".","B",IF(RIGHT(LEFT(F340,27))="*","M",IF(RIGHT(LEFT(D340,27))="Z",8,IF(RIGHT(LEFT(D340,27))="X",9,IF(RIGHT(LEFT(F340,27))=RIGHT(LEFT(D340,27)),1,0))))))
A341: 2019 | B341: 102499 | C341: ZDCBCCDB | D341: BXBCDXEBAAEDAABXECCCDXXCAAZ | G341: =IF(E341="","",IF(RIGHT(LEFT(E341,1))=".","B",IF(RIGHT(LEFT(E341,1))="*","M",IF(RIGHT(LEFT(C341,1))="Z",8,IF(RIGHT(LEFT(C341,1))="X",9,IF(RIGHT(LEFT(E341,1))=RIGHT(LEFT(C341,1)),1,0)))))) | H341: =IF(E341="","",IF(RIGHT(LEFT(E341,2))=".","B",IF(RIGHT(LEFT(E341,2))="*","M",IF(RIGHT(LEFT(C341,2))="Z",8,IF(RIGHT(LEFT(C341,2))="X",9,IF(RIGHT(LEFT(E341,2))=RIGHT(LEFT(C341,2)),1,0)))))) | I341: =IF(E341="","",IF(RIGHT(LEFT(E341,3))=".","B",IF(RIGHT(LEFT(E341,3))="*","M",IF(RIGHT(LEFT(C341,3))="Z",8,IF(RIGHT(LEFT(C341,3))="X",9,IF(RIGHT(LEFT(E341,3))=RIGHT(LEFT(C341,3)),1,0)))))) | J341: =IF(E341="","",IF(RIGHT(LEFT(E341,4))=".","B",IF(RIGHT(LEFT(E341,4))="*","M",IF(RIGHT(LEFT(C341,4))="Z",8,IF(RIGHT(LEFT(C341,4))="X",9,IF(RIGHT(LEFT(E341,4))=RIGHT(LEFT(C341,4)),1,0)))))) | K341: =IF(E341="","",IF(RIGHT(LEFT(E341,5))=".","B",IF(RIGHT(LEFT(E341,5))="*","M",IF(RIGHT(LEFT(C341,5))="Z",8,IF(RIGHT(LEFT(C341,5))="X",9,IF(RIGHT(LEFT(E341,5))=RIGHT(LEFT(C341,5)),1,0)))))) | L341: =IF(E341="","",IF(RIGHT(LEFT(E341,6))=".","B",IF(RIGHT(LEFT(E341,6))="*","M",IF(RIGHT(LEFT(C341,6))="Z",8,IF(RIGHT(LEFT(C341,6))="X",9,IF(RIGHT(LEFT(E341,6))=RIGHT(LEFT(C341,6)),1,0)))))) | M341: =IF(E341="","",IF(RIGHT(LEFT(E341,7))=".","B",IF(RIGHT(LEFT(E341,7))="*","M",IF(RIGHT(LEFT(C341,7))="Z",8,IF(RIGHT(LEFT(C341,7))="X",9,IF(RIGHT(LEFT(E341,7))=RIGHT(LEFT(C341,7)),1,0)))))) | N341: =IF(E341="","",IF(RIGHT(LEFT(E341,8))=".","B",IF(RIGHT(LEFT(E341,8))="*","M",IF(RIGHT(LEFT(C341,8))="Z",8,IF(RIGHT(LEFT(C341,8))="X",9,IF(RIGHT(LEFT(E341,8))=RIGHT(LEFT(C341,8)),1,0)))))) | O341: =IF(F341="","",IF(RIGHT(LEFT(F341,1))=".","B",IF(RIGHT(LEFT(F341,1))="*","M",IF(RIGHT(LEFT(D341,1))="Z",8,IF(RIGHT(LEFT(D341,1))="X",9,IF(RIGHT(LEFT(F341,1))=RIGHT(LEFT(D341,1)),1,0)))))) | P341: =IF(F341="","",IF(RIGHT(LEFT(F341,2))=".","B",IF(RIGHT(LEFT(F341,2))="*","M",IF(RIGHT(LEFT(D341,2))="Z",8,IF(RIGHT(LEFT(D341,2))="X",9,IF(RIGHT(LEFT(F341,2))=RIGHT(LEFT(D341,2)),1,0)))))) | Q341: =IF(F341="","",IF(RIGHT(LEFT(F341,3))=".","B",IF(RIGHT(LEFT(F341,3))="*","M",IF(RIGHT(LEFT(D341,3))="Z",8,IF(RIGHT(LEFT(D341,3))="X",9,IF(RIGHT(LEFT(F341,3))=RIGHT(LEFT(D341,3)),1,0)))))) | R341: =IF(F341="","",IF(RIGHT(LEFT(F341,4))=".","B",IF(RIGHT(LEFT(F341,4))="*","M",IF(RIGHT(LEFT(D341,4))="Z",8,IF(RIGHT(LEFT(D341,4))="X",9,IF(RIGHT(LEFT(F341,4))=RIGHT(LEFT(D341,4)),1,0)))))) | S341: =IF(F341="","",IF(RIGHT(LEFT(F341,5))=".","B",IF(RIGHT(LEFT(F341,5))="*","M",IF(RIGHT(LEFT(D341,5))="Z",8,IF(RIGHT(LEFT(D341,5))="X",9,IF(RIGHT(LEFT(F341,5))=RIGHT(LEFT(D341,5)),1,0)))))) | T341: =IF(F341="","",IF(RIGHT(LEFT(F341,6))=".","B",IF(RIGHT(LEFT(F341,6))="*","M",IF(RIGHT(LEFT(D341,6))="Z",8,IF(RIGHT(LEFT(D341,6))="X",9,IF(RIGHT(LEFT(F341,6))=RIGHT(LEFT(D341,6)),1,0)))))) | U341: =IF(F341="","",IF(RIGHT(LEFT(F341,7))=".","B",IF(RIGHT(LEFT(F341,7))="*","M",IF(RIGHT(LEFT(D341,7))="Z",8,IF(RIGHT(LEFT(D341,7))="X",9,IF(RIGHT(LEFT(F341,7))=RIGHT(LEFT(D341,7)),1,0)))))) | V341: =IF(F341="","",IF(RIGHT(LEFT(F341,8))=".","B",IF(RIGHT(LEFT(F341,8))="*","M",IF(RIGHT(LEFT(D341,8))="Z",8,IF(RIGHT(LEFT(D341,8))="X",9,IF(RIGHT(LEFT(F341,8))=RIGHT(LEFT(D341,8)),1,0)))))) | W341: =IF(F341="","",IF(RIGHT(LEFT(F341,9))=".","B",IF(RIGHT(LEFT(F341,9))="*","M",IF(RIGHT(LEFT(D341,9))="Z",8,IF(RIGHT(LEFT(D341,9))="X",9,IF(RIGHT(LEFT(F341,9))=RIGHT(LEFT(D341,9)),1,0)))))) | X341: =IF(F341="","",IF(RIGHT(LEFT(F341,10))=".","B",IF(RIGHT(LEFT(F341,10))="*","M",IF(RIGHT(LEFT(D341,10))="Z",8,IF(RIGHT(LEFT(D341,10))="X",9,IF(RIGHT(LEFT(F341,10))=RIGHT(LEFT(D341,10)),1,0)))))) | Y341: =IF(F341="","",IF(RIGHT(LEFT(F341,11))=".","B",IF(RIGHT(LEFT(F341,11))="*","M",IF(RIGHT(LEFT(D341,11))="Z",8,IF(RIGHT(LEFT(D341,11))="X",9,IF(RIGHT(LEFT(F341,11))=RIGHT(LEFT(D341,11)),1,0)))))) | Z341: =IF(F341="","",IF(RIGHT(LEFT(F341,12))=".","B",IF(RIGHT(LEFT(F341,12))="*","M",IF(RIGHT(LEFT(D341,12))="Z",8,IF(RIGHT(LEFT(D341,12))="X",9,IF(RIGHT(LEFT(F341,12))=RIGHT(LEFT(D341,12)),1,0)))))) | AA341: =IF(F341="","",IF(RIGHT(LEFT(F341,13))=".","B",IF(RIGHT(LEFT(F341,13))="*","M",IF(RIGHT(LEFT(D341,13))="Z",8,IF(RIGHT(LEFT(D341,13))="X",9,IF(RIGHT(LEFT(F341,13))=RIGHT(LEFT(D341,13)),1,0)))))) | AB341: =IF(F341="","",IF(RIGHT(LEFT(F341,14))=".","B",IF(RIGHT(LEFT(F341,14))="*","M",IF(RIGHT(LEFT(D341,14))="Z",8,IF(RIGHT(LEFT(D341,14))="X",9,IF(RIGHT(LEFT(F341,14))=RIGHT(LEFT(D341,14)),1,0)))))) | AC341: =IF(F341="","",IF(RIGHT(LEFT(F341,15))=".","B",IF(RIGHT(LEFT(F341,15))="*","M",IF(RIGHT(LEFT(D341,15))="Z",8,IF(RIGHT(LEFT(D341,15))="X",9,IF(RIGHT(LEFT(F341,15))=RIGHT(LEFT(D341,15)),1,0)))))) | AD341: =IF(F341="","",IF(RIGHT(LEFT(F341,16))=".","B",IF(RIGHT(LEFT(F341,16))="*","M",IF(RIGHT(LEFT(D341,16))="Z",8,IF(RIGHT(LEFT(D341,16))="X",9,IF(RIGHT(LEFT(F341,16))=RIGHT(LEFT(D341,16)),1,0)))))) | AE341: =IF(F341="","",IF(RIGHT(LEFT(F341,17))=".","B",IF(RIGHT(LEFT(F341,17))="*","M",IF(RIGHT(LEFT(D341,17))="Z",8,IF(RIGHT(LEFT(D341,17))="X",9,IF(RIGHT(LEFT(F341,17))=RIGHT(LEFT(D341,17)),1,0)))))) | AF341: =IF(F341="","",IF(RIGHT(LEFT(F341,18))=".","B",IF(RIGHT(LEFT(F341,18))="*","M",IF(RIGHT(LEFT(D341,18))="Z",8,IF(RIGHT(LEFT(D341,18))="X",9,IF(RIGHT(LEFT(F341,18))=RIGHT(LEFT(D341,18)),1,0)))))) | AG341: =IF(F341="","",IF(RIGHT(LEFT(F341,19))=".","B",IF(RIGHT(LEFT(F341,19))="*","M",IF(RIGHT(LEFT(D341,19))="Z",8,IF(RIGHT(LEFT(D341,19))="X",9,IF(RIGHT(LEFT(F341,19))=RIGHT(LEFT(D341,19)),1,0)))))) | AH341: =IF(F341="","",IF(RIGHT(LEFT(F341,20))=".","B",IF(RIGHT(LEFT(F341,20))="*","M",IF(RIGHT(LEFT(D341,20))="Z",8,IF(RIGHT(LEFT(D341,20))="X",9,IF(RIGHT(LEFT(F341,20))=RIGHT(LEFT(D341,20)),1,0)))))) | AI341: =IF(F341="","",IF(RIGHT(LEFT(F341,21))=".","B",IF(RIGHT(LEFT(F341,21))="*","M",IF(RIGHT(LEFT(D341,21))="Z",8,IF(RIGHT(LEFT(D341,21))="X",9,IF(RIGHT(LEFT(F341,21))=RIGHT(LEFT(D341,21)),1,0)))))) | AJ341: =IF(F341="","",IF(RIGHT(LEFT(F341,22))=".","B",IF(RIGHT(LEFT(F341,22))="*","M",IF(RIGHT(LEFT(D341,22))="Z",8,IF(RIGHT(LEFT(D341,22))="X",9,IF(RIGHT(LEFT(F341,22))=RIGHT(LEFT(D341,22)),1,0)))))) | AK341: =IF(F341="","",IF(RIGHT(LEFT(F341,23))=".","B",IF(RIGHT(LEFT(F341,23))="*","M",IF(RIGHT(LEFT(D341,23))="Z",8,IF(RIGHT(LEFT(D341,23))="X",9,IF(RIGHT(LEFT(F341,23))=RIGHT(LEFT(D341,23)),1,0)))))) | AL341: =IF(F341="","",IF(RIGHT(LEFT(F341,24))=".","B",IF(RIGHT(LEFT(F341,24))="*","M",IF(RIGHT(LEFT(D341,24))="Z",8,IF(RIGHT(LEFT(D341,24))="X",9,IF(RIGHT(LEFT(F341,24))=RIGHT(LEFT(D341,24)),1,0)))))) | AM341: =IF(F341="","",IF(RIGHT(LEFT(F341,25))=".","B",IF(RIGHT(LEFT(F341,25))="*","M",IF(RIGHT(LEFT(D341,25))="Z",8,IF(RIGHT(LEFT(D341,25))="X",9,IF(RIGHT(LEFT(F341,25))=RIGHT(LEFT(D341,25)),1,0)))))) | AN341: =IF(F341="","",IF(RIGHT(LEFT(F341,26))=".","B",IF(RIGHT(LEFT(F341,26))="*","M",IF(RIGHT(LEFT(D341,26))="Z",8,IF(RIGHT(LEFT(D341,26))="X",9,IF(RIGHT(LEFT(F341,26))=RIGHT(LEFT(D341,26)),1,0)))))) | AO341: =IF(F341="","",IF(RIGHT(LEFT(F341,27))=".","B",IF(RIGHT(LEFT(F341,27))="*","M",IF(RIGHT(LEFT(D341,27))="Z",8,IF(RIGHT(LEFT(D341,27))="X",9,IF(RIGHT(LEFT(F341,27))=RIGHT(LEFT(D341,27)),1,0))))))
